Workbook

Sheet Instructions
A1: Palm Listed Companies — Long List Template
A2: Annual report → standardized long list with auto-scoring & validation
A4: 1. Raw Data Management
A5: Raw_Extract | B5: Every fact extracted from the annual report goes here first. One row = one data point.
A6: ├ Required fields | B6: Company / Source File / Page / Field Name / Extracted Value / Unit / Evidence Quote
A7: ├ Audit trail | B7: Extracted By / Date / Method (Manual·AI·OCR) / Reviewed By / Date
A8: └ Confidence | B8: High / Medium / Low — Low automatically flagged in Validation_Flags
A10: 2. Output Generation
A11: Company_Master | B11: Company-level qualitative info (HQ, ownership, deal thoughts, red flags).
A12: Asset_Operations | B12: Land, mills, production volumes. [auto] columns auto-calculate yield/OER/KER.
A13: Financials | B13: P&L, B/S, CF, market data. [auto] columns auto-calculate Net Debt, NWC, FCF, ratios.
A15: 3. Screening & Scoring
A16: Screening | B16: Pulls KPIs from 3 source sheets via XLOOKUP. 9 score columns auto-generated.
A17: Scoring_Criteria | B17: Threshold table — edit blue cells (D5:H13) to recalibrate all scores instantly.
A18: ├ Auto scores | B18: Scale, Asset Quality, Integration, Op Eff, Profit, Leverage, Liquidity (X~AD)
A19: ├ Manual scores | B19: ESG & Legality, Dealability (AE, AF) — enter 1~5 directly
A20: └ Total Score | B20: Simple average of all 9 scores (AG)
A22: 4. Validation
A23: Validation_Flags | B23: Manual issue log (rows 2~50) + automated rule output (rows 62+).
A24: └ Auto rules | B24: 11 rules: area sums, OER range/definition, Net Debt sign, B/S balance, EBITDA logic, EBITDA reported-vs-calculated, Net Debt reported-vs-calculated, Low confidence, etc.
A26: Color Conventions
A27: Blue text | B27: Manual input — value typed by analyst from the annual report
A28: Black text | B28: Formula — auto-calculated within the same sheet
A29: Green text | B29: Cross-sheet link — pulled from another sheet via XLOOKUP
A30: Yellow fill | B30: Key output (Total Score) — review before final ranking
A31: [auto] header | B31: Column is calculated; do not overwrite the formula
A33: Unit Conventions
A34: Land | B34: hectares (ha)
A35: Production | B35: tonnes (t); capacities in tph or tpa as headed
A36: Prices | B36: local currency per kg
A37: Financials | B37: IDR billion (bn) — convert if source is mn or USD
A38: Ratios | B38: decimal (0.25 = 25%) — formatted as % automatically
A40: Business Model Notes (P7)
A41: Upstream | B41: Plantation only (FFB → CPO). Apply all 9 scores fully.
A42: Integrated | B42: Plantation + downstream (e.g., AALI). Apply all 9 scores fully.
A43: Downstream | B43: Refining only (e.g., CBUT). Plantation-based scores (Scale, Asset Quality, Op Eff) will return blank — Total Score auto-excludes blank scores via AVERAGE.
A44: Other | B44: Trading, services, or hybrid. Use manual qualitative notes.
A46: Per-PDF Workflow (v1 update)
A47: Usage | B47: This template is intended to be copied PER annual report PDF. Each filled copy represents one company × one report year (one row in Company_Master, Asset_Operations, Financials).
A48: File Naming | B48: Save each filled copy in the relevant company folder as {TICKER}_{YEAR}_longlist.xlsx.
A49: Merging | B49: To build a master longlist, merge rows from all per-PDF files into a single workbook. When the same company has multiple years, Screening XLOOKUPs will pick the first matching row; if per-year Screening is needed, switch to composite-key lookups (Company + Report Year).
A51: Changes from v0 (baseline)
A52: OER range | B52: Validation rule R3 (OER range) widened from 18-25% to 15-27% to reduce false positives for small companies.
A53: Validation rows | B53: Validation_Summary now covers rows 5-204 (200 companies) instead of 5-34 (30 companies).
A54: Raw_Extract rows | B54: Raw_Extract capacity extended from 200 to 1000 facts (table A1:L1001, dropdowns D/J/L/O through row 1001).
A55: Report Year in Asset_Operations | B55: New column BG = Report Year. Use when merging multi-year data so operational rows can be distinguished by year.
A56: Report Year in Company_Master | B56: Column D renamed from "Latest Report Year" to "Report Year" for per-PDF clarity.

Sheet Raw_Extract
A1: Company | B1: Source File | C1: Report Year | D1: Field Group | E1: Field Name | F1: Extracted Value | G1: Unit | H1: Page | I1: Evidence Quote | J1: Confidence | K1: Normalization Note | L1: Validation Flag | M1: Extracted By | N1: Extracted Date | O1: Method | P1: Reviewed By | Q1: Reviewed Date
A2: PT Astra Agro Lestari Tbk | B2: AALI_2023_AR.pdf | C2: 2023 | D2: Company | E2: Company Name | F2: PT Astra Agro Lestari Tbk | G2: text | H2: 1 | I2: Cover | J2: High | M2: LLM | N2: 2026-04-18 | O2: AI
A3: PT Astra Agro Lestari Tbk | B3: AALI_2023_AR.pdf | C3: 2023 | D3: Company | E3: Ticker | F3: AALI | G3: text | I3: Filename | J3: High | M3: LLM | N3: 2026-04-18 | O3: AI
A4: PT Astra Agro Lestari Tbk | B4: AALI_2023_AR.pdf | C4: 2023 | D4: Company | E4: Report Year | F4: 2023 | G4: year | I4: Filename | J4: High | M4: LLM | N4: 2026-04-18 | O4: AI
A5: PT Astra Agro Lestari Tbk | B5: AALI_2023_AR.pdf | C5: 2023 | D5: Financial | E5: Revenue | F5: 20745 | G5: IDR bn | H5: 10 | I5: Pendapatan Bersih 20,745 (2023), Rp miliar (confirmed by p11 label) | J5: High | M5: LLM | N5: 2026-04-18 | O5: AI
A6: PT Astra Agro Lestari Tbk | B6: AALI_2023_AR.pdf | C6: 2023 | D6: Financial | E6: Gross Profit | F6: 2771 | G6: IDR bn | H6: 10 | I6: Laba Bruto 2,771 | J6: High | M6: LLM | N6: 2026-04-18 | O6: AI
A7: PT Astra Agro Lestari Tbk | B7: AALI_2023_AR.pdf | C7: 2023 | D7: Financial | E7: Net Profit | F7: 1088 | G7: IDR bn | H7: 10 | I7: Laba Tahun Berjalan 1,088 | J7: High | M7: LLM | N7: 2026-04-18 | O7: AI
A8: PT Astra Agro Lestari Tbk | B8: AALI_2023_AR.pdf | C8: 2023 | D8: Financial | E8: Profit Attributable to Parent | F8: 1056 | G8: IDR bn | H8: 10 | I8: - Pemilik Entitas Induk 1,056 | J8: High | M8: LLM | N8: 2026-04-18 | O8: AI
A9: PT Astra Agro Lestari Tbk | B9: AALI_2023_AR.pdf | C9: 2023 | D9: Financial | E9: Total Comprehensive Income | F9: 1136 | G9: IDR bn | H9: 10 | I9: Penghasilan Komprehensif Tahun Berjalan 1,136 | J9: High | M9: LLM | N9: 2026-04-18 | O9: AI
A10: PT Astra Agro Lestari Tbk | B10: AALI_2023_AR.pdf | C10: 2023 | D10: Financial | E10: Current Assets | F10: 7118 | G10: IDR bn | H10: 10 | I10: Aset Lancar 7,118 | J10: High | M10: LLM | N10: 2026-04-18 | O10: AI
A11: PT Astra Agro Lestari Tbk | B11: AALI_2023_AR.pdf | C11: 2023 | D11: Financial | E11: Non-Current Assets | F11: 21728 | G11: IDR bn | H11: 10 | I11: Aset Tidak Lancar 21,728 | J11: High | M11: LLM | N11: 2026-04-18 | O11: AI
A12: PT Astra Agro Lestari Tbk | B12: AALI_2023_AR.pdf | C12: 2023 | D12: Financial | E12: Total Assets | F12: 28846 | G12: IDR bn | H12: 10 | I12: Total Aset 28,846 | J12: High | M12: LLM | N12: 2026-04-18 | O12: AI
A13: PT Astra Agro Lestari Tbk | B13: AALI_2023_AR.pdf | C13: 2023 | D13: Financial | E13: Current Liabilities | F13: 3882 | G13: IDR bn | H13: 10 | I13: Liabilitas Jangka Pendek 3,882 | J13: High | M13: LLM | N13: 2026-04-18 | O13: AI
A14: PT Astra Agro Lestari Tbk | B14: AALI_2023_AR.pdf | C14: 2023 | D14: Financial | E14: Long-Term Liabilities | F14: 2398 | G14: IDR bn | H14: 10 | I14: Liabilitas Jangka Panjang 2,398 | J14: High | M14: LLM | N14: 2026-04-18 | O14: AI
A15: PT Astra Agro Lestari Tbk | B15: AALI_2023_AR.pdf | C15: 2023 | D15: Financial | E15: Total Liabilities | F15: 6280 | G15: IDR bn | H15: 10 | I15: Total Liabilitas 6,280 | J15: High | M15: LLM | N15: 2026-04-18 | O15: AI
A16: PT Astra Agro Lestari Tbk | B16: AALI_2023_AR.pdf | C16: 2023 | D16: Financial | E16: Total Equity | F16: 22566 | G16: IDR bn | H16: 10 | I16: Total Ekuitas 22,566 | J16: High | M16: LLM | N16: 2026-04-18 | O16: AI
... A67: PT Astra Agro Lestari Tbk | B67: AALI_2023_AR.pdf | C67: 2023 | D67: Operation | E67: CPO Sales Volume | F67: 2345000 | G67: t | H67: 14 | I67: Volume Penjualan CPO dan Turunannya 2,345 ribu ton | J67: High | M67: LLM | N67: 2026-04-18 | O67: AI
A68: PT Astra Agro Lestari Tbk | B68: AALI_2024_AR.pdf | C68: 2024 | D68: Company | E68: Company Name | F68: PT Astra Agro Lestari Tbk | G68: text | H68: 12 | I68: Laporan Tahunan 2024 - PT Astra Agro Lestari Tbk | J68: High | M68: LLM | N68: 2026-04-18 | O68: AI
A69: PT Astra Agro Lestari Tbk | B69: AALI_2024_AR.pdf | C69: 2024 | D69: Company | E69: Controlling Shareholder | F69: PT Astra International Tbk 79.68% | G69: % | H69: 83 | I69: PT Astra International Tbk 1,533,682,440 79.68% | J69: High | M69: LLM | N69: 2026-04-18 | O69: AI
A70: PT Astra Agro Lestari Tbk | B70: AALI_2024_AR.pdf | C70: 2024 | D70: Company | E70: Public Float | F70: 0.2032 | G70: % | H70: 83 | I70: Masyarakat Lainnya (masing-masing di bawah 5%) 391,005,893 20.32% | J70: High | M70: LLM | N70: 2026-04-18 | O70: AI
A71: PT Astra Agro Lestari Tbk | B71: AALI_2024_AR.pdf | C71: 2024 | D71: Financial | E71: Revenue (Net) | F71: 21815 | G71: IDR bn | H71: 12 | I71: Pendapatan Bersih 21,815 20,745 21,829 | J71: High | M71: LLM | N71: 2026-04-18 | O71: AI
A72: PT Astra Agro Lestari Tbk | B72: AALI_2024_AR.pdf | C72: 2024 | D72: Financial | E72: Gross Profit | F72: 3341 | G72: IDR bn | H72: 12 | I72: Laba Bruto 3,341 2,771 3,822 | J72: High | M72: LLM | N72: 2026-04-18 | O72: AI
A73: PT Astra Agro Lestari Tbk | B73: AALI_2024_AR.pdf | C73: 2024 | D73: Financial | E73: Cost of Revenue | F73: 18474 | G73: IDR bn | H73: 108 | I73: Beban Pokok Pendapatan (18,474.41) (17,974.49) | J73: High | M73: LLM | N73: 2026-04-18 | O73: AI
A74: PT Astra Agro Lestari Tbk | B74: AALI_2024_AR.pdf | C74: 2024 | D74: Financial | E74: Operating Expense | F74: 1682 | G74: IDR bn | H74: 108 | I74: Beban Usaha (1,682.14) (1,519.77) | J74: High | M74: LLM | N74: 2026-04-18 | O74: AI
A75: PT Astra Agro Lestari Tbk | B75: AALI_2024_AR.pdf | C75: 2024 | D75: Financial | E75: EBIT (Gross Profit - OpEx) | F75: 1658 | G75: IDR bn | H75: 108 | I75: Calculated: Gross Profit 3,340.62 - OpEx 1,682.14 = 1,658.48 | J75: Medium | M75: LLM | N75: 2026-04-18 | O75: AI
A76: PT Astra Agro Lestari Tbk | B76: AALI_2024_AR.pdf | C76: 2024 | D76: Financial | E76: Finance Cost | F76: 265 | G76: IDR bn | H76: 108 | I76: Biaya Pendanaan (264.69) (268.26) | J76: High | M76: LLM | N76: 2026-04-18 | O76: AI
A77: PT Astra Agro Lestari Tbk | B77: AALI_2024_AR.pdf | C77: 2024 | D77: Financial | E77: Profit Before Income Tax | F77: 1707 | G77: IDR bn | H77: 108 | I77: Laba Sebelum Pajak Penghasilan 1,707.13 1,498.40 | J77: High | M77: LLM | N77: 2026-04-18 | O77: AI
A78: PT Astra Agro Lestari Tbk | B78: AALI_2024_AR.pdf | C78: 2024 | D78: Financial | E78: Net Profit | F78: 1187 | G78: IDR bn | H78: 12 | I78: Laba Tahun Berjalan 1,187 1,088 | J78: High | M78: LLM | N78: 2026-04-18 | O78: AI
A79: PT Astra Agro Lestari Tbk | B79: AALI_2024_AR.pdf | C79: 2024 | D79: Financial | E79: Profit Attributable to Parent | F79: 1148 | G79: IDR bn | H79: 12 | I79: Pemilik Entitas Induk 1,148 1,056 | J79: High | M79: LLM | N79: 2026-04-18 | O79: AI
A80: PT Astra Agro Lestari Tbk | B80: AALI_2024_AR.pdf | C80: 2024 | D80: Financial | E80: Total Assets | F80: 28793 | G80: IDR bn | H80: 12 | I80: Total Aset 28,793 28,846 | J80: High | M80: LLM | N80: 2026-04-18 | O80: AI
A81: PT Astra Agro Lestari Tbk | B81: AALI_2024_AR.pdf | C81: 2024 | D81: Financial | E81: Current Assets | F81: 8434 | G81: IDR bn | H81: 12 | I81: Aset Lancar 8,434 7,118 | J81: High | M81: LLM | N81: 2026-04-18 | O81: AI
... A144: PT Astra Agro Lestari Tbk | B144: AALI_2024_AR.pdf | C144: 2024 | D144: ESG | E144: PROPER Blue Certifications | F144: 26 | G144: count | H144: 105 | I144: Perseroan telah meraih sertifikasi PROPER Biru sebanyak 26 sertifikasi | J144: High | M144: LLM | N144: 2026-04-18 | O144: AI
A145: PT Astra Agro Lestari Tbk | B145: AALI_2025_AR.pdf | C145: 2025 | D145: Company | E145: Company Name | F145: PT Astra Agro Lestari Tbk | G145: text | H145: 15 | I145: Laporan Tahunan 2025 | PT Astra Agro Lestari Tbk | J145: High | M145: LLM | N145: 2026-04-18 | O145: AI
A146: PT Astra Agro Lestari Tbk | B146: AALI_2025_AR.pdf | C146: 2025 | D146: Financial | E146: Revenue (Net) | F146: 28655 | G146: IDR bn | H146: 15 | I146: Pendapatan Bersih 28,655 21,815 | J146: High | M146: LLM | N146: 2026-04-18 | O146: AI
A147: PT Astra Agro Lestari Tbk | B147: AALI_2025_AR.pdf | C147: 2025 | D147: Financial | E147: Cost of Revenue | F147: 24023 | G147: IDR bn | H147: 131 | I147: Beban Pokok Pendapatan (24,023.22) (18,474.41) | J147: High | M147: LLM | N147: 2026-04-18 | O147: AI
A148: PT Astra Agro Lestari Tbk | B148: AALI_2025_AR.pdf | C148: 2025 | D148: Financial | E148: Gross Profit | F148: 4631 | G148: IDR bn | H148: 15 | I148: Laba Bruto 4,631 3,341 | J148: High | M148: LLM | N148: 2026-04-18 | O148: AI
A149: PT Astra Agro Lestari Tbk | B149: AALI_2025_AR.pdf | C149: 2025 | D149: Financial | E149: Operating Expense | F149: 2214 | G149: IDR bn | H149: 131 | I149: Beban Usaha (2,214.37) (1,682.14) | J149: High | M149: LLM | N149: 2026-04-18 | O149: AI
A150: PT Astra Agro Lestari Tbk | B150: AALI_2025_AR.pdf | C150: 2025 | D150: Financial | E150: EBIT (Gross - OpEx) | F150: 2417 | G150: IDR bn | H150: 131 | I150: Calculated: 4,631.43 - 2,214.37 = 2,417.06 | J150: Medium | M150: LLM | N150: 2026-04-18 | O150: AI
A151: PT Astra Agro Lestari Tbk | B151: AALI_2025_AR.pdf | C151: 2025 | D151: Financial | E151: Finance Cost | F151: 139 | G151: IDR bn | H151: 131 | I151: Biaya Pendanaan (139.26) (264.69) | J151: High | M151: LLM | N151: 2026-04-18 | O151: AI
A152: PT Astra Agro Lestari Tbk | B152: AALI_2025_AR.pdf | C152: 2025 | D152: Financial | E152: Interest Income | F152: 280 | G152: IDR bn | H152: 131 | I152: Penghasilan Bunga 279.79 211.50 | J152: High | M152: LLM | N152: 2026-04-18 | O152: AI
A153: PT Astra Agro Lestari Tbk | B153: AALI_2025_AR.pdf | C153: 2025 | D153: Financial | E153: Profit Before Tax | F153: 2227 | G153: IDR bn | H153: 131 | I153: Laba Sebelum Pajak Penghasilan 2,226.73 1,707.13 | J153: High | M153: LLM | N153: 2026-04-18 | O153: AI
A154: PT Astra Agro Lestari Tbk | B154: AALI_2025_AR.pdf | C154: 2025 | D154: Financial | E154: Income Tax Expense | F154: 689 | G154: IDR bn | H154: 131 | I154: Beban Pajak Penghasilan (689.10) (520.35) | J154: High | M154: LLM | N154: 2026-04-18 | O154: AI
A155: PT Astra Agro Lestari Tbk | B155: AALI_2025_AR.pdf | C155: 2025 | D155: Financial | E155: Net Profit | F155: 1538 | G155: IDR bn | H155: 15 | I155: Laba Tahun Berjalan 1,538 1,187 | J155: High | M155: LLM | N155: 2026-04-18 | O155: AI
A156: PT Astra Agro Lestari Tbk | B156: AALI_2025_AR.pdf | C156: 2025 | D156: Financial | E156: Profit Attributable to Parent | F156: 1472 | G156: IDR bn | H156: 15 | I156: Pemilik Entitas Induk 1,472 1,148 | J156: High | M156: LLM | N156: 2026-04-18 | O156: AI
A157: PT Astra Agro Lestari Tbk | B157: AALI_2025_AR.pdf | C157: 2025 | D157: Financial | E157: Total Assets | F157: 27047 | G157: IDR bn | H157: 15 | I157: Total Aset 27,047 28,793 | J157: High | M157: LLM | N157: 2026-04-18 | O157: AI
... A216: PT Astra Agro Lestari Tbk | B216: AALI_2025_AR.pdf | C216: 2025 | D216: Operation | E216: Export Sales Proportion | F216: 0.36 | G216: % | H216: 124 | I216: 64% untuk pasar domestik dan 36% untuk ekspor | J216: High | M216: LLM | N216: 2026-04-18 | O216: AI
A217: PT Andira Agro Tbk | B217: ANDI_2022_AR.pdf | C217: 2022 | D217: Company | E217: Company Name | F217: PT Andira Agro Tbk | G217: text | H217: 36 | I217: PT Andira Agro Tbk (Perseroan) merupakan perusahaan terbuka | J217: High | M217: LLM | N217: 2026-04-18 | O217: AI
A218: PT Andira Agro Tbk | B218: ANDI_2022_AR.pdf | C218: 2022 | D218: Company | E218: Ticker | F218: ANDI | G218: text | H218: 36 | I218: Kode Saham/Stock Code: ANDI | J218: High | M218: LLM | N218: 2026-04-18 | O218: AI
A219: PT Andira Agro Tbk | B219: ANDI_2022_AR.pdf | C219: 2022 | D219: Company | E219: IDX Listing Date | F219: 16-Aug-2018 | G219: date | H219: 37 | I219: Pencatatan di BEI: 16 Agustus 2018 | J219: High | M219: LLM | N219: 2026-04-18 | O219: AI
A220: PT Andira Agro Tbk | B220: ANDI_2022_AR.pdf | C220: 2022 | D220: Company | E220: Headquarters | F220: Meta Epsi Building, Jl. Mayjen D.I. Panjaitan Kav.2, Jakarta Timur | G220: text | H220: 37 | I220: Meta Epsi Building - Jl. Mayjen D.I. Panjaitan Kav.2 Jakarta Timur | J220: High | M220: LLM | N220: 2026-04-18 | O220: AI
A221: PT Andira Agro Tbk | B221: ANDI_2022_AR.pdf | C221: 2022 | D221: Company | E221: Operations Location | F221: Banyuasin, South Sumatra | G221: text | H221: 36 | I221: Wilayah operasional Perseroan terletak di Kabupaten Banyuasin, Provinsi Sumatera Selatan | J221: High | M221: LLM | N221: 2026-04-18 | O221: AI
A222: PT Andira Agro Tbk | B222: ANDI_2022_AR.pdf | C222: 2022 | D222: Company | E222: PT Central Energi Pratama (controlling) | F222: 0.4973 | G222: % | H222: 53 | I222: PT. Central Energi Pratama 4,650,030,000 49.73% | J222: High | M222: LLM | N222: 2026-04-18 | O222: AI
A223: PT Andira Agro Tbk | B223: ANDI_2022_AR.pdf | C223: 2022 | D223: Company | E223: PT Anugerah Perkasa Semesta | F223: 0.0749 | G223: % | H223: 53 | I223: PT. Anugerah Perkasa Semesta 699,970,000 7.49% | J223: High | M223: LLM | N223: 2026-04-18 | O223: AI
A224: PT Andira Agro Tbk | B224: ANDI_2022_AR.pdf | C224: 2022 | D224: Company | E224: Kejaksaan Agung (Attorney General) | F224: 0.0607 | G224: % | H224: 53 | I224: Kejaksaan Agung 567,409,200 6.07% | J224: High | M224: LLM | N224: 2026-04-18 | O224: AI
A225: PT Andira Agro Tbk | B225: ANDI_2022_AR.pdf | C225: 2022 | D225: Company | E225: Public | F225: 0.3671 | G225: % | H225: 53 | I225: Masyarakat 3,432,590,800 36.71% | J225: High | M225: LLM | N225: 2026-04-18 | O225: AI
A226: PT Andira Agro Tbk | B226: ANDI_2022_AR.pdf | C226: 2022 | D226: Financial | E226: Net Sales | F226: 317.86 | G226: IDR bn | H226: 13 | I226: Penjualan Bersih 317,855,645,702 346,364,995,418 (Rupiah) | J226: High | M226: LLM | N226: 2026-04-18 | O226: AI
A227: PT Andira Agro Tbk | B227: ANDI_2022_AR.pdf | C227: 2022 | D227: Financial | E227: CPO Sales | F227: 269.46 | G227: IDR bn | H227: 75 | I227: Minyak mentah kelapa sawit 269,464,126,132 296,074,022,293 | J227: High | M227: LLM | N227: 2026-04-18 | O227: AI
A228: PT Andira Agro Tbk | B228: ANDI_2022_AR.pdf | C228: 2022 | D228: Financial | E228: PK Sales | F228: 48.39 | G228: IDR bn | H228: 75 | I228: Inti sawit 48,391,519,570 50,290,973,125 | J228: High | M228: LLM | N228: 2026-04-18 | O228: AI
A229: PT Andira Agro Tbk | B229: ANDI_2022_AR.pdf | C229: 2022 | D229: Financial | E229: Cost of Goods Sold | F229: 295.08 | G229: IDR bn | H229: 13 | I229: Beban Pokok Penjualan (295,077,013,708) | J229: High | M229: LLM | N229: 2026-04-18 | O229: AI
A230: PT Andira Agro Tbk | B230: ANDI_2022_AR.pdf | C230: 2022 | D230: Financial | E230: Gross Profit | F230: 22.78 | G230: IDR bn | H230: 13 | I230: Laba Bruto 22,778,631,994 | J230: High | M230: LLM | N230: 2026-04-18 | O230: AI
A231: PT Andira Agro Tbk | B231: ANDI_2022_AR.pdf | C231: 2022 | D231: Financial | E231: Operating Income/(Loss) | F231: -10.54 | G231: IDR bn | H231: 13 | I231: Laba (Rugi) Usaha (10,540,607,940) | J231: High | M231: LLM | N231: 2026-04-18 | O231: AI
A232: PT Andira Agro Tbk | B232: ANDI_2022_AR.pdf | C232: 2022 | D232: Financial | E232: Interest Expense | F232: 14.97 | G232: IDR bn | H232: 77 | I232: Beban Bunga (14,969,816,054) (15,192,038,239) | J232: High | M232: LLM | N232: 2026-04-18 | O232: AI
A233: PT Andira Agro Tbk | B233: ANDI_2022_AR.pdf | C233: 2022 | D233: Financial | E233: Loss Before Tax | F233: -12 | G233: IDR bn | H233: 13 | I233: Rugi Sebelum Pajak Penghasilan (12,004,143,654) | J233: High | M233: LLM | N233: 2026-04-18 | O233: AI
... A267: PT Andira Agro Tbk | B267: ANDI_2022_AR.pdf | C267: 2022 | D267: Operation | E267: FFB Processed 2021 (prior year) | F267: 146124 | G267: t | H267: 74 | I267: TBS olah pada tahun 2021 sebesar 146,124 ton | J267: High | M267: LLM | N267: 2026-04-18 | O267: AI
A268: PT Andira Agro Tbk | B268: ANDI_2022_AR.pdf | C268: 2022 | D268: ESG | E268: ISPO Certification | F268: Certified (MISB) | G268: text | H268: 17 | I268: ISPO (Indonesia Sustainable Palm Oil) certification by PT Mutu Indonesia Strategis Berkelanjutan | J268: High | M268: LLM | N268: 2026-04-18 | O268: AI
A269: PT Andira Agro Tbk | B269: ANDI_2022_AR.pdf | C269: 2022 | D269: ESG | E269: GAPKI Membership | F269: Member | G269: text | H269: 17 | I269: Gabungan Pengusaha Kelapa Sawit Indonesia (GAPKI) - sebagai anggota | J269: High | M269: LLM | N269: 2026-04-18 | O269: AI
A270: PT Andira Agro Tbk | B270: ANDI_2022_AR.pdf | C270: 2022 | D270: Company | E270: Total Headcount | F270: 121 | G270: count | H270: 38 | I270: Jumlah Karyawan 121 orang/people 163 163 | J270: High | M270: LLM | N270: 2026-04-18 | O270: AI
A271: PT Andira Agro Tbk | B271: ANDI_2023_AR.pdf | C271: 2023 | D271: Company | E271: Company Name | F271: PT Andira Agro Tbk | G271: text | H271: 1 | I271: PT Andira Agro Tbk | J271: High | M271: LLM | N271: 2026-04-18 | O271: AI
A272: PT Andira Agro Tbk | B272: ANDI_2023_AR.pdf | C272: 2023 | D272: Company | E272: Ticker | F272: ANDI | G272: text | H272: 11 | I272: IDX code ANDI | J272: High | M272: LLM | N272: 2026-04-18 | O272: AI
A273: PT Andira Agro Tbk | B273: ANDI_2023_AR.pdf | C273: 2023 | D273: Financial | E273: Net Sales | F273: 219.94 | G273: IDR bn | H273: 11 | I273: PENJUALAN BERSIH 219,942,382,085 317,855,645,702 | J273: High | M273: LLM | N273: 2026-04-18 | O273: AI
A274: PT Andira Agro Tbk | B274: ANDI_2023_AR.pdf | C274: 2023 | D274: Financial | E274: CPO Sales | F274: 195.16 | G274: IDR bn | H274: 79 | I274: Minyak mentah kelapa sawit 195,160,663,545 269,464,126,132 | J274: High | M274: LLM | N274: 2026-04-18 | O274: AI
A275: PT Andira Agro Tbk | B275: ANDI_2023_AR.pdf | C275: 2023 | D275: Financial | E275: Kernel Sales | F275: 24.78 | G275: IDR bn | H275: 79 | I275: Inti sawit 24,781,718,540 48,391,519,570 | J275: High | M275: LLM | N275: 2026-04-18 | O275: AI
A276: PT Andira Agro Tbk | B276: ANDI_2023_AR.pdf | C276: 2023 | D276: Financial | E276: Gross Profit | F276: 0.22 | G276: IDR bn | H276: 11 | I276: LABA BRUTO 223,757,049 22,778,631,994 | J276: High | M276: LLM | N276: 2026-04-18 | O276: AI
A277: PT Andira Agro Tbk | B277: ANDI_2023_AR.pdf | C277: 2023 | D277: Financial | E277: Operating Loss | F277: -63.1 | G277: IDR bn | H277: 11 | I277: LABA (RUGI) USAHA (63,098,260,750) (10,540,607,940) | J277: High | M277: LLM | N277: 2026-04-18 | O277: AI
A278: PT Andira Agro Tbk | B278: ANDI_2023_AR.pdf | C278: 2023 | D278: Financial | E278: Net Loss | F278: -55.96 | G278: IDR bn | H278: 11 | I278: RUGI TAHUN BERJALAN (55,959,237,094) (10,787,670,426) | J278: High | M278: LLM | N278: 2026-04-18 | O278: AI
A279: PT Andira Agro Tbk | B279: ANDI_2023_AR.pdf | C279: 2023 | D279: Financial | E279: Comprehensive Loss | F279: -55.95 | G279: IDR bn | H279: 11 | I279: JUMLAH RUGI KOMPREHENSIF (55,954,565,186) | J279: High | M279: LLM | N279: 2026-04-18 | O279: AI
A280: PT Andira Agro Tbk | B280: ANDI_2023_AR.pdf | C280: 2023 | D280: Financial | E280: Total Assets | F280: 378.14 | G280: IDR bn | H280: 11 | I280: Total Aset 378,135,050,642 444,210,370,402 | J280: High | M280: LLM | N280: 2026-04-18 | O280: AI
A281: PT Andira Agro Tbk | B281: ANDI_2023_AR.pdf | C281: 2023 | D281: Financial | E281: Current Assets | F281: 24.21 | G281: IDR bn | H281: 11 | I281: Aset Lancar 24,214,366,203 77,817,661,367 | J281: High | M281: LLM | N281: 2026-04-18 | O281: AI
A282: PT Andira Agro Tbk | B282: ANDI_2023_AR.pdf | C282: 2023 | D282: Financial | E282: Non-Current Assets | F282: 353.92 | G282: IDR bn | H282: 11 | I282: Aset Tidak Lancar 353,920,684,439 | J282: High | M282: LLM | N282: 2026-04-18 | O282: AI
A283: PT Andira Agro Tbk | B283: ANDI_2023_AR.pdf | C283: 2023 | D283: Financial | E283: Total Liabilities | F283: 195.4 | G283: IDR bn | H283: 11 | I283: Total Liabilitas 195,395,707,177 | J283: High | M283: LLM | N283: 2026-04-18 | O283: AI
A284: PT Andira Agro Tbk | B284: ANDI_2023_AR.pdf | C284: 2023 | D284: Financial | E284: Current Liabilities | F284: 41.92 | G284: IDR bn | H284: 11 | I284: Liabilitas Jangka Pendek 41,923,858,695 | J284: High | M284: LLM | N284: 2026-04-18 | O284: AI
... A310: PT Andira Agro Tbk | B310: ANDI_2023_AR.pdf | C310: 2023 | D310: Company | E310: Public Float | F310: 0.3671 | G310: % | H310: 57 | I310: Masyarakat 3,432,590,800 36.71% | J310: High | M310: LLM | N310: 2026-04-18 | O310: AI
A311: PT Andira Agro Tbk | B311: ANDI_2023_AR.pdf | C311: 2023 | D311: ESG | E311: ISPO Certification | F311: Certified | G311: text | H311: 15 | I311: ISPO certification | J311: High | M311: LLM | N311: 2026-04-18 | O311: AI
A312: PT Andira Agro Tbk | B312: ANDI_2024_AR.pdf | C312: 2024 | D312: Company | E312: Company Name | F312: PT Andira Agro Tbk | G312: text | H312: 11 | I312: Annual & Sustainability Report 2024 - PT Andira Agro Tbk | J312: High | M312: LLM | N312: 2026-04-18 | O312: AI
A313: PT Andira Agro Tbk | B313: ANDI_2024_AR.pdf | C313: 2024 | D313: Financial | E313: Net Sales | F313: 196.74 | G313: IDR bn | H313: 11 | I313: PENJUALAN BERSIH 196,741,616,114 219,942,382,085 | J313: High | M313: LLM | N313: 2026-04-18 | O313: AI
A314: PT Andira Agro Tbk | B314: ANDI_2024_AR.pdf | C314: 2024 | D314: Financial | E314: CPO Sales | F314: 166.56 | G314: IDR bn | H314: 86 | I314: Minyak mentah kelapa sawit 166,560,755,325 195,160,663,545 | J314: High | M314: LLM | N314: 2026-04-18 | O314: AI
A315: PT Andira Agro Tbk | B315: ANDI_2024_AR.pdf | C315: 2024 | D315: Financial | E315: Palm Kernel Sales | F315: 29.94 | G315: IDR bn | H315: 86 | I315: Inti sawit 29,944,599,527 24,781,718,540 | J315: High | M315: LLM | N315: 2026-04-18 | O315: AI
A316: PT Andira Agro Tbk | B316: ANDI_2024_AR.pdf | C316: 2024 | D316: Financial | E316: Shell Sales | F316: 0.24 | G316: IDR bn | H316: 86 | I316: Cangkang 236,261,262 - (new product) | J316: High | M316: LLM | N316: 2026-04-18 | O316: AI
A317: PT Andira Agro Tbk | B317: ANDI_2024_AR.pdf | C317: 2024 | D317: Financial | E317: Gross Profit (Loss) | F317: -11.96 | G317: IDR bn | H317: 11 | I317: LABA BRUTO (11,961,251,357) 223,757,049 | J317: High | M317: LLM | N317: 2026-04-18 | O317: AI
A318: PT Andira Agro Tbk | B318: ANDI_2024_AR.pdf | C318: 2024 | D318: Financial | E318: Operating Loss | F318: -34.61 | G318: IDR bn | H318: 11 | I318: LABA (RUGI) USAHA (34,607,531,181) (63,098,260,750) | J318: High | M318: LLM | N318: 2026-04-18 | O318: AI
A319: PT Andira Agro Tbk | B319: ANDI_2024_AR.pdf | C319: 2024 | D319: Financial | E319: Net Loss | F319: -23.05 | G319: IDR bn | H319: 11 | I319: RUGI TAHUN BERJALAN (23,050,071,071) (55,959,237,094) | J319: High | M319: LLM | N319: 2026-04-18 | O319: AI
A320: PT Andira Agro Tbk | B320: ANDI_2024_AR.pdf | C320: 2024 | D320: Financial | E320: Total Assets | F320: 350.16 | G320: IDR bn | H320: 11 | I320: Total Aset 350,160,565,915 378,135,050,642 | J320: High | M320: LLM | N320: 2026-04-18 | O320: AI
A321: PT Andira Agro Tbk | B321: ANDI_2024_AR.pdf | C321: 2024 | D321: Financial | E321: Current Assets | F321: 38.49 | G321: IDR bn | H321: 11 | I321: Aset Lancar 38,490,927,187 24,214,366,203 | J321: High | M321: LLM | N321: 2026-04-18 | O321: AI
A322: PT Andira Agro Tbk | B322: ANDI_2024_AR.pdf | C322: 2024 | D322: Financial | E322: Non-Current Assets | F322: 311.67 | G322: IDR bn | H322: 11 | I322: Aset Tidak Lancar 311,669,638,728 353,920,684,439 | J322: High | M322: LLM | N322: 2026-04-18 | O322: AI
A323: PT Andira Agro Tbk | B323: ANDI_2024_AR.pdf | C323: 2024 | D323: Financial | E323: Total Liabilities | F323: 190.38 | G323: IDR bn | H323: 11 | I323: Total Liabilitas 190,381,893,443 195,395,707,177 | J323: High | M323: LLM | N323: 2026-04-18 | O323: AI
A324: PT Andira Agro Tbk | B324: ANDI_2024_AR.pdf | C324: 2024 | D324: Financial | E324: Current Liabilities | F324: 50.09 | G324: IDR bn | H324: 11 | I324: Liabilitas Jangka Pendek 50,093,781,413 41,923,858,695 | J324: High | M324: LLM | N324: 2026-04-18 | O324: AI
... A348: PT Andira Agro Tbk | B348: ANDI_2024_AR.pdf | C348: 2024 | D348: Operation | E348: Calculated OER | F348: 0.1604 | G348: % | H348: 85 | I348: CPO 11,546 / FFB 71,988 = 16.04% | J348: Medium | M348: LLM | N348: 2026-04-18 | O348: AI
A349: PT Andira Agro Tbk | B349: ANDI_2024_AR.pdf | C349: 2024 | D349: Operation | E349: New Product: Palm Kernel Shell (Cangkang) | F349: Commenced | G349: text | H349: 86 | I349: Cangkang 236,261,262 (new line 2024) | J349: High | M349: LLM | N349: 2026-04-18 | O349: AI
A350: PT Andira Agro Tbk | B350: ANDI_2024_AR.pdf | C350: 2024 | D350: Company | E350: Headcount (Employees) | G350: count | H350: 0 | I350: Not retrieved in this pass | J350: Low | M350: LLM | N350: 2026-04-18 | O350: AI
A351: PT Austindo Nusantara Jaya Tbk | B351: ANJT_2022_AR.pdf | C351: 2023 | D351: Company | E351: Company Name | F351: PT Austindo Nusantara Jaya Tbk | G351: text | H351: 1 | I351: Cover: PT Austindo Nusantara Jaya Tbk. | J351: High | M351: LLM | N351: 2026-04-18 | O351: AI
...

Sheet Company_Master
A1: Company | B1: Ticker | C1: Exchange | D1: Report Year | E1: Report File | F1: HQ | G1: Country | H1: Core Region | I1: Group Structure Note | J1: Subsidiaries Note | K1: Shareholder Structure Note | L1: Listed Status | M1: Primary Business | N1: Deal Structure Initial Thought | O1: Dealability Note | P1: Acquisition Note | Q1: Key Red Flags | R1: Overall Comment | S1: Business Model [Upstream/Integrated/Downstream]
A2: PT Astra Agro Lestari Tbk | B2: AALI | C2: IDX | D2: 2023 | E2: AALI_2023_AR.pdf | F2: Jakarta, Indonesia | G2: Indonesia | H2: Sumatra/Kalimantan/Sulawesi (diversified) | I2: Part of Astra International group (PT Astra International Tbk parent) | L2: Listed (IDX: AALI) | M2: Palm oil plantation (upstream) + CPO/PKO refining + NPK blending | S2: Integrated
A3: PT Astra Agro Lestari Tbk | B3: AALI | C3: IDX | D3: 2024 | E3: AALI_2024_AR.pdf | F3: Jakarta, Indonesia | G3: Indonesia | H3: Sumatra/Kalimantan/Sulawesi (diversified) | I3: Part of Astra International group (PT Astra International Tbk parent, 79.68% ownership); ultimate controller Jardine Cycle & Carriage / Jardine Matheson. | J3: Multiple oil-palm plantation subsidiaries across Sumatra/Kalimantan/Sulawesi; refinery subsidiaries PT Tanjung Sarana Lestari (TSL, W. Sulawesi) and PT Tanjung Bina Lestari (TBL). | K3: PT Astra International Tbk 79.68%, Public 20.32% (each <5%) | L3: Listed (IDX: AALI) | M3: Palm oil plantation (upstream) + CPO/PKO refining + NPK blending | Q3: FFB production down 14% YoY due to extreme weather and ageing trees (avg age 16.5 yrs, 62% of mature area >15 yrs); third-party FFB availability tight; DMO/DPO export policies affect margins. | R3: Large diversified Indonesian palm producer with refinery and NPK integration. 2024 revenue +5% to Rp21.8 tn; net profit +9% to Rp1.19 tn on stronger CPO prices (+16% avg) offsetting 14% FFB volume decline. Low gearing (<1%). 69% domestic / 31% export sales mix. | S3: Integrated
A4: PT Astra Agro Lestari Tbk | B4: AALI | C4: IDX | D4: 2025 | E4: AALI_2025_AR.pdf | F4: Jakarta, Indonesia | G4: Indonesia | H4: Sumatra/Kalimantan/Sulawesi (diversified) | I4: Part of Astra International group (PT Astra International Tbk parent); ultimate controller Jardine Cycle & Carriage / Jardine Matheson. | J4: Plantation subsidiaries across Sumatra/Kalimantan/Sulawesi; refinery subsidiaries PT Tanjung Sarana Lestari (TSL) and PT Tanjung Bina Lestari (TBL). | K4: PT Astra International Tbk ~79.68% (controlling), Public ~20.32% | L4: Listed (IDX: AALI) | M4: Palm oil plantation (upstream) + CPO/PKO refining + NPK blending | Q4: Ageing plantation profile (avg age 16.7 yrs, ~71% of mature area >15 yrs); structural decline risk in productivity; dependence on replanting & 3rd-party FFB. | R4: Strong 2025: revenue +31% to Rp28.7 tn, net profit +28% to Rp1.47 tn on +11% CPO ASP and +13% sales volume. Company repaid all bank loans; gearing <1%, current ratio 4.3x, cash Rp2.76 tn. 64% domestic / 36% export. FFB total 3.82 mt (+2%), third-party FFB 2.41 mt (+11%), CPO 1.20 mt. | S4: Integrated
A5: PT Andira Agro Tbk | B5: ANDI | C5: IDX | D5: 2022 | E5: ANDI_2022_AR.pdf | F5: Jakarta, Indonesia (HO); Banyuasin, South Sumatra (operations) | G5: Indonesia | H5: South Sumatra (Banyuasin) | I5: Private, small single-site palm company. Controlling shareholder PT Central Energi Pratama 49.73%. | J5: No disclosed subsidiaries; single-entity issuer focused on Banyuasin estates. | K5: PT Central Energi Pratama 49.73%, PT Anugerah Perkasa Semesta 7.49%, Kejaksaan Agung (Attorney General's Office) 6.07%, Public 36.71% | L5: Listed (IDX: ANDI) since 16 Aug 2018 | M5: Oil palm plantation + single palm oil mill (CPO and PK production) | Q5: Loss-making (net loss Rp10.8 bn in 2022, 3rd consecutive loss year); 14.9x normalized CPO price declines hurt margins; share price stuck at Rp50 (listing floor); small scale (~4,453 ha HGU); high leverage (gross debt Rp166 bn vs equity Rp239 bn); Kejaksaan Agung 6.07% ownership unusual (post-suspected-case asset restitution). | R5: Small single-site palm producer in South Sumatra; 2022 revenue Rp317.9 bn (-8%), gross profit Rp22.8 bn (-40%), operating loss Rp10.5 bn (vs profit Rp9.8 bn in 2021), net loss Rp10.8 bn. FFB processed 121,298 t, CPO 21,524 t, PK 5,759 t. Mill capacity 30 tph. Share price Rp50 at IDX floor. Low trading liquidity. Assets Rp444 bn, equity Rp239 bn, gross bank debt Rp166 bn. | S5: Upstream
A6: PT Andira Agro Tbk | B6: ANDI | C6: IDX | D6: 2023 | E6: ANDI_2023_AR.pdf | F6: Jakarta, Indonesia (HO); Banyuasin, South Sumatra (operations) | G6: Indonesia | H6: South Sumatra (Banyuasin) | I6: Small single-site palm company. Controlling shareholder PT Central Energi Pratama 49.73%. | J6: No disclosed subsidiaries. | K6: PT Central Energi Pratama 49.73%, PT Anugerah Perkasa Semesta 7.49%, Kejaksaan Agung 6.07%, Public 36.71% (unchanged from 2022) | L6: Listed (IDX: ANDI) since 16 Aug 2018 | M6: Oil palm plantation + single palm oil mill (CPO and PK) | Q6: Deteriorating: revenue -31% to Rp219.9 bn, gross profit collapsed -99% to Rp0.22 bn, operating loss Rp63.1 bn (vs Rp10.5 bn 2022), net loss Rp56.0 bn (vs Rp10.8 bn). D/E 1.069x. Current ratio 0.58 - liquidity warning. Equity -23% to Rp182.7 bn. FFB volume -18% to 99,141 t; CPO -20% to 17,178 t. | R6: Steep deterioration in 2023: revenue declined as CPO & PK volumes shrank and prices eased. Gross margin fell from 7.2% to 0.1%. Large operating loss. Current ratio below 1x. Equity shrinking from accumulated losses. Share price unchanged at Rp50 (listing floor). High risk, possible going concern concern if trend continues. | S6: Upstream
A7: PT Andira Agro Tbk | B7: ANDI | C7: IDX | D7: 2024 | E7: ANDI_2024_AR.pdf | F7: Jakarta, Indonesia (HO); Banyuasin, South Sumatra (operations) | G7: Indonesia | H7: South Sumatra (Banyuasin) | I7: Small single-site palm company. Controlling shareholder PT Central Energi Pratama 49.73%. | J7: No disclosed subsidiaries. | K7: PT Central Energi Pratama ~49.73%, PT Anugerah Perkasa Semesta ~7.49%, Kejaksaan Agung ~6.07%, Public ~36.71% (per 2023; 2024 page 64 disclosure) | L7: Listed (IDX: ANDI) since 16 Aug 2018 | M7: Oil palm plantation + single palm oil mill (CPO, PK, cangkang) | Q7: Severe share price collapse: Rp50 -> Rp6 (from Q2 2024); market cap shrank from Rp467.5 bn to Rp56.1 bn. 3rd straight year of losses. Revenue -11% to Rp196.7 bn. Gross profit negative (-Rp12.0 bn, GP margin -6.08%). Operating loss Rp34.6 bn. Net loss Rp23.1 bn. D/E rose to 1.19x. FFB volume -27% to 71,988 t. Current ratio 0.77. Receivables collection period ballooned from 77 to 323 days - major working capital stress. | R7: PT Andira Agro continued to deteriorate in 2024; FFB volume down to 72k t, CPO down to 11,546 t. Share price collapsed from listing floor Rp50 to Rp6 in Q2-Q4. Working capital severely stressed (receivable days 323). Still loss-making with deeply negative gross margin. Going concern risk elevated. | S7: Upstream
A8: PT Austindo Nusantara Jaya Tbk | B8: ANJT | C8: IDX | D8: 2023 | E8: ANJT_2022_AR.pdf | F8: Jakarta, Indonesia | G8: Indonesia | H8: Sumatra/Kalimantan/Bangka Belitung/Southwest Papua | I8: Controlled by Tahija family via PT Memimpin Dengan Nurani (40.85%), PT Austindo Kencana Jaya (40.85%), George & Sjakon Tahija (4.74% each); Public 8.83% | J8: ANJA, ANJAS, SMM, KAL, GSB, PPM, PMP, ANJAP, LSP, AANE, GMIT, ANJB | K8: Tahija family ~91%; Public ~9%; Foundation (Yayasan Tahija) 0.0003% | L8: Listed (IDX: ANJT) since May 8, 2013 | M8: Palm oil plantation (upstream) + mills, sago, edamame, biogas renewable energy | Q8: FY2023 net profit collapsed to USD 1.9mn (-91% YoY) on lower CPO ASP and higher interest/depreciation | R8: Filename ANJT_2022_AR.txt actually corresponds to the 2023 Annual Report; primary year extracted is 2023. Reports in USD; converted to IDR bn at year-end rate ~15,394 IDR/USD. | S8: Integrated
A9: PT Austindo Nusantara Jaya Tbk | B9: ANJT | C9: IDX | D9: 2022 | E9: ANJT_2023_AR.pdf | F9: Jakarta, Indonesia | G9: Indonesia | H9: Sumatra/Kalimantan/Bangka Belitung/Southwest Papua | I9: Controlled by Tahija family via PT Memimpin Dengan Nurani, PT Austindo Kencana Jaya, and individual Tahija holdings | J9: ANJA, ANJAS, SMM, KAL, GSB, PPM, PMP, ANJAP, LSP, AANE, GMIT, ANJB | K9: Tahija family ~91%; Public ~9% | L9: Listed (IDX: ANJT) since May 8, 2013 | M9: Palm oil plantation (upstream) + mills, sago, edamame, renewable energy | Q9: 2022 profit halved vs 2021 (USD 21.2mn vs 36.6mn) on lower CPO ASP; consistent plasma share stagnating | R9: Filename ANJT_2023_AR.txt corresponds to FY2022 Annual Report. Primary year = 2022. Reports in USD; converted at year-end 2022 ~15,568 IDR/USD. | S9: Integrated
A10: PT Austindo Nusantara Jaya Tbk | B10: ANJT | C10: IDX | D10: 2024 | E10: ANJT_2024_AR.pdf | F10: Jakarta, Indonesia | G10: Indonesia | H10: Sumatra/Kalimantan/Bangka Belitung/Southwest Papua | I10: Controlled by Tahija family via PT Memimpin Dengan Nurani, PT Austindo Kencana Jaya, and individual Tahija holdings | J10: ANJA, ANJAS, SMM, KAL, GSB, PPM, PMP, ANJAP, LSP, AANE, GMIT, ANJB | K10: Tahija family ~91%; Public ~9% | L10: Listed (IDX: ANJT) since May 8, 2013 | M10: Palm oil plantation (upstream) + 5 mills, sago concession, edamame, biogas renewable energy | Q10: FFB production -11.7% YoY due to El Nino aftermath; North Sumatra II plantation suffered flooding; CPO production -13.5% YoY | R10: 2024 was a recovery year with net income +107% YoY but FFB production down sharply from 2023 due to weather. Reports in USD; converted at ~16,162 IDR/USD year-end 2024. | S10: Integrated
A11: PT BISI International Tbk | B11: BISI | C11: IDX | D11: 2023 | E11: BISI_2023_AR.pdf | F11: Sidoarjo, East Java, Indonesia | G11: Indonesia | H11: Java (East Java HQ) - nationwide sales in Indonesia | I11: Part of Charoen Pokphand Group (Jiaravanon family controlling shareholder). Subsidiaries: PT Multi Sarana Indotani (99.91%), PT Tanindo Intertraco (99.96%) | J11: PT Multi Sarana Indotani (pesticide), PT Tanindo Intertraco (fertilizer/pesticide trading) | K11: PT Agrindo Pratama 31.00%; Field Investment Holdings 6.36%; Valley Investment Holdings 6.36%; Vista Investment Holdings 6.36%; SJ BISI Holdings 4.08%; Public 45.73% (Jiaravanon family control ~54%) | L11: Listed (IDX: BISI) | M11: Hybrid seed producer (corn, horticulture, rice) + pesticides + fertilizers - NOT palm oil | Q11: Palm-specific operational metrics are N/A (BISI is a seeds/agritech company, not palm plantation). Revenue fell 4.86% on adverse weather affecting corn seed production | R11: BISI is a hybrid seeds and agrochemicals company affiliated with PT Charoen Pokphand Indonesia (offtaker). No palm plantation/mill operations; palm-specific fields left empty. | S11: Other
A12: PT BISI International Tbk | B12: BISI | C12: IDX | D12: 2024 | E12: BISI_2024_AR.pdf | F12: Sidoarjo, East Java, Indonesia | G12: Indonesia | H12: Java (East Java HQ) - nationwide sales in Indonesia | I12: Part of Charoen Pokphand Group (Jiaravanon family controlling shareholder). Subsidiaries: PT Multi Sarana Indotani, PT Tanindo Intertraco | J12: PT Multi Sarana Indotani (pesticide), PT Tanindo Intertraco (fertilizer/pesticide trading) | K12: PT Agrindo Pratama 31.00%; Field/Valley/Vista Investment Holdings 6.36% each; SJ BISI Holdings 4.08%; Public ~45.7% (Jiaravanon family control) | L12: Listed (IDX: BISI) | M12: Hybrid seed producer (corn, horticulture, rice) + pesticides + fertilizers | Q12: Revenue collapsed 40%; net profit -70% YoY due to weather-driven reduction in corn seed sales; operating CF was negative Rp 146 bn in 2024 | R12: BISI is a seeds/agritech company, not palm oil; palm-specific operational fields are N/A. 2024 was a weak year due to adverse weather and delayed planting seasons. | S12: Other
A13: PT BISI International Tbk | B13: BISI | C13: IDX | D13: 2025 | E13: BISI_2025_AR.pdf | F13: Sidoarjo, East Java, Indonesia | G13: Indonesia | H13: Java (East Java HQ) - nationwide sales in Indonesia | I13: Part of Charoen Pokphand Group (Jiaravanon family controlling shareholder) | J13: Subsidiaries from prior AR: PT Multi Sarana Indotani, PT Tanindo Intertraco | K13: Controlled by Jiaravanon family via PT Agrindo Pratama (31%) and BVI holding companies | L13: Listed (IDX: BISI) | M13: Hybrid seed producer (corn, horticulture, rice) + pesticides + fertilizers | Q13: Source file is consolidated financial statements only (audited FS, not full Annual Report). Operating CF still negative at Rp -263 bn in 2025; cash position fell sharply from Rp 568 bn to Rp 167 bn | R13: BISI_2025 source is only the consolidated audited financial statements (not a full AR). Operational/ESG sections not available. Revenue recovered 24% YoY to Rp 1,696 bn. | S13: Other
A14: PT Bumi Teknokultura Unggul Tbk | B14: BTEK | C14: IDX | D14: 2022 | E14: BTEK_2022_AR.pdf | F14: Jakarta Timur, Indonesia | G14: Indonesia | H14: Java (Tangerang) - cocoa processing | I14: Holding company with subsidiary PT Golden Harvest Cocoa Indonesia (cocoa bean processing); also owns Golden Harvest Cocoa Pte. Ltd. (Singapore). | J14: PT Golden Harvest Cocoa Indonesia; Golden Harvest Cocoa Pte. Ltd. | K14: Golden Harvest Cocoa Ltd 41.59%; Kejaksaan Agung 5.25%; public <5%. | L14: Listed (IDX: BTEK) | M14: Cocoa bean processing (cocoa butter, cocoa cake, cocoa powder). Not a palm-oil producer. | Q14: Not a palm oil company despite inclusion in palm longlist; cocoa processing. Current ratio 0.35, DER 2.44x, bank loans Rp 2,478 bn vs total equity Rp 1,203 bn; gross loss and net comprehensive loss Rp 358.68 bn (2022). | R14: BTEK is a cocoa (kakao) bean processor, not a palm oil producer. Financial statement in raw rupiah (header 'dalam Ribuan Rupiah' appears mislabeled; narrative figures confirm raw rupiah). Heavy leverage, continued losses. | S14: Other
... A94: PT Wahana Pronatural Tbk | B94: WAPO | C94: IDX | D94: 2024 | E94: WAPO_2024_AR.pdf | F94: Surabaya, Indonesia | G94: Indonesia | H94: Java/Surabaya (HQ); candy factory in Bogor West Java (leased out); coffee-bean trading operations national | I94: Small trading-industrial company. No disclosed subsidiaries; standalone (non-consolidated) financials. Controlling shareholders PT Hijau Sari (36.07%) and PT Mitra Niaga Sakti (32.44%). | J94: None disclosed in the AR (standalone financial statements). | K94: PT Hijau Sari 36.07%, PT Mitra Niaga Sakti 32.44%, PT Surya Pelangi Mandiri 8.06%, PT Pesona Bangun Mandiri 4.43%, Public <5% 19.00%. Total 1,240,923,111 shares. | L94: Listed (IDX: WAPO); IPO 22 June 2001. | M94: Trading company - coffee beans (green beans) as 97% of 2024 revenue, with minor contributions from AirAlam bottled water (1.1%), Sunkist Water C vitamin drink (1%), and dried seaweed (0.4%). NOT a palm oil producer. | Q94: NOT A PALM OIL COMPANY. WAPO is a coffee-bean (green bean) trading house with minor beverage/seaweed activity. No oil-palm plantations, CPO mills, FFB production or any palm processing. Revenue surged 404% YoY in 2024 driven by coffee-bean trade volumes (30,000 t), but margins remain razor-thin (gross margin 1.2%, operating margin 0.02%). Only 9 employees. Ticker should likely be EXCLUDED from the Indonesian palm long-list - clearly does not belong in palm oil peer set. | R94: PT Wahana Pronatural Tbk posted 2024 net sales of Rp 2,122.33 bn (+404% YoY), almost entirely driven by green-bean coffee trading (30,000 t at inflated global prices; 97% of revenue). Gross profit Rp 24.65 bn, operating profit Rp 0.52 bn (vs Rp -0.36 bn loss in 2023), and net profit Rp 0.72 bn (comprehensive Rp 0.78 bn). Total assets fell to Rp 86.59 bn from Rp 131.94 bn as trade receivables collapsed from Rp 61.1 bn to Rp 4.7 bn. No palm-oil operations anywhere. Company has a negligible employee count (9) and trades commodities rather than producing them. | S94: Other

Sheet Asset_Operations
A1: Company | B1: Planted Area Total (ha) | C1: Nucleus Area (ha) | D1: Plasma Area (ha) | E1: Mature Area (ha) | F1: Immature Area (ha) | G1: Productive Age Area (ha) | H1: Old Age Area (ha) | I1: Average Tree Age (years) | J1: Replanting Area (ha) | K1: Sumatra Area (ha) | L1: Kalimantan Area (ha) | M1: Sulawesi Area (ha) | N1: Other Region Area (ha) | O1: Mills Count (#) | P1: Mill Capacity (tph) | Q1: Kernel Crushing Count (#) | R1: Kernel Crushing Capacity (tph) | S1: CPO Refinery Count (#) | T1: CPO Refinery Capacity (tpa) | U1: PKO Refinery Count (#) | V1: PKO Refinery Capacity (tpa) | W1: NPK Plant Count (#) | X1: Jetty/Logistics Note | Y1: Power Infrastructure Note | Z1: Road Infrastructure Note | AA1: Third-Party FFB (t) | AB1: Third-Party Dependence (%) [auto] | AC1: FFB Production (t) | AD1: Nucleus FFB (t) | AE1: Plasma FFB (t) | AF1: FFB Processed (t) | AG1: CPO Production (t) | AH1: Kernel Production (t) | AI1: PKO Production (t) | AJ1: RBDPO Production (t) | AK1: Olein Production (t) | AL1: Stearin Production (t) | AM1: PFAD Production (t) | AN1: PKE Production (t) | AO1: FFB Yield (t/ha) [auto = FFB Prod/Mature Area] | AP1: Nucleus FFB Yield (t/ha) [auto] | AQ1: CPO Yield (t/ha) [auto = CPO Prod/Mature Area] | AR1: OER (%) [auto = CPO/FFB Processed] | AS1: KER (%) [auto = Kernel/FFB Processed] | AT1: PKO Extraction (%) [auto] | AU1: PKE Extraction (%) [auto] | AV1: Average CPO Selling Price (local ccy/kg) | AW1: Domestic Sales (%) | AX1: Export Sales (%) | AY1: Asset Quality Note | AZ1: Ops Risk Note | BA1: Digitalization Note | BB1: Sustainability Ops Note | BC1: OER vs Own FFB (%) [auto = CPO/Own FFB] | BD1: OER vs Total Available FFB (%) [auto = CPO/(Own+3rd Party)] | BE1: OER Reported (%) (manual; company disclosure) | BF1: OER Method Note (manual) | BG1: Report Year
A2: PT Astra Agro Lestari Tbk | B2: 285387 | C2: 213158 | D2: 72229 | E2: 265518 | F2: 19869 | G2: 102319 | H2: 163199 | I2: 16.2 | K2: 105300 | L2: 129804 | M2: 50283 | N2: 0 | O2: 32 | P2: 1570 | Q2: 14 | S2: 2 | U2: 1 | W2: 2 | AA2: 2398457 | AB2: =IFERROR(AA2/AF2,"") | AC2: 3312149 | AD2: 3312149 | AE2: 1041496 | AF2: 6752102 | AG2: 1275539 | AH2: 272310 | AI2: 45158 | AJ2: 17289 | AK2: 441671 | AL2: 115918 | AM2: 23621 | AN2: 56142 | AO2: =IFERROR(AC2/E2,"") | AP2: =IFERROR(AD2/E2,"") | AQ2: =IFERROR(AG2/E2,"") | AR2: =IFERROR(AG2/AF2,"") | AS2: =IFERROR(AH2/AF2,"") | AT2: =IFERROR(AI2/AH2,"") | AU2: =IFERROR(AN2/AH2,"") | AV2: 12948 | BC2: =IFERROR(AG2/AC2,"") | BD2: =IFERROR(AG2/(AC2+AA2),"") | BE2: 0.1889 | BF2: Reported CPO Extraction Rate 18.89% (p.13 "Rendemen Minyak Sawit") | BG2: 2023
A3: PT Astra Agro Lestari Tbk | B3: 284831 | C3: 212602 | D3: 72229 | E3: 265490 | F3: 19341 | G3: 87761 | H3: 177729 | I3: 16.5 | K3: 104376 | L3: 130043 | M3: 50412 | O3: 32 | P3: 1570 | Q3: 14 | S3: 2 | U3: 1 | W3: 2 | AA3: 2180762 | AB3: =IFERROR(AA3/AF3,"") | AC3: 3002685 | AD3: 3002685 | AE3: 731773 | AF3: 5915220 | AG3: 1125388 | AH3: 234121 | AI3: 46454 | AJ3: 14760 | AK3: 388106 | AL3: 95826 | AM3: 19382 | AN3: 57001 | AO3: =IFERROR(AC3/E3,"") | AP3: =IFERROR(AD3/E3,"") | AQ3: =IFERROR(AG3/E3,"") | AR3: =IFERROR(AG3/AF3,"") | AS3: =IFERROR(AH3/AF3,"") | AT3: =IFERROR(AI3/AH3,"") | AU3: =IFERROR(AN3/AH3,"") | AV3: 12883 | AW3: 0.69 | AX3: 0.31 | BC3: =IFERROR(AG3/AC3,"") | BD3: =IFERROR(AG3/(AC3+AA3),"") | BE3: 0.1903 | BF3: Reported CPO Extraction Rate 19.03% (p.15 'Rendemen Minyak Sawit') | BG3: 2024
A4: PT Astra Agro Lestari Tbk | B4: 280325 | C4: 208063 | D4: 72262 | E4: 260927 | F4: 19399 | G4: 76292 | H4: 184635 | I4: 16.7 | K4: 103389 | L4: 129093 | M4: 47843 | O4: 32 | P4: 1655 | Q4: 14 | S4: 2 | U4: 1 | W4: 2 | AA4: 2409810 | AB4: =IFERROR(AA4/AF4,"") | AC4: 3009024 | AD4: 3009024 | AE4: 812535 | AF4: 6231369 | AG4: 1197514 | AH4: 251874 | AI4: 60451 | AJ4: 17718 | AK4: 457987 | AL4: 119496 | AM4: 26920 | AN4: 74765 | AO4: =IFERROR(AC4/E4,"") | AP4: =IFERROR(AD4/E4,"") | AQ4: =IFERROR(AG4/E4,"") | AR4: =IFERROR(AG4/AF4,"") | AS4: =IFERROR(AH4/AF4,"") | AT4: =IFERROR(AI4/AH4,"") | AU4: =IFERROR(AN4/AH4,"") | AV4: 14316 | AW4: 0.64 | AX4: 0.36 | BC4: =IFERROR(AG4/AC4,"") | BD4: =IFERROR(AG4/(AC4+AA4),"") | BE4: 0.1922 | BF4: Reported CPO Extraction Rate 19.22% (p.16 'Rendemen Minyak Sawit') | BG4: 2025
A5: PT Andira Agro Tbk | E5: 5040.63 | K5: 4453 | O5: 1 | P5: 30 | AB5: =IFERROR(AA5/AF5,"") | AF5: 121298 | AG5: 21524 | AH5: 5759 | AO5: =IFERROR(AC5/E5,"") | AP5: =IFERROR(AD5/E5,"") | AQ5: =IFERROR(AG5/E5,"") | AR5: =IFERROR(AG5/AF5,"") | AS5: =IFERROR(AH5/AF5,"") | AT5: =IFERROR(AI5/AH5,"") | AU5: =IFERROR(AN5/AH5,"") | BC5: =IFERROR(AG5/AC5,"") | BD5: =IFERROR(AG5/(AC5+AA5),"") | BE5: 0.1775 | BF5: Calculated OER = CPO 21,524 / FFB processed 121,298 = 17.75% | BG5: 2022
A6: PT Andira Agro Tbk | B6: 10006.31 | C6: 5040.63 | D6: 4965.68 | E6: 5040.63 | K6: 4453 | O6: 1 | P6: 30 | Q6: 0 | S6: 0 | AB6: =IFERROR(AA6/AF6,"") | AF6: 99141 | AG6: 17178 | AH6: 4620 | AO6: =IFERROR(AC6/E6,"") | AP6: =IFERROR(AD6/E6,"") | AQ6: =IFERROR(AG6/E6,"") | AR6: =IFERROR(AG6/AF6,"") | AS6: =IFERROR(AH6/AF6,"") | AT6: =IFERROR(AI6/AH6,"") | AU6: =IFERROR(AN6/AH6,"") | BC6: =IFERROR(AG6/AC6,"") | BD6: =IFERROR(AG6/(AC6+AA6),"") | BE6: 0.1733 | BF6: Calculated OER = CPO 17,178 / FFB 99,141 = 17.33% | BG6: 2023
A7: PT Andira Agro Tbk | B7: 9709.24 | C7: 4743.56 | D7: 4965.68 | E7: 4558.21 | F7: 185.35 | K7: 4453 | O7: 1 | P7: 30 | Q7: 0 | S7: 0 | AB7: =IFERROR(AA7/AF7,"") | AF7: 71988 | AG7: 11546 | AH7: 3166 | AO7: =IFERROR(AC7/E7,"") | AP7: =IFERROR(AD7/E7,"") | AQ7: =IFERROR(AG7/E7,"") | AR7: =IFERROR(AG7/AF7,"") | AS7: =IFERROR(AH7/AF7,"") | AT7: =IFERROR(AI7/AH7,"") | AU7: =IFERROR(AN7/AH7,"") | AW7: 1 | AX7: 0 | BC7: =IFERROR(AG7/AC7,"") | BD7: =IFERROR(AG7/(AC7+AA7),"") | BE7: 0.1604 | BF7: Calculated OER = CPO 11,546 / FFB 71,988 = 16.04% | BG7: 2024
A8: PT Austindo Nusantara Jaya Tbk | B8: 48516 | C8: 43400 | D8: 5116 | E8: 43400 | F8: 5174 | I8: 13 | K8: 26049 | L8: 9051 | N8: 13416 | O8: 5 | P8: 315 | Q8: 1 | S8: 0 | AA8: 503811 | AB8: =IFERROR(AA8/AF8,"") | AC8: 881051 | AF8: 1374871 | AG8: 283659 | AH8: 57477 | AI8: 1459 | AO8: =IFERROR(AC8/E8,"") | AP8: =IFERROR(AD8/E8,"") | AQ8: =IFERROR(AG8/E8,"") | AR8: =IFERROR(AG8/AF8,"") | AS8: =IFERROR(AH8/AF8,"") | AT8: =IFERROR(AI8/AH8,"") | AU8: =IFERROR(AN8/AH8,"") | AV8: 11253 | AW8: 0.9976 | AX8: 0.0024 | BC8: =IFERROR(AG8/AC8,"") | BD8: =IFERROR(AG8/(AC8+AA8),"") | BE8: 0.206 | BF8: CPO Extraction Rate 20.6% (p.11, Palm Oil Production table). USD 731/t ASP converted to Rp/kg at 15,394 IDR/USD. | BG8: 2023
A9: PT Austindo Nusantara Jaya Tbk | B9: 49409 | C9: 43700 | D9: 5709 | E9: 42200 | F9: 7338 | I9: 12.9 | K9: 26491 | L9: 9051 | N9: 13867 | O9: 5 | P9: 315 | Q9: 1 | S9: 0 | AA9: 538483 | AB9: =IFERROR(AA9/AF9,"") | AC9: 840581 | AF9: 1379064 | AG9: 275769 | AH9: 55011 | AI9: 1052 | AO9: =IFERROR(AC9/E9,"") | AP9: =IFERROR(AD9/E9,"") | AQ9: =IFERROR(AG9/E9,"") | AR9: =IFERROR(AG9/AF9,"") | AS9: =IFERROR(AH9/AF9,"") | AT9: =IFERROR(AI9/AH9,"") | AU9: =IFERROR(AN9/AH9,"") | AV9: 13109 | AW9: 0.9967 | AX9: 0.0033 | BC9: =IFERROR(AG9/AC9,"") | BD9: =IFERROR(AG9/(AC9+AA9),"") | BE9: 0.201 | BF9: CPO Extraction Rate 20.1% (p.8). USD 842/t ASP x ~15,568 IDR/USD. | BG9: 2022
A10: PT Austindo Nusantara Jaya Tbk | B10: 53357 | C10: 48352 | D10: 5005 | E10: 42176 | F10: 6212 | I10: 12.9 | J10: 1718 | K10: 26049 | L10: 9163 | N10: 18145 | O10: 5 | P10: 315 | Q10: 1 | S10: 0 | AA10: 463835 | AB10: =IFERROR(AA10/AF10,"") | AC10: 777615 | AF10: 1233180 | AG10: 245395 | AH10: 51889 | AI10: 1121 | AO10: =IFERROR(AC10/E10,"") | AP10: =IFERROR(AD10/E10,"") | AQ10: =IFERROR(AG10/E10,"") | AR10: =IFERROR(AG10/AF10,"") | AS10: =IFERROR(AH10/AF10,"") | AT10: =IFERROR(AI10/AH10,"") | AU10: =IFERROR(AN10/AH10,"") | AV10: 13285 | BC10: =IFERROR(AG10/AC10,"") | BD10: =IFERROR(AG10/(AC10+AA10),"") | BE10: 0.199 | BF10: Combined OER 19.9% (CPO production / total FFB processed). USD 822/t x 16,162 IDR/USD. | BG10: 2024
A11: PT BISI International Tbk | AB11: =IFERROR(AA11/AF11,"") | AO11: =IFERROR(AC11/E11,"") | AP11: =IFERROR(AD11/E11,"") | AQ11: =IFERROR(AG11/E11,"") | AR11: =IFERROR(AG11/AF11,"") | AS11: =IFERROR(AH11/AF11,"") | AT11: =IFERROR(AI11/AH11,"") | AU11: =IFERROR(AN11/AH11,"") | BC11: =IFERROR(AG11/AC11,"") | BD11: =IFERROR(AG11/(AC11+AA11),"") | BG11: 2023
A12: PT BISI International Tbk | AB12: =IFERROR(AA12/AF12,"") | AO12: =IFERROR(AC12/E12,"") | AP12: =IFERROR(AD12/E12,"") | AQ12: =IFERROR(AG12/E12,"") | AR12: =IFERROR(AG12/AF12,"") | AS12: =IFERROR(AH12/AF12,"") | AT12: =IFERROR(AI12/AH12,"") | AU12: =IFERROR(AN12/AH12,"") | BC12: =IFERROR(AG12/AC12,"") | BD12: =IFERROR(AG12/(AC12+AA12),"") | BG12: 2024
A13: PT BISI International Tbk | AB13: =IFERROR(AA13/AF13,"") | AO13: =IFERROR(AC13/E13,"") | AP13: =IFERROR(AD13/E13,"") | AQ13: =IFERROR(AG13/E13,"") | AR13: =IFERROR(AG13/AF13,"") | AS13: =IFERROR(AH13/AF13,"") | AT13: =IFERROR(AI13/AH13,"") | AU13: =IFERROR(AN13/AH13,"") | BC13: =IFERROR(AG13/AC13,"") | BD13: =IFERROR(AG13/(AC13+AA13),"") | BG13: 2025
A14: PT Bumi Teknokultura Unggul Tbk | AB14: =IFERROR(AA14/AF14,"") | AO14: =IFERROR(AC14/E14,"") | AP14: =IFERROR(AD14/E14,"") | AQ14: =IFERROR(AG14/E14,"") | AR14: =IFERROR(AG14/AF14,"") | AS14: =IFERROR(AH14/AF14,"") | AT14: =IFERROR(AI14/AH14,"") | AU14: =IFERROR(AN14/AH14,"") | BC14: =IFERROR(AG14/AC14,"") | BD14: =IFERROR(AG14/(AC14+AA14),"") | BG14: 2022
A15: PT Bumi Teknokultura Unggul Tbk | AB15: =IFERROR(AA15/AF15,"") | AO15: =IFERROR(AC15/E15,"") | AP15: =IFERROR(AD15/E15,"") | AQ15: =IFERROR(AG15/E15,"") | AR15: =IFERROR(AG15/AF15,"") | AS15: =IFERROR(AH15/AF15,"") | AT15: =IFERROR(AI15/AH15,"") | AU15: =IFERROR(AN15/AH15,"") | BC15: =IFERROR(AG15/AC15,"") | BD15: =IFERROR(AG15/(AC15+AA15),"") | BG15: 2023
A16: PT Bumi Teknokultura Unggul Tbk | AB16: =IFERROR(AA16/AF16,"") | AO16: =IFERROR(AC16/E16,"") | AP16: =IFERROR(AD16/E16,"") | AQ16: =IFERROR(AG16/E16,"") | AR16: =IFERROR(AG16/AF16,"") | AS16: =IFERROR(AH16/AF16,"") | AT16: =IFERROR(AI16/AH16,"") | AU16: =IFERROR(AN16/AH16,"") | BC16: =IFERROR(AG16/AC16,"") | BD16: =IFERROR(AG16/(AC16+AA16),"") | BG16: 2024
A17: PT Eagle High Plantations Tbk | B17: 87000 | E17: 87000 | F17: 0 | K17: 2000 | L17: 73000 | N17: 12000 | O17: 7 | P17: 370 | Q17: 0 | S17: 0 | AA17: 272931 | AB17: =IFERROR(AA17/AF17,"") | AC17: 975251 | AD17: 930761 | AE17: 154180 | AF17: 1357872 | AG17: 320107 | AH17: 59278 | AO17: =IFERROR(AC17/E17,"") | AP17: =IFERROR(AD17/E17,"") | AQ17: =IFERROR(AG17/E17,"") | AR17: =IFERROR(AG17/AF17,"") | AS17: =IFERROR(AH17/AF17,"") | AT17: =IFERROR(AI17/AH17,"") | AU17: =IFERROR(AN17/AH17,"") | AV17: 11015 | AW17: 1 | AX17: 0 | BC17: =IFERROR(AG17/AC17,"") | BD17: =IFERROR(AG17/(AC17+AA17),"") | BE17: 0.2357 | BF17: Derived as CPO production (320,107 t) / FFB processed (1,357,872 t); AR does not report OER directly. | BG17: 2023
A18: PT Eagle High Plantations Tbk | B18: 87000 | E18: 86729 | F18: 271 | K18: 2000 | L18: 73000 | N18: 12000 | O18: 7 | P18: 370 | Q18: 0 | S18: 0 | AB18: =IFERROR(AA18/AF18,"") | AC18: 1041515 | AG18: 263657 | AH18: 49193 | AO18: =IFERROR(AC18/E18,"") | AP18: =IFERROR(AD18/E18,"") | AQ18: =IFERROR(AG18/E18,"") | AR18: =IFERROR(AG18/AF18,"") | AS18: =IFERROR(AH18/AF18,"") | AT18: =IFERROR(AI18/AH18,"") | AU18: =IFERROR(AN18/AH18,"") | AV18: 12515 | BC18: =IFERROR(AG18/AC18,"") | BD18: =IFERROR(AG18/(AC18+AA18),"") | BE18: 0.236 | BG18: 2024
A19: PT Eagle High Plantations Tbk | B19: 74339 | E19: 74068 | F19: 271 | O19: 7 | P19: 370 | AB19: =IFERROR(AA19/AF19,"") | AO19: =IFERROR(AC19/E19,"") | AP19: =IFERROR(AD19/E19,"") | AQ19: =IFERROR(AG19/E19,"") | AR19: =IFERROR(AG19/AF19,"") | AS19: =IFERROR(AH19/AF19,"") | AT19: =IFERROR(AI19/AH19,"") | AU19: =IFERROR(AN19/AH19,"") | BC19: =IFERROR(AG19/AC19,"") | BD19: =IFERROR(AG19/(AC19+AA19),"") | BG19: 2025
A20: PT Citra Borneo Utama Tbk | O20: 0 | Q20: 1 | R20: 25 | S20: 1 | T20: 850000 | U20: 0 | AB20: =IFERROR(AA20/AF20,"") | AO20: =IFERROR(AC20/E20,"") | AP20: =IFERROR(AD20/E20,"") | AQ20: =IFERROR(AG20/E20,"") | AR20: =IFERROR(AG20/AF20,"") | AS20: =IFERROR(AH20/AF20,"") | AT20: =IFERROR(AI20/AH20,"") | AU20: =IFERROR(AN20/AH20,"") | AW20: 0.2254 | AX20: 0.7746 | AZ20: 780,010 MT total production (8.23% below 850,000 MT target); Refinery utilization 91.77% (up from 63.44%); Fractionation utilization 84.95%; Kernel crushing utilization 35.81%. CPO refinery yields: RBDPO 95.76%, PFAD 3.76%. Fractionation yields: Olein 81.01%, Stearin 18.99%. | BC20: =IFERROR(AG20/AC20,"") | BD20: =IFERROR(AG20/(AC20+AA20),"") | BG20: 2023
A21: PT Citra Borneo Utama Tbk | O21: 0 | Q21: 1 | R21: 25 | S21: 1 | T21: 850000 | U21: 0 | AB21: =IFERROR(AA21/AF21,"") | AJ21: 387833 | AK21: 296406 | AL21: 67661 | AM21: 14659 | AO21: =IFERROR(AC21/E21,"") | AP21: =IFERROR(AD21/E21,"") | AQ21: =IFERROR(AG21/E21,"") | AR21: =IFERROR(AG21/AF21,"") | AS21: =IFERROR(AH21/AF21,"") | AT21: =IFERROR(AI21/AH21,"") | AU21: =IFERROR(AN21/AH21,"") | AW21: 0.2366 | AX21: 0.7634 | AZ21: Total production 402,492 MT (47.59% of 845,750 MT target). Refinery CPO processing utilization 47.62% (down from 91.77%), non-processing 29.39%, total 77.01%. Fractionation utilization 42.83% (vs 84.95%). Kernel crushing utilization 29.00%. Yields: RBDPO 95.82%, PFAD 3.62%; Olein 81.42%, Stearin 18.58%; CPKO 40.42%, PKE 54.97%. Kernel storage expanded to 12,500t. | BC21: =IFERROR(AG21/AC21,"") | BD21: =IFERROR(AG21/(AC21+AA21),"") | BG21: 2024
A22: PT Citra Borneo Utama Tbk | O22: 0 | Q22: 1 | R22: 25 | S22: 1 | T22: 850000 | U22: 0 | AB22: =IFERROR(AA22/AF22,"") | AJ22: 578928 | AK22: 467921 | AL22: 101320 | AM22: 21898 | AO22: =IFERROR(AC22/E22,"") | AP22: =IFERROR(AD22/E22,"") | AQ22: =IFERROR(AG22/E22,"") | AR22: =IFERROR(AG22/AF22,"") | AS22: =IFERROR(AH22/AF22,"") | AT22: =IFERROR(AI22/AH22,"") | AU22: =IFERROR(AN22/AH22,"") | AW22: 0.2136 | AX22: 0.7864 | AZ22: Total production 603,670 MT (71.02% of 850,000 MT target). Refinery utilization 71.02%; Fractionation utilization 66.97%; Kernel crushing 50.66%. Yields: RBDPO 95.90%, PFAD 3.63%; Olein 82.21%, Stearin 17.78%; CPKO 42.09%, PKE 54.44%. New bottling capacity 222,222 L/day (68.23% Minyak Kita, 31.77% Hanau) utilization 41.95%. | BC22: =IFERROR(AG22/AC22,"") | BD22: =IFERROR(AG22/(AC22+AA22),"") | BG22: 2025
A23: PT Cisadane Sawit Raya Tbk. | B23: 19333.9 | C23: 19333.9 | E23: 16147.1 | F23: 3186.8 | G23: 12053.3 | H23: 4093.8 | K23: 19333.9 | O23: 1 | P23: 45 | Q23: 0 | S23: 0 | AA23: 14326 | AB23: =IFERROR(AA23/AF23,"") | AC23: 342464 | AD23: 342464 | AF23: 174180 | AG23: 35701 | AH23: 8974 | AO23: =IFERROR(AC23/E23,"") | AP23: =IFERROR(AD23/E23,"") | AQ23: =IFERROR(AG23/E23,"") | AR23: =IFERROR(AG23/AF23,"") | AS23: =IFERROR(AH23/AF23,"") | AT23: =IFERROR(AI23/AH23,"") | AU23: =IFERROR(AN23/AH23,"") | AV23: 12468 | AW23: 1 | AX23: 0 | BC23: =IFERROR(AG23/AC23,"") | BD23: =IFERROR(AG23/(AC23+AA23),"") | BE23: 0.205 | BF23: OER 20.5% and KER 5.2% (Extraction rates of CPO and Kernel from FFB processed) | BG23: 2022
A24: PT Cisadane Sawit Raya Tbk. | B24: 19552 | C24: 19552 | D24: 183.71 | E24: 17258.3 | F24: 2293.7 | G24: 13227.2 | H24: 4031.1 | K24: 19552 | O24: 2 | P24: 90 | Q24: 0 | S24: 0 | AA24: 26402 | AB24: =IFERROR(AA24/AF24,"") | AC24: 337367 | AD24: 337367 | AF24: 229687 | AG24: 48663 | AH24: 11166 | AO24: =IFERROR(AC24/E24,"") | AP24: =IFERROR(AD24/E24,"") | AQ24: =IFERROR(AG24/E24,"") | AR24: =IFERROR(AG24/AF24,"") | AS24: =IFERROR(AH24/AF24,"") | AT24: =IFERROR(AI24/AH24,"") | AU24: =IFERROR(AN24/AH24,"") | AV24: 10821 | AW24: 1 | AX24: 0 | BC24: =IFERROR(AG24/AC24,"") | BD24: =IFERROR(AG24/(AC24+AA24),"") | BE24: 0.212 | BF24: OER 21.2% and KER 4.9%. Two palm oil mills operational in 2023 (existing Sei Siarti 45 tph + PT SKL South Tapanuli 45 tph). Total capacity now 90 tph. | BG24: 2023
A25: PT Cisadane Sawit Raya Tbk. | B25: 20067.6 | C25: 20067.6 | D25: 868.8 | E25: 17430.9 | F25: 2636.7 | G25: 13352 | H25: 4078.9 | K25: 20067.6 | O25: 2 | P25: 90 | Q25: 0 | S25: 0 | AA25: 33723 | AB25: =IFERROR(AA25/AF25,"") | AC25: 319085 | AD25: 319085 | AF25: 265837 | AG25: 55700 | AH25: 11801 | AO25: =IFERROR(AC25/E25,"") | AP25: =IFERROR(AD25/E25,"") | AQ25: =IFERROR(AG25/E25,"") | AR25: =IFERROR(AG25/AF25,"") | AS25: =IFERROR(AH25/AF25,"") | AT25: =IFERROR(AI25/AH25,"") | AU25: =IFERROR(AN25/AH25,"") | AV25: 12793 | AW25: 1 | AX25: 0 | BC25: =IFERROR(AG25/AC25,"") | BD25: =IFERROR(AG25/(AC25+AA25),"") | BE25: 0.21 | BF25: OER 21.0% and KER 4.4%. Two operational mills (Sei Siarti 45 tph + PT SKL 45 tph, total 90 tph). Third mill at PT BKL Banyuasin (South Sumatra) in construction (~45 tph), target Jun-2025. | BG25: 2024
A26: PT Dharma Satya Nusantara Tbk | B26: 112500 | C26: 84600 | D26: 28300 | E26: 104000 | F26: 8800 | I26: 12.8 | L26: 112500 | O26: 12 | P26: 675 | Q26: 1 | R26: 16.7 | S26: 0 | AB26: =IFERROR(AA26/AF26,"") | AC26: 2213698 | AD26: 1758257 | AE26: 455442 | AF26: 2809177 | AG26: 639480 | AH26: 117622 | AI26: 37970 | AO26: =IFERROR(AC26/E26,"") | AP26: =IFERROR(AD26/E26,"") | AQ26: =IFERROR(AG26/E26,"") | AR26: =IFERROR(AG26/AF26,"") | AS26: =IFERROR(AH26/AF26,"") | AT26: =IFERROR(AI26/AH26,"") | AU26: =IFERROR(AN26/AH26,"") | AV26: 11180 | AW26: 1 | AX26: 0 | BC26: =IFERROR(AG26/AC26,"") | BD26: =IFERROR(AG26/(AC26+AA26),"") | BE26: 0.2276 | BF26: CPO OER as reported in MD&A for palm oil segment; FFA 3.78% | BG26: 2022
A27: PT Dharma Satya Nusantara Tbk | B27: 112700 | C27: 84800 | D27: 27900 | E27: 105700 | F27: 7000 | I27: 13.3 | L27: 112700 | O27: 12 | P27: 675 | Q27: 1 | R27: 16.7 | S27: 0 | AA27: 582738 | AB27: =IFERROR(AA27/AF27,"") | AC27: 2271821 | AD27: 1796532 | AE27: 475289 | AF27: 2854559 | AG27: 661892 | AH27: 122732 | AI27: 40356 | AO27: =IFERROR(AC27/E27,"") | AP27: =IFERROR(AD27/E27,"") | AQ27: =IFERROR(AG27/E27,"") | AR27: =IFERROR(AG27/AF27,"") | AS27: =IFERROR(AH27/AF27,"") | AT27: =IFERROR(AI27/AH27,"") | AU27: =IFERROR(AN27/AH27,"") | AV27: 11390 | AW27: 1 | AX27: 0 | BC27: =IFERROR(AG27/AC27,"") | BD27: =IFERROR(AG27/(AC27+AA27),"") | BE27: 0.2319 | BF27: CPO OER as reported in MD&A; FFA 2.96% | BG27: 2023
A28: PT Dharma Satya Nusantara Tbk | B28: 110700 | C28: 82800 | D28: 27908 | E28: 104101 | F28: 6599 | I28: 14 | J28: 900 | L28: 110700 | O28: 12 | P28: 675 | Q28: 1 | R28: 16.7 | S28: 0 | AA28: 405349 | AB28: =IFERROR(AA28/AF28,"") | AC28: 2109737 | AD28: 1661979 | AE28: 447757 | AF28: 2515086 | AG28: 601508 | AH28: 114210 | AI28: 38217 | AO28: =IFERROR(AC28/E28,"") | AP28: =IFERROR(AD28/E28,"") | AQ28: =IFERROR(AG28/E28,"") | AR28: =IFERROR(AG28/AF28,"") | AS28: =IFERROR(AH28/AF28,"") | AT28: =IFERROR(AI28/AH28,"") | AU28: =IFERROR(AN28/AH28,"") | AV28: 12790 | AW28: 1 | AX28: 0 | BC28: =IFERROR(AG28/AC28,"") | BD28: =IFERROR(AG28/(AC28+AA28),"") | BE28: 0.2392 | BF28: CPO OER reported 23.92%; FFA 2.86% | BG28: 2024
A29: PT FAP Agri Tbk | B29: 88752 | C29: 77384 | D29: 11368 | E29: 82624 | F29: 6128 | I29: 11 | L29: 85420 | N29: 3332 | O29: 5 | Q29: 1 | S29: 0 | AB29: =IFERROR(AA29/AF29,"") | AC29: 1202008 | AF29: 1202008 | AG29: 277058 | AH29: 48192 | AI29: 11106 | AN29: 12433 | AO29: =IFERROR(AC29/E29,"") | AP29: =IFERROR(AD29/E29,"") | AQ29: =IFERROR(AG29/E29,"") | AR29: =IFERROR(AG29/AF29,"") | AS29: =IFERROR(AH29/AF29,"") | AT29: =IFERROR(AI29/AH29,"") | AU29: =IFERROR(AN29/AH29,"") | AV29: 13406 | AW29: 1 | AX29: 0 | BC29: =IFERROR(AG29/AC29,"") | BD29: =IFERROR(AG29/(AC29+AA29),"") | BF29: Approx CPO OER ~23% (277,058/1,202,008); not explicitly disclosed. ASP from revenue Rp3,888bn CPO / 290,111 tons ≈ Rp13,407/kg. | BG29: 2022
A30: PT FAP Agri Tbk | B30: 88752 | C30: 77434 | D30: 11318 | E30: 84128 | F30: 4623 | I30: 11.9 | L30: 85420 | N30: 3332 | O30: 6 | Q30: 1 | S30: 0 | AB30: =IFERROR(AA30/AF30,"") | AC30: 1261820 | AG30: 307674 | AH30: 55797 | AI30: 13370 | AN30: 15188 | AO30: =IFERROR(AC30/E30,"") | AP30: =IFERROR(AD30/E30,"") | AQ30: =IFERROR(AG30/E30,"") | AR30: =IFERROR(AG30/AF30,"") | AS30: =IFERROR(AH30/AF30,"") | AT30: =IFERROR(AI30/AH30,"") | AU30: =IFERROR(AN30/AH30,"") | AW30: 1 | AX30: 0 | BC30: =IFERROR(AG30/AC30,"") | BD30: =IFERROR(AG30/(AC30+AA30),"") | BF30: Approx CPO OER ~24.4% (307,674/1,261,820); not explicitly disclosed. | BG30: 2023
A31: PT FAP Agri Tbk | B31: 88701 | C31: 78315 | D31: 10386 | E31: 87633 | F31: 1068 | I31: 13 | L31: 85369 | N31: 3332 | O31: 6 | Q31: 1 | S31: 0 | AB31: =IFERROR(AA31/AF31,"") | AC31: 1312257 | AG31: 297758 | AH31: 52859 | AI31: 13692 | AN31: 15452 | AO31: =IFERROR(AC31/E31,"") | AP31: =IFERROR(AD31/E31,"") | AQ31: =IFERROR(AG31/E31,"") | AR31: =IFERROR(AG31/AF31,"") | AS31: =IFERROR(AH31/AF31,"") | AT31: =IFERROR(AI31/AH31,"") | AU31: =IFERROR(AN31/AH31,"") | AW31: 1 | AX31: 0 | BC31: =IFERROR(AG31/AC31,"") | BD31: =IFERROR(AG31/(AC31+AA31),"") | BF31: Approx CPO OER ~22.7% (297,758/1,312,257); not explicitly disclosed. FFB yield 14.97 t/ha. | BG31: 2024
A32: PT FKS Multi Agro Tbk | AB32: =IFERROR(AA32/AF32,"") | AO32: =IFERROR(AC32/E32,"") | AP32: =IFERROR(AD32/E32,"") | AQ32: =IFERROR(AG32/E32,"") | AR32: =IFERROR(AG32/AF32,"") | AS32: =IFERROR(AH32/AF32,"") | AT32: =IFERROR(AI32/AH32,"") | AU32: =IFERROR(AN32/AH32,"") | BC32: =IFERROR(AG32/AC32,"") | BD32: =IFERROR(AG32/(AC32+AA32),"") | BG32: 2022
A33: PT FKS Multi Agro Tbk | AB33: =IFERROR(AA33/AF33,"") | AO33: =IFERROR(AC33/E33,"") | AP33: =IFERROR(AD33/E33,"") | AQ33: =IFERROR(AG33/E33,"") | AR33: =IFERROR(AG33/AF33,"") | AS33: =IFERROR(AH33/AF33,"") | AT33: =IFERROR(AI33/AH33,"") | AU33: =IFERROR(AN33/AH33,"") | BC33: =IFERROR(AG33/AC33,"") | BD33: =IFERROR(AG33/(AC33+AA33),"") | BG33: 2023
A34: PT FKS Multi Agro Tbk | AB34: =IFERROR(AA34/AF34,"") | AO34: =IFERROR(AC34/E34,"") | AP34: =IFERROR(AD34/E34,"") | AQ34: =IFERROR(AG34/E34,"") | AR34: =IFERROR(AG34/AF34,"") | AS34: =IFERROR(AH34/AF34,"") | AT34: =IFERROR(AI34/AH34,"") | AU34: =IFERROR(AN34/AH34,"") | BC34: =IFERROR(AG34/AC34,"") | BD34: =IFERROR(AG34/(AC34+AA34),"") | BG34: 2024
A35: PT Golden Plantation Tbk | AB35: =IFERROR(AA35/AF35,"") | AO35: =IFERROR(AC35/E35,"") | AP35: =IFERROR(AD35/E35,"") | AQ35: =IFERROR(AG35/E35,"") | AR35: =IFERROR(AG35/AF35,"") | AS35: =IFERROR(AH35/AF35,"") | AT35: =IFERROR(AI35/AH35,"") | AU35: =IFERROR(AN35/AH35,"") | BC35: =IFERROR(AG35/AC35,"") | BD35: =IFERROR(AG35/(AC35+AA35),"") | BG35: 2020
A36: PT Gunanusa Eramandiri Tbk | AB36: =IFERROR(AA36/AF36,"") | AO36: =IFERROR(AC36/E36,"") | AP36: =IFERROR(AD36/E36,"") | AQ36: =IFERROR(AG36/E36,"") | AR36: =IFERROR(AG36/AF36,"") | AS36: =IFERROR(AH36/AF36,"") | AT36: =IFERROR(AI36/AH36,"") | AU36: =IFERROR(AN36/AH36,"") | BC36: =IFERROR(AG36/AC36,"") | BD36: =IFERROR(AG36/(AC36+AA36),"") | BG36: 2024
A37: PT Gozco Plantations Tbk | B37: 12917 | C37: 12917 | D37: 0 | E37: 12700 | F37: 217 | G37: 2918 | H37: 9782 | I37: 16.58 | K37: 11905 | L37: 1012 | O37: 1 | P37: 90 | AA37: 34068 | AB37: =IFERROR(AA37/AF37,"") | AC37: 189719 | AD37: 189719 | AF37: 210847 | AG37: 48841 | AH37: 9517 | AO37: =IFERROR(AC37/E37,"") | AP37: =IFERROR(AD37/E37,"") | AQ37: =IFERROR(AG37/E37,"") | AR37: =IFERROR(AG37/AF37,"") | AS37: =IFERROR(AH37/AF37,"") | AT37: =IFERROR(AI37/AH37,"") | AU37: =IFERROR(AN37/AH37,"") | AV37: 11917 | AW37: 1 | AX37: 0 | BC37: =IFERROR(AG37/AC37,"") | BD37: =IFERROR(AG37/(AC37+AA37),"") | BE37: 0.2316 | BF37: Reported CPO extraction rate 23.16% in 2022 (vs 22.25% 2021). KER 4.51%. | BG37: 2022
A38: PT Gozco Plantations Tbk | B38: 13114 | C38: 13114 | D38: 0 | E38: 12452 | F38: 662 | G38: 2446 | H38: 10005 | I38: 17.33 | J38: 331 | K38: 12102 | L38: 1012 | O38: 1 | P38: 90 | AA38: 28621 | AB38: =IFERROR(AA38/AF38,"") | AC38: 208937 | AD38: 208937 | AF38: 227025 | AG38: 50310 | AH38: 10532 | AO38: =IFERROR(AC38/E38,"") | AP38: =IFERROR(AD38/E38,"") | AQ38: =IFERROR(AG38/E38,"") | AR38: =IFERROR(AG38/AF38,"") | AS38: =IFERROR(AH38/AF38,"") | AT38: =IFERROR(AI38/AH38,"") | AU38: =IFERROR(AN38/AH38,"") | AV38: 11094 | AW38: 1 | AX38: 0 | BC38: =IFERROR(AG38/AC38,"") | BD38: =IFERROR(AG38/(AC38+AA38),"") | BE38: 0.2216 | BF38: Reported CPO extraction rate 22.16% in 2023 (down from 23.16% in 2022). KER 4.64%. PKS SA mill occupancy ~60% (normal 75%). | BG38: 2023
A39: PT Gozco Plantations Tbk | B39: 15596 | C39: 15200 | D39: 396 | E39: 13939 | F39: 1658 | G39: 4801 | H39: 9137 | I39: 16 | J39: 1203 | K39: 11190 | L39: 4406 | O39: 1 | P39: 90 | AA39: 31296 | AB39: =IFERROR(AA39/AF39,"") | AC39: 225259 | AD39: 225259 | AF39: 206772 | AG39: 43934 | AH39: 9123 | AO39: =IFERROR(AC39/E39,"") | AP39: =IFERROR(AD39/E39,"") | AQ39: =IFERROR(AG39/E39,"") | AR39: =IFERROR(AG39/AF39,"") | AS39: =IFERROR(AH39/AF39,"") | AT39: =IFERROR(AI39/AH39,"") | AU39: =IFERROR(AN39/AH39,"") | AV39: 13117 | AW39: 1 | AX39: 0 | BC39: =IFERROR(AG39/AC39,"") | BD39: =IFERROR(AG39/(AC39+AA39),"") | BE39: 0.2125 | BF39: Reported CPO extraction rate (Rendemen) 21.25% in 2024, down from 22.16% in 2023 due to El Nino drought. KER 4.41%. | BG39: 2024
A40: PT Indo Pureco Pratama Tbk | O40: 1 | AB40: =IFERROR(AA40/AF40,"") | AO40: =IFERROR(AC40/E40,"") | AP40: =IFERROR(AD40/E40,"") | AQ40: =IFERROR(AG40/E40,"") | AR40: =IFERROR(AG40/AF40,"") | AS40: =IFERROR(AH40/AF40,"") | AT40: =IFERROR(AI40/AH40,"") | AU40: =IFERROR(AN40/AH40,"") | BC40: =IFERROR(AG40/AC40,"") | BD40: =IFERROR(AG40/(AC40+AA40),"") | BF40: No palm oil operations. IPPE processes coconut (kelapa), not oil palm (kelapa sawit). No plantation area (buys raw copra from third-party suppliers in Riau, Palembang, Jambi, Tangerang, etc.). Single coconut flesh processing factory in Balingbing, Pagaden Barat, Subang, West Java. Subsidiary ALJ holds 13,587 ha location permit in Katingan, Central Kalimantan for horticultural plantation but subsidiary is pre-operating. 2023 product mix by revenue: Crude Coconut Oil (CCO) 86.08% / Copra Meal (Bungkil Kelapa) 13.92%. All sales domestic (Jakarta, Subang, Bekasi, Central Java, Tangerang); no export sales reported. | BG40: 2023
A41: PT Jhonlin Agro Raya Tbk | B41: 10782.99 | C41: 10264.87 | D41: 518.12 | E41: 9370.35 | F41: 894.52 | L41: 10264.87 | O41: 0 | P41: 0 | S41: 1 | AA41: 0 | AB41: =IFERROR(AA41/AF41,"") | AC41: 54299 | AG41: 0 | AH41: 0 | AO41: =IFERROR(AC41/E41,"") | AP41: =IFERROR(AD41/E41,"") | AQ41: =IFERROR(AG41/E41,"") | AR41: =IFERROR(AG41/AF41,"") | AS41: =IFERROR(AH41/AF41,"") | AT41: =IFERROR(AI41/AH41,"") | AU41: =IFERROR(AN41/AH41,"") | AW41: 0.85 | AX41: 0.15 | BC41: =IFERROR(AG41/AC41,"") | BD41: =IFERROR(AG41/(AC41+AA41),"") | BF41: No PKS operating in 2022 - PKS under construction (60 TPH, targeted Dec 2023). Company purchased all CPO from third parties (mainly related parties PG, ACL, BAS, KAM, MSAM). FFB output 54,299 tons (vs 32,576 ton target, 167% achievement). FAME output 308,142 KL (vs 300,000 KL target, 103%); RBDPO/olein/stearin/PFAD/PKE produced via refinery and biodiesel plant. | BG41: 2022
A42: PT Jhonlin Agro Raya Tbk | B42: 17964.7 | C42: 17964.7 | D42: 518.12 | E42: 14961.46 | F42: 3003.24 | L42: 17964.7 | O42: 1 | P42: 60 | S42: 1 | AB42: =IFERROR(AA42/AF42,"") | AC42: 208107 | AO42: =IFERROR(AC42/E42,"") | AP42: =IFERROR(AD42/E42,"") | AQ42: =IFERROR(AG42/E42,"") | AR42: =IFERROR(AG42/AF42,"") | AS42: =IFERROR(AH42/AF42,"") | AT42: =IFERROR(AI42/AH42,"") | AU42: =IFERROR(AN42/AH42,"") | BC42: =IFERROR(AG42/AC42,"") | BD42: =IFERROR(AG42/(AC42+AA42),"") | BF42: PKS (60 TPH) came online late 2023 (commissioning period). FAME output 310,678 KL (vs 333,562 KL target, 93%); FFB 208,107 ton (135% of 154,314 ton target); FAME avg selling price Rp10,985/L (2023) vs Rp12,377/L (2022). Revenue -4% due to lower FAME prices. Merger with PT Jhonlin Agro Lestari 24 Nov 2023 added planting area. | BG42: 2023
A43: PT Jhonlin Agro Raya Tbk | B43: 18226.09 | C43: 17707.97 | D43: 518.12 | E43: 10667.64 | F43: 7558.45 | L43: 18226.09 | O43: 1 | P43: 60 | S43: 1 | AB43: =IFERROR(AA43/AF43,"") | AC43: 159688 | AG43: 40318 | AH43: 7888 | AO43: =IFERROR(AC43/E43,"") | AP43: =IFERROR(AD43/E43,"") | AQ43: =IFERROR(AG43/E43,"") | AR43: =IFERROR(AG43/AF43,"") | AS43: =IFERROR(AH43/AF43,"") | AT43: =IFERROR(AI43/AH43,"") | AU43: =IFERROR(AN43/AH43,"") | AV43: 13120 | AW43: 1 | AX43: 0 | BC43: =IFERROR(AG43/AC43,"") | BD43: =IFERROR(AG43/(AC43+AA43),"") | BF43: PKS (60 TPH) now fully operational; ~15% of total CPO processed internally sourced (up from near-zero in 2022). FAME production 272,596 KL (down from 310,678 KL in 2023); FFB production 159,688 t (65% of 244,080 t target). Target 2025: internal CPO 20-25% of total purchases. | BG43: 2024
A44: PT Jaya Agra Wattie Tbk | B44: 27919 | C44: 21407 | D44: 6512 | E44: 31524 | F44: 12503 | K44: 0 | L44: 29723 | N44: 14304 | O44: 2 | P44: 90 | Q44: 0 | S44: 0 | U44: 0 | W44: 0 | AA44: 153717 | AB44: =IFERROR(AA44/AF44,"") | AC44: 81206 | AD44: 81206 | AF44: 234924 | AG44: 47983 | AH44: 8573 | AI44: 0 | AJ44: 0 | AK44: 0 | AL44: 0 | AM44: 0 | AN44: 0 | AO44: =IFERROR(AC44/E44,"") | AP44: =IFERROR(AD44/E44,"") | AQ44: =IFERROR(AG44/E44,"") | AR44: =IFERROR(AG44/AF44,"") | AS44: =IFERROR(AH44/AF44,"") | AT44: =IFERROR(AI44/AH44,"") | AU44: =IFERROR(AN44/AH44,"") | AV44: 12337 | AW44: 1 | AX44: 0 | BC44: =IFERROR(AG44/AC44,"") | BD44: =IFERROR(AG44/(AC44+AA44),"") | BE44: 0.2042 | BF44: CPO Extraction Rate 20.42% (2021: 20.53%); Kernel Extraction Rate 3.65%; FFB yield 4.94 t/ha (-10%); CPO yield 1.01 t/ha. Palm mills: 2 POMs Kintap + Marabahan; total POM capacity 90 t/hr (513,000 t/y); used 234,924 t (45.79% util). Rubber sheet 9 plants 6,386 t/y (38.15% util); rubber crumb 3 plants 26,040 t/y (48.00% util). All sales domestic. | BG44: 2022
A45: PT Jaya Agra Wattie Tbk | B45: 27919 | C45: 21407 | D45: 6512 | E45: 31673 | F45: 12354 | K45: 0 | L45: 29723 | N45: 14304 | O45: 2 | P45: 90 | Q45: 0 | S45: 0 | U45: 0 | W45: 0 | AA45: 160058 | AB45: =IFERROR(AA45/AF45,"") | AC45: 98357 | AD45: 98357 | AF45: 258416 | AG45: 53447 | AH45: 9534 | AI45: 0 | AJ45: 0 | AK45: 0 | AL45: 0 | AM45: 0 | AN45: 0 | AO45: =IFERROR(AC45/E45,"") | AP45: =IFERROR(AD45/E45,"") | AQ45: =IFERROR(AG45/E45,"") | AR45: =IFERROR(AG45/AF45,"") | AS45: =IFERROR(AH45/AF45,"") | AT45: =IFERROR(AI45/AH45,"") | AU45: =IFERROR(AN45/AH45,"") | AV45: 11039 | AW45: 1 | AX45: 0 | BC45: =IFERROR(AG45/AC45,"") | BD45: =IFERROR(AG45/(AC45+AA45),"") | BE45: 0.2068 | BF45: CPO Extraction Rate 20.68% (2022: 20.42%); Kernel Extraction Rate 3.69%; FFB yield 5.99 t/ha; CPO yield 1.24 t/ha. Palm mills: 2 POMs at Kintap (S.Kalimantan) + Marabahan; design capacity 513,000 t/y; used 258,416 t (50.4% utilization). Rubber sheet 9 plants 6,386 t/y (24.25% util); rubber crumb 3 plants 26,040 t/y (30.7% util). All sales domestic. | BG45: 2023
A46: PT Jaya Agra Wattie Tbk | B46: 27918 | C46: 21407 | D46: 6512 | E46: 31699 | F46: 12288 | K46: 0 | L46: 29723 | N46: 14264 | O46: 2 | P46: 90 | Q46: 0 | S46: 0 | U46: 0 | W46: 0 | AA46: 121298 | AB46: =IFERROR(AA46/AF46,"") | AC46: 105499 | AD46: 105499 | AF46: 226797 | AG46: 44955 | AH46: 7888 | AI46: 0 | AJ46: 0 | AK46: 0 | AL46: 0 | AM46: 0 | AN46: 0 | AO46: =IFERROR(AC46/E46,"") | AP46: =IFERROR(AD46/E46,"") | AQ46: =IFERROR(AG46/E46,"") | AR46: =IFERROR(AG46/AF46,"") | AS46: =IFERROR(AH46/AF46,"") | AT46: =IFERROR(AI46/AH46,"") | AU46: =IFERROR(AN46/AH46,"") | AV46: 13169 | AW46: 1 | AX46: 0 | BC46: =IFERROR(AG46/AC46,"") | BD46: =IFERROR(AG46/(AC46+AA46),"") | BE46: 0.1982 | BF46: CPO Extraction Rate 19.82% (2023: 20.68%); Kernel Extraction Rate 3.48%; FFB yield 6.62 t/ha; CPO yield 1.31 t/ha. Palm mills: 2 POMs (Kintap + Marabahan ABS); design capacity 513,000 t/y; used 226,797 t (44.2% utilization). Rubber crumb 3 plants 26,040 t/y (52.1%); sheet 9 plants 5,487 t/y (31.95%). Tea factory 400 t/y; 1 coffee plant. All sales domestic (Banten, Jabar, Jatim, Jateng, Kalsel). | BG46: 2024
A47: PT Perusahaan Perkebunan London Sumatra Indonesia Tbk | B47: 111240 | C47: 111240 | D47: 35064 | E47: 101306 | F47: 9934 | G47: 2710 | H47: 81033 | I47: 19 | K47: 85373 | L47: 17152 | M47: 5466 | N47: 3249 | O47: 12 | S47: 0 | U47: 0 | W47: 0 | AA47: 243000 | AB47: =IFERROR(AA47/AF47,"") | AC47: 1174000 | AD47: 1174000 | AG47: 306000 | AH47: 88000 | AO47: =IFERROR(AC47/E47,"") | AP47: =IFERROR(AD47/E47,"") | AQ47: =IFERROR(AG47/E47,"") | AR47: =IFERROR(AG47/AF47,"") | AS47: =IFERROR(AH47/AF47,"") | AT47: =IFERROR(AI47/AH47,"") | AU47: =IFERROR(AN47/AH47,"") | AW47: 0.9493 | AX47: 0.0507 | BC47: =IFERROR(AG47/AC47,"") | BD47: =IFERROR(AG47/(AC47+AA47),"") | BF47: OER not disclosed. Implied CPO/FFB ~21.6% (306kt / 1,417kt). | BG47: 2022
A48: PT Perusahaan Perkebunan London Sumatra Indonesia Tbk | B48: 111940 | C48: 111940 | D48: 35417 | E48: 102884 | F48: 9056 | G48: 3229 | H48: 81969 | I48: 19 | K48: 86125 | L48: 17152 | M48: 5486 | N48: 3177 | O48: 12 | S48: 0 | U48: 0 | W48: 0 | AA48: 201000 | AB48: =IFERROR(AA48/AF48,"") | AC48: 1177000 | AD48: 1177000 | AG48: 294000 | AH48: 87000 | AO48: =IFERROR(AC48/E48,"") | AP48: =IFERROR(AD48/E48,"") | AQ48: =IFERROR(AG48/E48,"") | AR48: =IFERROR(AG48/AF48,"") | AS48: =IFERROR(AH48/AF48,"") | AT48: =IFERROR(AI48/AH48,"") | AU48: =IFERROR(AN48/AH48,"") | AW48: 0.9847 | AX48: 0.0153 | BC48: =IFERROR(AG48/AC48,"") | BD48: =IFERROR(AG48/(AC48+AA48),"") | BF48: OER not separately disclosed. Implied CPO/FFB ~21.3% (294kt / 1,377kt). | BG48: 2023
A49: PT Perusahaan Perkebunan London Sumatra Indonesia Tbk | B49: 111367 | C49: 111367 | D49: 35779 | E49: 84941 | F49: 6211 | I49: 19 | K49: 86746 | L49: 15924 | M49: 5480 | N49: 3217 | O49: 12 | S49: 0 | U49: 0 | W49: 0 | AA49: 172000 | AB49: =IFERROR(AA49/AF49,"") | AC49: 1173000 | AD49: 1173000 | AG49: 287000 | AH49: 82000 | AO49: =IFERROR(AC49/E49,"") | AP49: =IFERROR(AD49/E49,"") | AQ49: =IFERROR(AG49/E49,"") | AR49: =IFERROR(AG49/AF49,"") | AS49: =IFERROR(AH49/AF49,"") | AT49: =IFERROR(AI49/AH49,"") | AU49: =IFERROR(AN49/AH49,"") | AV49: 13190 | AW49: 0.9847 | AX49: 0.0153 | BC49: =IFERROR(AG49/AC49,"") | BD49: =IFERROR(AG49/(AC49+AA49),"") | BF49: CPO/FFB processed extraction rate not separately disclosed; implied ~21.3% (287kt CPO / 1,345kt FFB). Domestic CPO price (KPB avg) Rp13,190/kg - proxy for selling price. | BG49: 2024
A50: PT Multi Agro Gemilang Plantation Tbk | AB50: =IFERROR(AA50/AF50,"") | AO50: =IFERROR(AC50/E50,"") | AP50: =IFERROR(AD50/E50,"") | AQ50: =IFERROR(AG50/E50,"") | AR50: =IFERROR(AG50/AF50,"") | AS50: =IFERROR(AH50/AF50,"") | AT50: =IFERROR(AI50/AH50,"") | AU50: =IFERROR(AN50/AH50,"") | BC50: =IFERROR(AG50/AC50,"") | BD50: =IFERROR(AG50/(AC50+AA50),"") | BF50: Operational production data not disclosed in Q1 interim financial statements; no plantation hectarage, FFB, CPO, mill figures published in this interim report. | BG50: 2022
A51: PT Mahkota Group Tbk | B51: 391.29 | C51: 391.29 | E51: 169.72 | F51: 221.57 | O51: 5 | P51: 240 | Q51: 1 | S51: 1 | T51: 495000 | U51: 1 | AA51: 1506111 | AB51: =IFERROR(AA51/AF51,"") | AF51: 1506111 | AG51: 278280 | AH51: 83960 | AI51: 22550 | AJ51: 340060 | AK51: 7690 | AL51: 2440 | AM51: 19610 | AN51: 27340 | AO51: =IFERROR(AC51/E51,"") | AP51: =IFERROR(AD51/E51,"") | AQ51: =IFERROR(AG51/E51,"") | AR51: =IFERROR(AG51/AF51,"") | AS51: =IFERROR(AH51/AF51,"") | AT51: =IFERROR(AI51/AH51,"") | AU51: =IFERROR(AN51/AH51,"") | AW51: 0.76 | AX51: 0.24 | BC51: =IFERROR(AG51/AC51,"") | BD51: =IFERROR(AG51/(AC51+AA51),"") | BF51: Not reported directly. CPO / FFB processed = 278,280 / 1,506,111 = 18.5% (includes 3rd party FFB). | BG51: 2022
A52: PT Mahkota Group Tbk | B52: 427.88 | C52: 427.88 | E52: 166.92 | F52: 260.96 | O52: 5 | P52: 240 | Q52: 1 | S52: 1 | U52: 1 | AA52: 1470215 | AB52: =IFERROR(AA52/AF52,"") | AC52: 694.59 | AF52: 1470215 | AG52: 256930 | AH52: 77230 | AI52: 15730 | AJ52: 274680 | AK52: 9420 | AL52: 3630 | AM52: 15970 | AN52: 19960 | AO52: =IFERROR(AC52/E52,"") | AP52: =IFERROR(AD52/E52,"") | AQ52: =IFERROR(AG52/E52,"") | AR52: =IFERROR(AG52/AF52,"") | AS52: =IFERROR(AH52/AF52,"") | AT52: =IFERROR(AI52/AH52,"") | AU52: =IFERROR(AN52/AH52,"") | AW52: 0.85 | AX52: 0.15 | BC52: =IFERROR(AG52/AC52,"") | BD52: =IFERROR(AG52/(AC52+AA52),"") | BF52: Not reported directly. CPO / FFB processed = 256,930 / 1,470,215 = 17.5% (includes 3rd party FFB). | BG52: 2023
A53: PT Mahkota Group Tbk | B53: 477.85 | C53: 477.85 | O53: 6 | P53: 360 | Q53: 1 | S53: 1 | T53: 1188000 | U53: 1 | AA53: 1132255 | AB53: =IFERROR(AA53/AF53,"") | AC53: 487 | AF53: 1132255 | AG53: 195440 | AH53: 57860 | AI53: 21230 | AJ53: 212470 | AK53: 12460 | AL53: 3660 | AM53: 9330 | AN53: 26650 | AO53: =IFERROR(AC53/E53,"") | AP53: =IFERROR(AD53/E53,"") | AQ53: =IFERROR(AG53/E53,"") | AR53: =IFERROR(AG53/AF53,"") | AS53: =IFERROR(AH53/AF53,"") | AT53: =IFERROR(AI53/AH53,"") | AU53: =IFERROR(AN53/AH53,"") | AW53: 0.76 | AX53: 0.24 | BC53: =IFERROR(AG53/AC53,"") | BD53: =IFERROR(AG53/(AC53+AA53),"") | BF53: Not reported directly in AR; can be approximated as CPO production / FFB processed (195,440 / 1,132,255 = 17.3%) but includes 3rd party FFB. | BG53: 2024
A54: PT Menthobi Karyatama Raya Tbk | B54: 8000 | I54: 10 | O54: 1 | P54: 30 | Q54: 0 | S54: 0 | AA54: 71472 | AB54: =IFERROR(AA54/AF54,"") | AC54: 117967 | AF54: 189912 | AG54: 43729 | AH54: 7453 | AO54: =IFERROR(AC54/E54,"") | AP54: =IFERROR(AD54/E54,"") | AQ54: =IFERROR(AG54/E54,"") | AR54: =IFERROR(AG54/AF54,"") | AS54: =IFERROR(AH54/AF54,"") | AT54: =IFERROR(AI54/AH54,"") | AU54: =IFERROR(AN54/AH54,"") | AV54: 12739 | AW54: 1 | AX54: 0 | BC54: =IFERROR(AG54/AC54,"") | BD54: =IFERROR(AG54/(AC54+AA54),"") | BE54: 0.2302 | BF54: Calculated: CPO 43,729 / FFB processed 189,912 = 23.02%. CPO yield target 17-24% per company. | BG54: 2022
A55: PT Menthobi Karyatama Raya Tbk | C55: 6000 | I55: 10 | O55: 2 | P55: 60 | Q55: 0 | S55: 0 | AA55: 180478 | AB55: =IFERROR(AA55/AF55,"") | AC55: 121778 | AF55: 302317 | AG55: 57803 | AH55: 11149 | AO55: =IFERROR(AC55/E55,"") | AP55: =IFERROR(AD55/E55,"") | AQ55: =IFERROR(AG55/E55,"") | AR55: =IFERROR(AG55/AF55,"") | AS55: =IFERROR(AH55/AF55,"") | AT55: =IFERROR(AI55/AH55,"") | AU55: =IFERROR(AN55/AH55,"") | AV55: 10933 | AW55: 1 | AX55: 0 | BC55: =IFERROR(AG55/AC55,"") | BD55: =IFERROR(AG55/(AC55+AA55),"") | BE55: 0.1912 | BF55: Calculated: CPO 57,803 / FFB processed 302,317 = 19.12% | BG55: 2023
A56: PT Menthobi Karyatama Raya Tbk | B56: 7424.11 | C56: 6000 | I56: 10 | O56: 2 | P56: 30 | Q56: 1 | R56: 2.5 | S56: 0 | AA56: 217660 | AB56: =IFERROR(AA56/AF56,"") | AC56: 100830 | AF56: 318717 | AG56: 69967 | AH56: 13667 | AI56: 3531 | AO56: =IFERROR(AC56/E56,"") | AP56: =IFERROR(AD56/E56,"") | AQ56: =IFERROR(AG56/E56,"") | AR56: =IFERROR(AG56/AF56,"") | AS56: =IFERROR(AH56/AF56,"") | AT56: =IFERROR(AI56/AH56,"") | AU56: =IFERROR(AN56/AH56,"") | AV56: 12932 | AW56: 1 | AX56: 0 | BC56: =IFERROR(AG56/AC56,"") | BD56: =IFERROR(AG56/(AC56+AA56),"") | BE56: 0.2195 | BF56: OER derived: CPO production 69,967 / FFB processed 318,717 = 21.95%. Management states CPO yield 17-24% target on p.81. | BG56: 2024
A57: PT Nusantara Sawit Sejahtera Tbk | B57: 27265 | C57: 26384 | D57: 881 | E57: 25757 | F57: 1508 | L57: 27265 | O57: 1 | P57: 60 | Q57: 0 | S57: 0 | AB57: =IFERROR(AA57/AF57,"") | AC57: 399606 | AF57: 399606 | AG57: 82862 | AH57: 15617 | AO57: =IFERROR(AC57/E57,"") | AP57: =IFERROR(AD57/E57,"") | AQ57: =IFERROR(AG57/E57,"") | AR57: =IFERROR(AG57/AF57,"") | AS57: =IFERROR(AH57/AF57,"") | AT57: =IFERROR(AI57/AH57,"") | AU57: =IFERROR(AN57/AH57,"") | AV57: 12145 | AW57: 1 | AX57: 0 | BC57: =IFERROR(AG57/AC57,"") | BD57: =IFERROR(AG57/(AC57+AA57),"") | BE57: 0.2177 | BF57: OER 21.77% (2022), KER 4.10% | BG57: 2022
A58: PT Nusantara Sawit Sejahtera Tbk | B58: 28148 | C58: 26767 | D58: 1382 | E58: 26175 | F58: 1972 | L58: 28148 | O58: 2 | P58: 120 | Q58: 0 | S58: 0 | AB58: =IFERROR(AA58/AF58,"") | AC58: 463843 | AF58: 463843 | AG58: 91285 | AH58: 18926 | AO58: =IFERROR(AC58/E58,"") | AP58: =IFERROR(AD58/E58,"") | AQ58: =IFERROR(AG58/E58,"") | AR58: =IFERROR(AG58/AF58,"") | AS58: =IFERROR(AH58/AF58,"") | AT58: =IFERROR(AI58/AH58,"") | AU58: =IFERROR(AN58/AH58,"") | AV58: 10796 | AW58: 1 | AX58: 0 | BC58: =IFERROR(AG58/AC58,"") | BD58: =IFERROR(AG58/(AC58+AA58),"") | BE58: 0.2169 | BF58: OER 21.69% (2023), KER 4.62% | BG58: 2023
A59: PT Nusantara Sawit Sejahtera Tbk | B59: 29125 | C59: 27384 | D59: 1741 | E59: 26725 | F59: 2400 | I59: 9.8 | L59: 29125 | O59: 2 | P59: 120 | Q59: 0 | S59: 0 | AB59: =IFERROR(AA59/AF59,"") | AC59: 477288 | AF59: 477288 | AG59: 105570 | AH59: 21062 | AO59: =IFERROR(AC59/E59,"") | AP59: =IFERROR(AD59/E59,"") | AQ59: =IFERROR(AG59/E59,"") | AR59: =IFERROR(AG59/AF59,"") | AS59: =IFERROR(AH59/AF59,"") | AT59: =IFERROR(AI59/AH59,"") | AU59: =IFERROR(AN59/AH59,"") | AV59: 12802 | AW59: 1 | AX59: 0 | BC59: =IFERROR(AG59/AC59,"") | BD59: =IFERROR(AG59/(AC59+AA59),"") | BE59: 0.212 | BF59: Reported OER 21.2% (2024), KER 4.2% | BG59: 2024
A60: PT Indo Oil Perkasa Tbk | O60: 1 | AB60: =IFERROR(AA60/AF60,"") | AO60: =IFERROR(AC60/E60,"") | AP60: =IFERROR(AD60/E60,"") | AQ60: =IFERROR(AG60/E60,"") | AR60: =IFERROR(AG60/AF60,"") | AS60: =IFERROR(AH60/AF60,"") | AT60: =IFERROR(AI60/AH60,"") | AU60: =IFERROR(AN60/AH60,"") | AW60: 0.362 | AX60: 0.638 | BC60: =IFERROR(AG60/AC60,"") | BD60: =IFERROR(AG60/(AC60+AA60),"") | BG60: 2022
A61: PT Indo Oil Perkasa Tbk | O61: 1 | AB61: =IFERROR(AA61/AF61,"") | AO61: =IFERROR(AC61/E61,"") | AP61: =IFERROR(AD61/E61,"") | AQ61: =IFERROR(AG61/E61,"") | AR61: =IFERROR(AG61/AF61,"") | AS61: =IFERROR(AH61/AF61,"") | AT61: =IFERROR(AI61/AH61,"") | AU61: =IFERROR(AN61/AH61,"") | AW61: 0.497 | AX61: 0.503 | BC61: =IFERROR(AG61/AC61,"") | BD61: =IFERROR(AG61/(AC61+AA61),"") | BG61: 2023
A62: PT Indo Oil Perkasa Tbk | O62: 1 | AB62: =IFERROR(AA62/AF62,"") | AO62: =IFERROR(AC62/E62,"") | AP62: =IFERROR(AD62/E62,"") | AQ62: =IFERROR(AG62/E62,"") | AR62: =IFERROR(AG62/AF62,"") | AS62: =IFERROR(AH62/AF62,"") | AT62: =IFERROR(AI62/AH62,"") | AU62: =IFERROR(AN62/AH62,"") | AW62: 0.487 | AX62: 0.513 | BC62: =IFERROR(AG62/AC62,"") | BD62: =IFERROR(AG62/(AC62+AA62),"") | BG62: 2024
A63: PT Pradiksi Gunatama Tbk | B63: 20267 | C63: 16877.18 | D63: 3194.15 | E63: 12396.52 | F63: 4480.66 | L63: 20267 | O63: 1 | P63: 60 | Q63: 0 | S63: 0 | AB63: =IFERROR(AA63/AF63,"") | AC63: 243726 | AG63: 72118 | AH63: 12856 | AO63: =IFERROR(AC63/E63,"") | AP63: =IFERROR(AD63/E63,"") | AQ63: =IFERROR(AG63/E63,"") | AR63: =IFERROR(AG63/AF63,"") | AS63: =IFERROR(AH63/AF63,"") | AT63: =IFERROR(AI63/AH63,"") | AU63: =IFERROR(AN63/AH63,"") | AV63: 12732 | AW63: 1 | AX63: 0 | BC63: =IFERROR(AG63/AC63,"") | BD63: =IFERROR(AG63/(AC63+AA63),"") | BG63: 2022
A64: PT Pradiksi Gunatama Tbk | B64: 26945.33 | C64: 23366.63 | D64: 3578.7 | E64: 19417 | F64: 3336.21 | L64: 20267 | O64: 1 | P64: 90 | Q64: 0 | S64: 0 | AB64: =IFERROR(AA64/AF64,"") | AC64: 306497 | AG64: 71957 | AH64: 13998 | AO64: =IFERROR(AC64/E64,"") | AP64: =IFERROR(AD64/E64,"") | AQ64: =IFERROR(AG64/E64,"") | AR64: =IFERROR(AG64/AF64,"") | AS64: =IFERROR(AH64/AF64,"") | AT64: =IFERROR(AI64/AH64,"") | AU64: =IFERROR(AN64/AH64,"") | AV64: 10900 | AW64: 1 | AX64: 0 | BC64: =IFERROR(AG64/AC64,"") | BD64: =IFERROR(AG64/(AC64+AA64),"") | BG64: 2023
A65: PT Pradiksi Gunatama Tbk | B65: 26620.92 | C65: 22782 | D65: 3839 | E65: 19491 | F65: 3291 | J65: 856 | L65: 22782 | O65: 1 | P65: 90 | Q65: 0 | S65: 0 | AB65: =IFERROR(AA65/AF65,"") | AC65: 223235 | AG65: 53108 | AH65: 9262 | AO65: =IFERROR(AC65/E65,"") | AP65: =IFERROR(AD65/E65,"") | AQ65: =IFERROR(AG65/E65,"") | AR65: =IFERROR(AG65/AF65,"") | AS65: =IFERROR(AH65/AF65,"") | AT65: =IFERROR(AI65/AH65,"") | AU65: =IFERROR(AN65/AH65,"") | AW65: 1 | AX65: 0 | BC65: =IFERROR(AG65/AC65,"") | BD65: =IFERROR(AG65/(AC65+AA65),"") | BG65: 2024
A66: PT Pinago Utama Tbk | B66: 13324 | C66: 13324 | E66: 10649 | F66: 2675 | I66: 14 | K66: 13324 | O66: 1 | P66: 120 | Q66: 0 | S66: 0 | AA66: 279009 | AB66: =IFERROR(AA66/AF66,"") | AC66: 162559 | AD66: 162559 | AE66: 19677 | AF66: 461245 | AG66: 100914 | AH66: 20749 | AO66: =IFERROR(AC66/E66,"") | AP66: =IFERROR(AD66/E66,"") | AQ66: =IFERROR(AG66/E66,"") | AR66: =IFERROR(AG66/AF66,"") | AS66: =IFERROR(AH66/AF66,"") | AT66: =IFERROR(AI66/AH66,"") | AU66: =IFERROR(AN66/AH66,"") | AV66: 12108 | BC66: =IFERROR(AG66/AC66,"") | BD66: =IFERROR(AG66/(AC66+AA66),"") | BG66: 2022
A67: PT Pinago Utama Tbk | B67: 13834 | C67: 13834 | E67: 11183 | F67: 2651 | K67: 13834 | O67: 1 | P67: 120 | Q67: 0 | S67: 0 | AA67: 227544 | AB67: =IFERROR(AA67/AF67,"") | AC67: 179913 | AD67: 179913 | AE67: 30967 | AF67: 438424 | AG67: 99766 | AH67: 19947 | AO67: =IFERROR(AC67/E67,"") | AP67: =IFERROR(AD67/E67,"") | AQ67: =IFERROR(AG67/E67,"") | AR67: =IFERROR(AG67/AF67,"") | AS67: =IFERROR(AH67/AF67,"") | AT67: =IFERROR(AI67/AH67,"") | AU67: =IFERROR(AN67/AH67,"") | AV67: 11096 | BC67: =IFERROR(AG67/AC67,"") | BD67: =IFERROR(AG67/(AC67+AA67),"") | BG67: 2023
A68: PT Pinago Utama Tbk | B68: 15232 | C68: 15232 | E68: 11485 | F68: 3747 | K68: 15232 | O68: 1 | P68: 120 | Q68: 0 | S68: 0 | AA68: 225533 | AB68: =IFERROR(AA68/AF68,"") | AC68: 155246 | AD68: 155246 | AE68: 44550 | AF68: 425023 | AG68: 95507 | AH68: 19025 | AO68: =IFERROR(AC68/E68,"") | AP68: =IFERROR(AD68/E68,"") | AQ68: =IFERROR(AG68/E68,"") | AR68: =IFERROR(AG68/AF68,"") | AS68: =IFERROR(AH68/AF68,"") | AT68: =IFERROR(AI68/AH68,"") | AU68: =IFERROR(AN68/AH68,"") | AV68: 12978 | BC68: =IFERROR(AG68/AC68,"") | BD68: =IFERROR(AG68/(AC68+AA68),"") | BG68: 2024
A69: PT Pulau Subur Tbk | B69: 1091 | C69: 1091 | E69: 995.75 | F69: 94.89 | K69: 1091 | O69: 0 | Q69: 0 | S69: 0 | U69: 0 | W69: 0 | AB69: =IFERROR(AA69/AF69,"") | AC69: 26037 | AD69: 26037 | AO69: =IFERROR(AC69/E69,"") | AP69: =IFERROR(AD69/E69,"") | AQ69: =IFERROR(AG69/E69,"") | AR69: =IFERROR(AG69/AF69,"") | AS69: =IFERROR(AH69/AF69,"") | AT69: =IFERROR(AI69/AH69,"") | AU69: =IFERROR(AN69/AH69,"") | AW69: 1 | AX69: 0 | BC69: =IFERROR(AG69/AC69,"") | BD69: =IFERROR(AG69/(AC69+AA69),"") | BF69: Company sells FFB only (no CPO mill in 2023). IPO proceeds earmarked for 10 tph PKS construction starting 2024. | BG69: 2023
A70: PT Pulau Subur Tbk | B70: 1091 | C70: 1091 | E70: 995.75 | F70: 94.89 | K70: 1091 | O70: 0 | P70: 10 | Q70: 0 | S70: 0 | U70: 0 | W70: 0 | AB70: =IFERROR(AA70/AF70,"") | AC70: 22461 | AD70: 22461 | AG70: 0 | AH70: 0 | AO70: =IFERROR(AC70/E70,"") | AP70: =IFERROR(AD70/E70,"") | AQ70: =IFERROR(AG70/E70,"") | AR70: =IFERROR(AG70/AF70,"") | AS70: =IFERROR(AH70/AF70,"") | AT70: =IFERROR(AI70/AH70,"") | AU70: =IFERROR(AN70/AH70,"") | AW70: 1 | AX70: 0 | BC70: =IFERROR(AG70/AC70,"") | BD70: =IFERROR(AG70/(AC70+AA70),"") | BF70: Company sells FFB only (no milling yet); 10 tph PKS under construction ~70-83% complete, target Q1 2026 operation. | BG70: 2024
A71: PT Sampoerna Agro Tbk | B71: 132660 | C71: 82973 | D71: 49687 | E71: 122047.2 | F71: 10612.8 | I71: 14 | K71: 83000 | L71: 50036 | N71: 35142 | O71: 8 | P71: 515 | S71: 0 | AA71: 133952 | AB71: =IFERROR(AA71/AF71,"") | AC71: 1242866 | AD71: 1242866 | AE71: 670728 | AF71: 1913594 | AG71: 394847 | AH71: 98321 | AO71: =IFERROR(AC71/E71,"") | AP71: =IFERROR(AD71/E71,"") | AQ71: =IFERROR(AG71/E71,"") | AR71: =IFERROR(AG71/AF71,"") | AS71: =IFERROR(AH71/AF71,"") | AT71: =IFERROR(AI71/AH71,"") | AU71: =IFERROR(AN71/AH71,"") | AV71: 12341 | AW71: 1 | AX71: 0 | BC71: =IFERROR(AG71/AC71,"") | BD71: =IFERROR(AG71/(AC71+AA71),"") | BE71: 0.21 | BF71: Reported OER 21.0% in 2022 (high rainfall Q4 caused slight dip). KER not separately disclosed. Palm planted area: Sumatra ~83k ha + Kalimantan ~50k ha = ~133k ha palm; total incl. sago 12,781 ha + rubber 22,361 ha = ~168k ha. Kalimantan FFB contribution 36%; Sumatra 64%. | BG71: 2022
A72: PT Sampoerna Agro Tbk | B72: 132162 | C72: 82123 | D72: 50039 | E72: 117624.18 | F72: 14537.82 | I72: 15 | J72: 10000 | K72: 82000 | L72: 50000 | N72: 35637 | O72: 8 | P72: 515 | Q72: 0 | S72: 0 | AA72: 171015.66 | AB72: =IFERROR(AA72/AF72,"") | AC72: 1259629 | AD72: 1259629 | AE72: 640545 | AF72: 1900174 | AG72: 396927 | AH72: 98984 | AO72: =IFERROR(AC72/E72,"") | AP72: =IFERROR(AD72/E72,"") | AQ72: =IFERROR(AG72/E72,"") | AR72: =IFERROR(AG72/AF72,"") | AS72: =IFERROR(AH72/AF72,"") | AT72: =IFERROR(AI72/AH72,"") | AU72: =IFERROR(AN72/AH72,"") | AV72: 11405 | AW72: 1 | AX72: 0 | BC72: =IFERROR(AG72/AC72,"") | BD72: =IFERROR(AG72/(AC72+AA72),"") | BE72: 0.214 | BF72: Reported OER 21.4% in 2023 (vs 21.0% in 2022). KER not separately disclosed. Palm planted area: Sumatra ~82k ha + Kalimantan ~50k ha = 132k ha palm; total incl. sago 12,781 ha + rubber 22,856 ha = ~167.6k ha. | BG72: 2023
A73: PT Sampoerna Agro Tbk | B73: 128290 | C73: 81733 | D73: 46557 | E73: 108816 | F73: 19348 | I73: 14 | J73: 11200 | K73: 79000 | L73: 49000 | N73: 35901 | O73: 8 | P73: 510 | Q73: 0 | S73: 0 | AA73: 160000 | AB73: =IFERROR(AA73/AF73,"") | AC73: 1167927 | AD73: 1167927 | AE73: 399000 | AF73: 1726376 | AG73: 341287 | AH73: 83827 | AO73: =IFERROR(AC73/E73,"") | AP73: =IFERROR(AD73/E73,"") | AQ73: =IFERROR(AG73/E73,"") | AR73: =IFERROR(AG73/AF73,"") | AS73: =IFERROR(AH73/AF73,"") | AT73: =IFERROR(AI73/AH73,"") | AU73: =IFERROR(AN73/AH73,"") | AV73: 13283 | BC73: =IFERROR(AG73/AC73,"") | BD73: =IFERROR(AG73/(AC73+AA73),"") | BE73: 0.205 | BF73: Reported OER 20.5% in 2024 (vs 21.4% in 2023); KER not separately disclosed. Palm-oil planted area: Sumatra ~79k ha + Kalimantan ~49k ha = 128k ha; Total company planted incl. sago 12,781 ha + rubber 23,120 ha = 164,721 ha. | BG73: 2024
A74: PT Salim Ivomas Pratama Tbk | B74: 294488 | C74: 244768 | D74: 90551 | E74: 218064 | F74: 26704 | G74: 132699 | H74: 85365 | I74: 18 | K74: 188537 | L74: 97235 | M74: 5467 | N74: 3249 | O74: 27 | S74: 5 | T74: 1700000 | AA74: 929000 | AB74: =IFERROR(AA74/AF74,"") | AC74: 2812000 | AD74: 2812000 | AG74: 736000 | AH74: 180000 | AO74: =IFERROR(AC74/E74,"") | AP74: =IFERROR(AD74/E74,"") | AQ74: =IFERROR(AG74/E74,"") | AR74: =IFERROR(AG74/AF74,"") | AS74: =IFERROR(AH74/AF74,"") | AT74: =IFERROR(AI74/AH74,"") | AU74: =IFERROR(AN74/AH74,"") | AV74: 12341 | BC74: =IFERROR(AG74/AC74,"") | BD74: =IFERROR(AG74/(AC74+AA74),"") | BE74: 0.21 | BF74: OER not reported in Ikhtisar Operasional. | BG74: 2022
A75: PT Salim Ivomas Pratama Tbk | B75: 293429 | C75: 244337 | D75: 90867 | E75: 220531 | F75: 23806 | G75: 134833 | H75: 85698 | I75: 19 | K75: 187610 | L75: 97156 | M75: 5486 | N75: 3177 | O75: 27 | S75: 5 | T75: 1700000 | AA75: 848000 | AB75: =IFERROR(AA75/AF75,"") | AC75: 2784000 | AD75: 2784000 | AG75: 708000 | AH75: 175000 | AO75: =IFERROR(AC75/E75,"") | AP75: =IFERROR(AD75/E75,"") | AQ75: =IFERROR(AG75/E75,"") | AR75: =IFERROR(AG75/AF75,"") | AS75: =IFERROR(AH75/AF75,"") | AT75: =IFERROR(AI75/AH75,"") | AU75: =IFERROR(AN75/AH75,"") | AV75: 11273 | AW75: 0.86 | AX75: 0.14 | BC75: =IFERROR(AG75/AC75,"") | BD75: =IFERROR(AG75/(AC75+AA75),"") | BE75: 0.1949 | BF75: OER not reported in Ikhtisar Operasional. | BG75: 2023
A76: PT Salim Ivomas Pratama Tbk | B76: 288649 | C76: 241208 | D76: 91523 | E76: 220318 | F76: 20890 | K76: 188414 | L76: 91538 | M76: 5480 | N76: 3217 | O76: 27 | S76: 5 | T76: 1700000 | AA76: 887000 | AB76: =IFERROR(AA76/AF76,"") | AC76: 2758000 | AD76: 2758000 | AG76: 706000 | AH76: 167000 | AO76: =IFERROR(AC76/E76,"") | AP76: =IFERROR(AD76/E76,"") | AQ76: =IFERROR(AG76/E76,"") | AR76: =IFERROR(AG76/AF76,"") | AS76: =IFERROR(AH76/AF76,"") | AT76: =IFERROR(AI76/AH76,"") | AU76: =IFERROR(AN76/AH76,"") | AV76: 13190 | AW76: 0.861 | AX76: 0.139 | BC76: =IFERROR(AG76/AC76,"") | BD76: =IFERROR(AG76/(AC76+AA76),"") | BF76: OER not reported in 'Ikhtisar Operasional'; rough estimate = CPO 706 / FFB processed ~ n/a (FFB processed not disclosed separately). | BG76: 2024
A77: PT Sinar Mas Agro Resources and Technology Tbk | B77: 136402 | C77: 105030 | D77: 31372 | E77: 129615 | F77: 7187 | G77: 85990 | H77: 34390 | J77: 2800 | O77: 16 | S77: 4 | T77: 2900000 | V77: 810000 | AB77: =IFERROR(AA77/AF77,"") | AC77: 1950842 | AD77: 1925000 | AE77: 557000 | AF77: 4350000 | AG77: 572000 | AH77: 157000 | AO77: =IFERROR(AC77/E77,"") | AP77: =IFERROR(AD77/E77,"") | AQ77: =IFERROR(AG77/E77,"") | AR77: =IFERROR(AG77/AF77,"") | AS77: =IFERROR(AH77/AF77,"") | AT77: =IFERROR(AI77/AH77,"") | AU77: =IFERROR(AN77/AH77,"") | AV77: 18488 | BC77: =IFERROR(AG77/AC77,"") | BD77: =IFERROR(AG77/(AC77+AA77),"") | BE77: 0.208 | BF77: Oil extraction rate 20.8%; Kernel extraction rate 5.7%. Avg CPO FOB Belawan US$1,248/t x avg FX Rp14,814/US$ = ~Rp18,488/kg implied. | BG77: 2022
A78: PT Sinar Mas Agro Resources and Technology Tbk | B78: 134177 | C78: 103316 | D78: 30861 | E78: 126343 | F78: 7834 | G78: 77494 | H78: 38953 | J78: 3200 | O78: 16 | S78: 4 | T78: 2900000 | V78: 819000 | AA78: 314528 | AB78: =IFERROR(AA78/AF78,"") | AC78: 1849591 | AD78: 1850000 | AE78: 560000 | AF78: 4350000 | AG78: 567000 | AH78: 155000 | AO78: =IFERROR(AC78/E78,"") | AP78: =IFERROR(AD78/E78,"") | AQ78: =IFERROR(AG78/E78,"") | AR78: =IFERROR(AG78/AF78,"") | AS78: =IFERROR(AH78/AF78,"") | AT78: =IFERROR(AI78/AH78,"") | AU78: =IFERROR(AN78/AH78,"") | AV78: 13734 | AW78: 0.5653 | AX78: 0.4347 | BC78: =IFERROR(AG78/AC78,"") | BD78: =IFERROR(AG78/(AC78+AA78),"") | BE78: 0.208 | BF78: Oil extraction rate 20.8%; Kernel extraction rate 5.7%. Avg CPO FOB Belawan US$901/t x avg FX Rp15,243/US$ = ~Rp13,734/kg implied. | BG78: 2023
A79: PT Sinar Mas Agro Resources and Technology Tbk | B79: 136587 | C79: 105172 | D79: 31415 | E79: 123260 | F79: 13227 | G79: 71581 | H79: 41665 | J79: 7900 | K79: 62830 | L79: 73757 | O79: 16 | Q79: 4 | S79: 4 | T79: 2880000 | V79: 879000 | AB79: =IFERROR(AA79/AF79,"") | AC79: 1741349 | AD79: 1741000 | AE79: 501000 | AF79: 4350000 | AG79: 532000 | AH79: 145000 | AO79: =IFERROR(AC79/E79,"") | AP79: =IFERROR(AD79/E79,"") | AQ79: =IFERROR(AG79/E79,"") | AR79: =IFERROR(AG79/AF79,"") | AS79: =IFERROR(AH79/AF79,"") | AT79: =IFERROR(AI79/AH79,"") | AU79: =IFERROR(AN79/AH79,"") | AV79: 15906 | AW79: 0.58 | AX79: 0.42 | BC79: =IFERROR(AG79/AC79,"") | BD79: =IFERROR(AG79/(AC79+AA79),"") | BE79: 0.203 | BF79: Oil extraction rate 20.3%; Kernel extraction rate 5.5%. Avg CPO FOB Belawan US$1,005/t x avg FX Rp15,827/US$ = ~Rp15,906/kg implied. | BG79: 2024
A80: PT Sawit Sumbermas Sarana Tbk | B80: 82465.72 | C80: 69167.06 | D80: 13238.67 | E80: 81405 | F80: 1060 | K80: 0 | L80: 115880 | M80: 0 | N80: 0 | O80: 8 | P80: 540 | Q80: 1 | R80: 25 | S80: 1 | T80: 850000 | U80: 0 | W80: 0 | AA80: 571063 | AB80: =IFERROR(AA80/AF80,"") | AC80: 1723170 | AD80: 1723170 | AE80: 94226 | AF80: 2345131 | AG80: 518819 | AH80: 99082 | AI80: 22327 | AJ80: 746544 | AK80: 584864 | AL80: 137360 | AM80: 29323 | AN80: 34448 | AO80: =IFERROR(AC80/E80,"") | AP80: =IFERROR(AD80/E80,"") | AQ80: =IFERROR(AG80/E80,"") | AR80: =IFERROR(AG80/AF80,"") | AS80: =IFERROR(AH80/AF80,"") | AT80: =IFERROR(AI80/AH80,"") | AU80: =IFERROR(AN80/AH80,"") | BC80: =IFERROR(AG80/AC80,"") | BD80: =IFERROR(AG80/(AC80+AA80),"") | BE80: 0.221 | BF80: Reported OER 22.1% for 2023 (per 2024 AR MDA comparison). Refinery utilization 91.77% (very high vs 47.48% in 2024). Fractionation 84.95%; KCP 35.81%. 2023 was peak downstream year pre-demand softening. | BG80: 2023
A81: PT Sawit Sumbermas Sarana Tbk | B81: 115571 | C81: 93224 | D81: 22347 | E81: 81604 | F81: 925 | K81: 0 | L81: 115571 | M81: 0 | N81: 0 | O81: 8 | P81: 540 | Q81: 2 | R81: 25 | S81: 1 | T81: 850000 | U81: 0 | W81: 0 | AA81: 488647 | AB81: =IFERROR(AA81/AF81,"") | AC81: 1562446 | AD81: 1562446 | AE81: 134421 | AF81: 2118160 | AG81: 461414 | AH81: 89833 | AI81: 20388 | AJ81: 387457 | AK81: 296405 | AL81: 67660 | AM81: 15064 | AN81: 28086 | AO81: =IFERROR(AC81/E81,"") | AP81: =IFERROR(AD81/E81,"") | AQ81: =IFERROR(AG81/E81,"") | AR81: =IFERROR(AG81/AF81,"") | AS81: =IFERROR(AH81/AF81,"") | AT81: =IFERROR(AI81/AH81,"") | AU81: =IFERROR(AN81/AH81,"") | BC81: =IFERROR(AG81/AC81,"") | BD81: =IFERROR(AG81/(AC81+AA81),"") | BE81: 0.218 | BF81: Reported OER 21.8% (p.108 MDA: 'Oil Extraction Rate (OER) tahun 2024 tercatat sebesar 21,8%'). Refinery yield RBDPO 95.82%, PFAD 3.62%; Fractionation yield Olein 81.42%, Stearin 18.58%. Refinery utilization 47.48%, fractionation 42.71%, KCP 25.51%. | BG81: 2024
A82: PT Sawit Sumbermas Sarana Tbk | B82: 136447 | C82: 77314 | D82: 17500 | E82: 93726 | F82: 1221 | K82: 0 | L82: 136447 | M82: 0 | N82: 0 | O82: 10 | P82: 675 | Q82: 1 | R82: 25 | S82: 1 | T82: 850000 | U82: 0 | W82: 0 | AA82: 596153 | AB82: =IFERROR(AA82/AF82,"") | AC82: 1628452 | AD82: 1628452 | AE82: 178559 | AF82: 2382942 | AG82: 527052 | AH82: 104130 | AI82: 15379 | AJ82: 569213 | AK82: 467934 | AL82: 101221 | AM82: 21913 | AN82: 37506 | AO82: =IFERROR(AC82/E82,"") | AP82: =IFERROR(AD82/E82,"") | AQ82: =IFERROR(AG82/E82,"") | AR82: =IFERROR(AG82/AF82,"") | AS82: =IFERROR(AH82/AF82,"") | AT82: =IFERROR(AI82/AH82,"") | AU82: =IFERROR(AN82/AH82,"") | AW82: 0.2583 | AX82: 0.7417 | BC82: =IFERROR(AG82/AC82,"") | BD82: =IFERROR(AG82/(AC82+AA82),"") | BE82: 0.2212 | BF82: Reported OER 22.12% (p.131: 'Oil Extraction Rate (OER) of 22.12%'). Refinery utilization 71.02% (recovery from 47.62% in 2024). Fractionation 66.97%; KCP 50.66%. Refinery yield RBDPO 95.90%, PFAD 3.63%; Fractionation yield Olein 82.21%, Stearin 17.78%. | BG82: 2025
A83: PT Triputra Agro Persada Tbk | B83: 160500 | C83: 136400 | D83: 24100 | E83: 129221 | F83: 7164 | G83: 3880 | H83: 7155 | K83: 5515 | L83: 130870 | O83: 18 | P83: 995 | Q83: 1 | S83: 0 | U83: 0 | AA83: 820000 | AB83: =IFERROR(AA83/AF83,"") | AC83: 3050000 | AD83: 3050000 | AE83: 348000 | AF83: 4203000 | AG83: 978000 | AH83: 208000 | AI83: 6500 | AO83: =IFERROR(AC83/E83,"") | AP83: =IFERROR(AD83/E83,"") | AQ83: =IFERROR(AG83/E83,"") | AR83: =IFERROR(AG83/AF83,"") | AS83: =IFERROR(AH83/AF83,"") | AT83: =IFERROR(AI83/AH83,"") | AU83: =IFERROR(AN83/AH83,"") | AV83: 11115 | BC83: =IFERROR(AG83/AC83,"") | BD83: =IFERROR(AG83/(AC83+AA83),"") | BE83: 0.233 | BF83: Rendemen CPO 23.3% (incl associates). Rendemen PK (KER) 4.9%. | BG83: 2023
A84: PT Triputra Agro Persada Tbk | B84: 160800 | C84: 135600 | D84: 25200 | E84: 128178 | F84: 7416 | G84: 4375 | H84: 6796 | K84: 5578 | L84: 130016 | O84: 18 | P84: 995 | Q84: 1 | S84: 0 | U84: 0 | AA84: 679000 | AB84: =IFERROR(AA84/AF84,"") | AC84: 2946000 | AD84: 2946000 | AE84: 330000 | AF84: 3962000 | AG84: 916000 | AH84: 193000 | AI84: 20300 | AO84: =IFERROR(AC84/E84,"") | AP84: =IFERROR(AD84/E84,"") | AQ84: =IFERROR(AG84/E84,"") | AR84: =IFERROR(AG84/AF84,"") | AS84: =IFERROR(AH84/AF84,"") | AT84: =IFERROR(AI84/AH84,"") | AU84: =IFERROR(AN84/AH84,"") | AV84: 13156 | BC84: =IFERROR(AG84/AC84,"") | BD84: =IFERROR(AG84/(AC84+AA84),"") | BE84: 0.231 | BF84: Rendemen CPO 23.1% (incl associates). Rendemen PK (KER) 4.9%. | BG84: 2024
A85: PT Triputra Agro Persada Tbk | B85: 159700 | C85: 132800 | D85: 26900 | E85: 125201 | F85: 7613 | G85: 4853 | H85: 4544 | K85: 5376 | L85: 127438 | O85: 18 | P85: 995 | Q85: 1 | S85: 0 | U85: 0 | AA85: 659000 | AB85: =IFERROR(AA85/AF85,"") | AC85: 3040000 | AD85: 3040000 | AE85: 384000 | AF85: 4089000 | AG85: 953000 | AH85: 202000 | AI85: 22100 | AO85: =IFERROR(AC85/E85,"") | AP85: =IFERROR(AD85/E85,"") | AQ85: =IFERROR(AG85/E85,"") | AR85: =IFERROR(AG85/AF85,"") | AS85: =IFERROR(AH85/AF85,"") | AT85: =IFERROR(AI85/AH85,"") | AU85: =IFERROR(AN85/AH85,"") | AV85: 14220 | BC85: =IFERROR(AG85/AC85,"") | BD85: =IFERROR(AG85/(AC85+AA85),"") | BE85: 0.233 | BF85: Rendemen CPO 23.3% (incl associates). Rendemen PK (KER) 4.9%. | BG85: 2025
A86: PT Teladan Prima Agro Tbk | B86: 60497 | C86: 48524 | D86: 11973 | E86: 59937 | F86: 560 | I86: 14.5 | L86: 60497 | O86: 6 | P86: 335 | Q86: 0 | S86: 0 | AA86: 196484 | AB86: =IFERROR(AA86/AF86,"") | AC86: 1068338 | AD86: 1068338 | AE86: 144730 | AF86: 1409552 | AG86: 327688 | AH86: 52207 | AO86: =IFERROR(AC86/E86,"") | AP86: =IFERROR(AD86/E86,"") | AQ86: =IFERROR(AG86/E86,"") | AR86: =IFERROR(AG86/AF86,"") | AS86: =IFERROR(AH86/AF86,"") | AT86: =IFERROR(AI86/AH86,"") | AU86: =IFERROR(AN86/AH86,"") | AV86: 10959 | AW86: 1 | AX86: 0 | BC86: =IFERROR(AG86/AC86,"") | BD86: =IFERROR(AG86/(AC86+AA86),"") | BE86: 0.232 | BF86: Reported CPO Extraction Rate 23.2% (p.14 'Tingkat Ekstraksi Minyak Kelapa Sawit'); PK extraction 3.7%. | BG86: 2023
A87: PT Teladan Prima Agro Tbk | B87: 60515 | C87: 48542 | D87: 11973 | E87: 59165 | F87: 260 | I87: 15.5 | L87: 60515 | O87: 6 | P87: 335 | Q87: 1 | R87: 4.17 | S87: 0 | AA87: 162383 | AB87: =IFERROR(AA87/AF87,"") | AC87: 1071173 | AD87: 1071173 | AE87: 148121 | AF87: 1381677 | AG87: 324857 | AH87: 50787 | AI87: 5262 | AN87: 6862 | AO87: =IFERROR(AC87/E87,"") | AP87: =IFERROR(AD87/E87,"") | AQ87: =IFERROR(AG87/E87,"") | AR87: =IFERROR(AG87/AF87,"") | AS87: =IFERROR(AH87/AF87,"") | AT87: =IFERROR(AI87/AH87,"") | AU87: =IFERROR(AN87/AH87,"") | AV87: 12230 | AW87: 1 | AX87: 0 | BC87: =IFERROR(AG87/AC87,"") | BD87: =IFERROR(AG87/(AC87+AA87),"") | BE87: 0.235 | BF87: Reported CPO Extraction Rate 23.5% (p.12 'Tingkat Ekstraksi Minyak Kelapa Sawit'); PK extraction 3.7%; new PKO extraction 40.0% from newly commissioned KCP. | BG87: 2024
A88: PT Teladan Prima Agro Tbk | B88: 64430 | C88: 51960 | D88: 12470 | E88: 63975 | F88: 455 | I88: 16.1 | L88: 64430 | O88: 6 | P88: 335 | Q88: 1 | R88: 4.17 | S88: 0 | AA88: 192405 | AB88: =IFERROR(AA88/AF88,"") | AC88: 1109558 | AD88: 1109558 | AE88: 161476 | AF88: 1463439 | AG88: 333092 | AH88: 52197 | AI88: 11991 | AN88: 15803 | AO88: =IFERROR(AC88/E88,"") | AP88: =IFERROR(AD88/E88,"") | AQ88: =IFERROR(AG88/E88,"") | AR88: =IFERROR(AG88/AF88,"") | AS88: =IFERROR(AH88/AF88,"") | AT88: =IFERROR(AI88/AH88,"") | AU88: =IFERROR(AN88/AH88,"") | AV88: 14004 | AW88: 1 | AX88: 0 | BC88: =IFERROR(AG88/AC88,"") | BD88: =IFERROR(AG88/(AC88+AA88),"") | BE88: 0.2276 | BF88: Reported CPO Extraction Rate 22.76% (p.12 'Tingkat Ekstraksi Minyak Kelapa Sawit'); PK extraction 3.57%; CPKO extraction 41.0%. | BG88: 2025
A89: PT Bakrie Sumatera Plantations Tbk | B89: 52192 | C89: 37217 | D89: 14975 | E89: 45968 | F89: 6346 | K89: 62583 | L89: 411 | M89: 0 | N89: 3222 | O89: 5 | P89: 240 | Q89: 1 | S89: 1 | T89: 495000 | U89: 1 | V89: 165000 | W89: 0 | AB89: =IFERROR(AA89/AF89,"") | AC89: 376655 | AG89: 154701 | AH89: 36488 | AO89: =IFERROR(AC89/E89,"") | AP89: =IFERROR(AD89/E89,"") | AQ89: =IFERROR(AG89/E89,"") | AR89: =IFERROR(AG89/AF89,"") | AS89: =IFERROR(AH89/AF89,"") | AT89: =IFERROR(AI89/AH89,"") | AU89: =IFERROR(AN89/AH89,"") | AW89: 0.6934 | AX89: 0.3066 | BC89: =IFERROR(AG89/AC89,"") | BD89: =IFERROR(AG89/(AC89+AA89),"") | BF89: OER not explicitly disclosed in 2022 AR narrative. | BG89: 2022
A90: PT Bakrie Sumatera Plantations Tbk | B90: 54828 | C90: 39853 | D90: 14975 | E90: 62677 | F90: 7036 | K90: 65119 | L90: 411 | M90: 0 | N90: 3222 | O90: 5 | P90: 240 | Q90: 1 | S90: 1 | T90: 495000 | U90: 1 | V90: 165000 | W90: 0 | AB90: =IFERROR(AA90/AF90,"") | AC90: 366113 | AG90: 123628 | AH90: 28591 | AO90: =IFERROR(AC90/E90,"") | AP90: =IFERROR(AD90/E90,"") | AQ90: =IFERROR(AG90/E90,"") | AR90: =IFERROR(AG90/AF90,"") | AS90: =IFERROR(AH90/AF90,"") | AT90: =IFERROR(AI90/AH90,"") | AU90: =IFERROR(AN90/AH90,"") | AW90: 0.9369 | AX90: 0.0631 | BC90: =IFERROR(AG90/AC90,"") | BD90: =IFERROR(AG90/(AC90+AA90),"") | BF90: OER not explicitly disclosed in 2023 AR narrative. | BG90: 2023
A91: PT Bakrie Sumatera Plantations Tbk | B91: 56147 | C91: 43745 | D91: 14975 | E91: 43869 | F91: 12278 | K91: 51776 | L91: 411 | M91: 0 | N91: 3222 | O91: 5 | P91: 240 | Q91: 0 | S91: 0 | U91: 0 | W91: 0 | AB91: =IFERROR(AA91/AF91,"") | AC91: 347865 | AG91: 113918 | AH91: 24263 | AO91: =IFERROR(AC91/E91,"") | AP91: =IFERROR(AD91/E91,"") | AQ91: =IFERROR(AG91/E91,"") | AR91: =IFERROR(AG91/AF91,"") | AS91: =IFERROR(AH91/AF91,"") | AT91: =IFERROR(AI91/AH91,"") | AU91: =IFERROR(AN91/AH91,"") | AW91: 0.9738 | AX91: 0.0262 | BC91: =IFERROR(AG91/AC91,"") | BD91: =IFERROR(AG91/(AC91+AA91),"") | BF91: OER not explicitly disclosed in 2024 AR narrative. | BG91: 2024
A92: PT Wahana Pronatural Tbk | AB92: =IFERROR(AA92/AF92,"") | AO92: =IFERROR(AC92/E92,"") | AP92: =IFERROR(AD92/E92,"") | AQ92: =IFERROR(AG92/E92,"") | AR92: =IFERROR(AG92/AF92,"") | AS92: =IFERROR(AH92/AF92,"") | AT92: =IFERROR(AI92/AH92,"") | AU92: =IFERROR(AN92/AH92,"") | BC92: =IFERROR(AG92/AC92,"") | BD92: =IFERROR(AG92/(AC92+AA92),"") | BF92: Not applicable - company does not operate oil palm plantations, palm oil mills, or any palm-related processing. | BG92: 2022
A93: PT Wahana Pronatural Tbk | AB93: =IFERROR(AA93/AF93,"") | AO93: =IFERROR(AC93/E93,"") | AP93: =IFERROR(AD93/E93,"") | AQ93: =IFERROR(AG93/E93,"") | AR93: =IFERROR(AG93/AF93,"") | AS93: =IFERROR(AH93/AF93,"") | AT93: =IFERROR(AI93/AH93,"") | AU93: =IFERROR(AN93/AH93,"") | BC93: =IFERROR(AG93/AC93,"") | BD93: =IFERROR(AG93/(AC93+AA93),"") | BF93: Not applicable - company does not operate oil palm plantations, palm oil mills, or any palm-related processing. | BG93: 2023
A94: PT Wahana Pronatural Tbk | AB94: =IFERROR(AA94/AF94,"") | AO94: =IFERROR(AC94/E94,"") | AP94: =IFERROR(AD94/E94,"") | AQ94: =IFERROR(AG94/E94,"") | AR94: =IFERROR(AG94/AF94,"") | AS94: =IFERROR(AH94/AF94,"") | AT94: =IFERROR(AI94/AH94,"") | AU94: =IFERROR(AN94/AH94,"") | BC94: =IFERROR(AG94/AC94,"") | BD94: =IFERROR(AG94/(AC94+AA94),"") | BF94: Not applicable - WAPO does not operate oil palm plantations, palm oil mills, or any palm-related processing. Coffee-bean trading volume was 30,000 t and dried seaweed trading volume was 1,200 t in 2024. | BG94: 2024
AB95: =IFERROR(AA95/AF95,"") | AO95: =IFERROR(AC95/E95,"") | AP95: =IFERROR(AD95/E95,"") | AQ95: =IFERROR(AG95/E95,"") | AR95: =IFERROR(AG95/AF95,"") | AS95: =IFERROR(AH95/AF95,"") | AT95: =IFERROR(AI95/AH95,"") | AU95: =IFERROR(AN95/AH95,"") | BC95: =IFERROR(AG95/AC95,"") | BD95: =IFERROR(AG95/(AC95+AA95),"")
AB96: =IFERROR(AA96/AF96,"") | AO96: =IFERROR(AC96/E96,"") | AP96: =IFERROR(AD96/E96,"") | AQ96: =IFERROR(AG96/E96,"") | AR96: =IFERROR(AG96/AF96,"") | AS96: =IFERROR(AH96/AF96,"") | AT96: =IFERROR(AI96/AH96,"") | AU96: =IFERROR(AN96/AH96,"") | BC96: =IFERROR(AG96/AC96,"") | BD96: =IFERROR(AG96/(AC96+AA96),"")
AB97: =IFERROR(AA97/AF97,"") | AO97: =IFERROR(AC97/E97,"") | AP97: =IFERROR(AD97/E97,"") | AQ97: =IFERROR(AG97/E97,"") | AR97: =IFERROR(AG97/AF97,"") | AS97: =IFERROR(AH97/AF97,"") | AT97: =IFERROR(AI97/AH97,"") | AU97: =IFERROR(AN97/AH97,"") | BC97: =IFERROR(AG97/AC97,"") | BD97: =IFERROR(AG97/(AC97+AA97),"")
AB98: =IFERROR(AA98/AF98,"") | AO98: =IFERROR(AC98/E98,"") | AP98: =IFERROR(AD98/E98,"") | AQ98: =IFERROR(AG98/E98,"") | AR98: =IFERROR(AG98/AF98,"") | AS98: =IFERROR(AH98/AF98,"") | AT98: =IFERROR(AI98/AH98,"") | AU98: =IFERROR(AN98/AH98,"") | BC98: =IFERROR(AG98/AC98,"") | BD98: =IFERROR(AG98/(AC98+AA98),"")
AB99: =IFERROR(AA99/AF99,"") | AO99: =IFERROR(AC99/E99,"") | AP99: =IFERROR(AD99/E99,"") | AQ99: =IFERROR(AG99/E99,"") | AR99: =IFERROR(AG99/AF99,"") | AS99: =IFERROR(AH99/AF99,"") | AT99: =IFERROR(AI99/AH99,"") | AU99: =IFERROR(AN99/AH99,"") | BC99: =IFERROR(AG99/AC99,"") | BD99: =IFERROR(AG99/(AC99+AA99),"")
AB100: =IFERROR(AA100/AF100,"") | AO100: =IFERROR(AC100/E100,"") | AP100: =IFERROR(AD100/E100,"") | AQ100: =IFERROR(AG100/E100,"") | AR100: =IFERROR(AG100/AF100,"") | AS100: =IFERROR(AH100/AF100,"") | AT100: =IFERROR(AI100/AH100,"") | AU100: =IFERROR(AN100/AH100,"") | BC100: =IFERROR(AG100/AC100,"") | BD100: =IFERROR(AG100/(AC100+AA100),"")
...

Sheet Financials
A1: Company | B1: Report Year | C1: Revenue (IDR bn) | D1: Gross Profit (IDR bn) | E1: EBITDA Reported (IDR bn) (manual) | F1: EBIT (IDR bn) (manual) | G1: Net Profit (IDR bn) | H1: Profit Attributable to Parent (IDR bn) | I1: Total Assets (IDR bn) | J1: Current Assets (IDR bn) | K1: Non-Current Assets (IDR bn) | L1: Total Liabilities (IDR bn) | M1: Current Liabilities (IDR bn) | N1: Long-Term Liabilities (IDR bn) | O1: Total Equity (IDR bn) | P1: Net Working Capital (IDR bn) [auto] | Q1: Cash & Cash Equivalents (IDR bn) | R1: Gross Debt (IDR bn) | S1: Net Debt Calculated (IDR bn) [auto = R-Q] | T1: CFO (IDR bn) | U1: Capex (IDR bn) (manual; Net Fixed Asset + Bearer Plant Increase, NOT Investing CF) | V1: FCF (IDR bn) [auto] | W1: Shares Outstanding (mn) | X1: EPS (local ccy/share) | Y1: NAV per Share (local ccy/share) | Z1: Interim DPS (local ccy/share) | AA1: Final DPS (local ccy/share) | AB1: Closing Price (local ccy/share) | AC1: Market Cap (IDR bn) [auto] | AD1: Current Ratio (x) [auto] | AE1: Debt / Assets (x) [auto] | AF1: Debt / Equity (x) [auto] | AG1: ROA Reported (%) [auto] | AH1: ROE Reported (%) [auto] | AI1: Net Margin Reported (%) [auto] | AJ1: Gross Margin Reported (%) [auto] | AK1: Financial Risk Note | AL1: Liquidity Note | AM1: Debt Maturity Note | AN1: Covenant Note | AO1: D&A Total (IDR bn) (manual; from Notes) | AP1: EBITDA Calculated (IDR bn) [auto = F+AO] | AQ1: EBITDA Variance (IDR bn) [auto = E-AP] | AR1: Net Debt Reported (IDR bn) (manual) | AS1: Net Debt Variance (IDR bn) [auto = AR-S] | AT1: Net Debt Reported - Definition Note (manual)
A2: PT Astra Agro Lestari Tbk | B2: 2023 | C2: 20745 | D2: 2771 | F2: 1251.22 | G2: 1088 | H2: 1056 | I2: 28846 | J2: 7118 | K2: 21728 | L2: 6280 | M2: 3882 | N2: 2398 | O2: 22566 | P2: =IFERROR(J2-M2,"") | Q2: 2089.51 | R2: 4005.05 | S2: =IFERROR(R2-Q2,"") | T2: 2538.74 | U2: 1236.34 | V2: =IFERROR(T2-U2,"") | W2: 1925 | X2: 549 | Y2: 11724 | Z2: 82 | AA2: 319 | AB2: 7025 | AC2: =IFERROR(W2*AB2/1000,"") | AD2: =IFERROR(J2/M2,"") | AE2: =IFERROR(R2/I2,"") | AF2: =IFERROR(R2/O2,"") | AG2: =IFERROR(G2/I2,"") | AH2: =IFERROR(G2/O2,"") | AI2: =IFERROR(G2/C2,"") | AJ2: =IFERROR(D2/C2,"") | AP2: =IFERROR(IF(AND(NOT(ISNUMBER(F2)),NOT(ISNUMBER(AO2))),"",F2+AO2),"") | AQ2: =IFERROR(IF(OR(NOT(ISNUMBER(E2)),NOT(ISNUMBER(AP2))),"",E2-AP2),"") | AS2: =IFERROR(IF(OR(NOT(ISNUMBER(AR2)),NOT(ISNUMBER(S2))),"",AR2-S2),"")
A3: PT Astra Agro Lestari Tbk | B3: 2024 | C3: 21815 | D3: 3341 | F3: 1658 | G3: 1187 | H3: 1148 | I3: 28793 | J3: 8434 | K3: 20360 | L3: 5591 | M3: 3238 | N3: 2354 | O3: 23202 | P3: =IFERROR(J3-M3,"") | Q3: 3236 | R3: 3190 | S3: =IFERROR(R3-Q3,"") | T3: 3380 | U3: 941 | V3: =IFERROR(T3-U3,"") | W3: 1925 | X3: 596 | Y3: 12055 | Z3: 84 | AA3: 165 | AB3: 6200 | AC3: =IFERROR(W3*AB3/1000,"") | AD3: =IFERROR(J3/M3,"") | AE3: =IFERROR(R3/I3,"") | AF3: =IFERROR(R3/O3,"") | AG3: =IFERROR(G3/I3,"") | AH3: =IFERROR(G3/O3,"") | AI3: =IFERROR(G3/C3,"") | AJ3: =IFERROR(D3/C3,"") | AP3: =IFERROR(IF(AND(NOT(ISNUMBER(F3)),NOT(ISNUMBER(AO3))),"",F3+AO3),"") | AQ3: =IFERROR(IF(OR(NOT(ISNUMBER(E3)),NOT(ISNUMBER(AP3))),"",E3-AP3),"") | AS3: =IFERROR(IF(OR(NOT(ISNUMBER(AR3)),NOT(ISNUMBER(S3))),"",AR3-S3),"") | AT3: Reported gearing <1% in 2024 (2023: 9%); Net debt = Gross debt (Rp3,189.54 bn = 1,689.54 current + 1,500 LT) - cash (Rp3,236 bn) = negative net debt.
A4: PT Astra Agro Lestari Tbk | B4: 2025 | C4: 28654.648 | D4: 4631.429 | F4: 2086.194 | G4: 1471.714 | H4: 1472 | I4: 27047.104 | J4: 8663 | K4: 18384 | L4: 2889.47 | M4: 2000 | N4: 889 | O4: 24157.634 | P4: =IFERROR(J4-M4,"") | Q4: 2755.715 | R4: 0 | S4: =IFERROR(R4-Q4,"") | T4: 4210 | U4: 782 | V4: =IFERROR(T4-U4,"") | W4: 1925 | X4: 765 | Y4: 12551 | Z4: 123 | AB4: 7375 | AC4: =IFERROR(W4*AB4/1000,"") | AD4: =IFERROR(J4/M4,"") | AE4: =IFERROR(R4/I4,"") | AF4: =IFERROR(R4/O4,"") | AG4: =IFERROR(G4/I4,"") | AH4: =IFERROR(G4/O4,"") | AI4: =IFERROR(G4/C4,"") | AJ4: =IFERROR(D4/C4,"") | AP4: =IFERROR(IF(AND(NOT(ISNUMBER(F4)),NOT(ISNUMBER(AO4))),"",F4+AO4),"") | AQ4: =IFERROR(IF(OR(NOT(ISNUMBER(E4)),NOT(ISNUMBER(AP4))),"",E4-AP4),"") | AR4: -2760 | AS4: =IFERROR(IF(OR(NOT(ISNUMBER(AR4)),NOT(ISNUMBER(S4))),"",AR4-S4),"") | AT4: Gearing <1% in 2025 (no bank loans outstanding; all bank loans settled during 2025). Net debt = Gross debt 0 - Cash 2,760 = -Rp2.76 tn (net cash).
A5: PT Andira Agro Tbk | B5: 2022 | C5: 317.86 | D5: 22.78 | F5: -10.54 | G5: -10.79 | H5: -10.79 | I5: 444.21 | J5: 77.82 | K5: 366.39 | L5: 205.52 | M5: 51.32 | N5: 154.2 | O5: 238.69 | P5: =IFERROR(J5-M5,"") | Q5: 15.02 | R5: 166.18 | S5: =IFERROR(R5-Q5,"") | T5: 51.02 | U5: 29.78 | V5: =IFERROR(T5-U5,"") | W5: 9350 | X5: -1.15 | AB5: 50 | AC5: =IFERROR(W5*AB5/1000,"") | AD5: =IFERROR(J5/M5,"") | AE5: =IFERROR(R5/I5,"") | AF5: =IFERROR(R5/O5,"") | AG5: =IFERROR(G5/I5,"") | AH5: =IFERROR(G5/O5,"") | AI5: =IFERROR(G5/C5,"") | AJ5: =IFERROR(D5/C5,"") | AP5: =IFERROR(IF(AND(NOT(ISNUMBER(F5)),NOT(ISNUMBER(AO5))),"",F5+AO5),"") | AQ5: =IFERROR(IF(OR(NOT(ISNUMBER(E5)),NOT(ISNUMBER(AP5))),"",E5-AP5),"") | AS5: =IFERROR(IF(OR(NOT(ISNUMBER(AR5)),NOT(ISNUMBER(S5))),"",AR5-S5),"") | AT5: Net debt approx = Bank loans 166.18 - Cash 15.02 = Rp151.16 bn. D/E 0.861x, D/A 0.463x reported.
A6: PT Andira Agro Tbk | B6: 2023 | C6: 219.94 | D6: 0.22 | F6: -63.1 | G6: -55.96 | H6: -55.96 | I6: 378.14 | J6: 24.21 | K6: 353.92 | L6: 195.4 | M6: 41.92 | N6: 153.47 | O6: 182.74 | P6: =IFERROR(J6-M6,"") | Q6: 8.36 | R6: 153.47 | S6: =IFERROR(R6-Q6,"") | T6: 14.61 | U6: 12.62 | V6: =IFERROR(T6-U6,"") | W6: 9350 | X6: -5.98 | AB6: 50 | AC6: =IFERROR(W6*AB6/1000,"") | AD6: =IFERROR(J6/M6,"") | AE6: =IFERROR(R6/I6,"") | AF6: =IFERROR(R6/O6,"") | AG6: =IFERROR(G6/I6,"") | AH6: =IFERROR(G6/O6,"") | AI6: =IFERROR(G6/C6,"") | AJ6: =IFERROR(D6/C6,"") | AP6: =IFERROR(IF(AND(NOT(ISNUMBER(F6)),NOT(ISNUMBER(AO6))),"",F6+AO6),"") | AQ6: =IFERROR(IF(OR(NOT(ISNUMBER(E6)),NOT(ISNUMBER(AP6))),"",E6-AP6),"") | AS6: =IFERROR(IF(OR(NOT(ISNUMBER(AR6)),NOT(ISNUMBER(S6))),"",AR6-S6),"") | AT6: D/E 1.069x reported. Net debt approx = Liabilities - cash (per AR capital structure note: debt to capital = 1.02x)
A7: PT Andira Agro Tbk | B7: 2024 | C7: 196.74 | D7: -11.96 | F7: -34.61 | G7: -23.05 | H7: -23.05 | I7: 350.16 | J7: 38.49 | K7: 311.67 | L7: 190.38 | M7: 50.09 | N7: 140.29 | O7: 159.78 | P7: =IFERROR(J7-M7,"") | Q7: 15.82 | R7: 140.29 | S7: =IFERROR(R7-Q7,"") | T7: 23.75 | U7: 4.35 | V7: =IFERROR(T7-U7,"") | W7: 9350 | X7: -2.47 | AB7: 6 | AC7: =IFERROR(W7*AB7/1000,"") | AD7: =IFERROR(J7/M7,"") | AE7: =IFERROR(R7/I7,"") | AF7: =IFERROR(R7/O7,"") | AG7: =IFERROR(G7/I7,"") | AH7: =IFERROR(G7/O7,"") | AI7: =IFERROR(G7/C7,"") | AJ7: =IFERROR(D7/C7,"") | AP7: =IFERROR(IF(AND(NOT(ISNUMBER(F7)),NOT(ISNUMBER(AO7))),"",F7+AO7),"") | AQ7: =IFERROR(IF(OR(NOT(ISNUMBER(E7)),NOT(ISNUMBER(AP7))),"",E7-AP7),"") | AS7: =IFERROR(IF(OR(NOT(ISNUMBER(AR7)),NOT(ISNUMBER(S7))),"",AR7-S7),"") | AT7: D/E 1.191x reported. Net debt approx = Liabilities 190.38 - cash 15.82 = ~Rp174.6 bn. Debt to capital ratio maintained at 1.09x per capital management note (p92).
A8: PT Austindo Nusantara Jaya Tbk | B8: 2023 | C8: 3641 | D8: 487 | E8: 756 | F8: 229 | G8: 29 | H8: 40 | I8: 9454 | J8: 847 | K8: 8608 | L8: 2904 | M8: 813 | N8: 2091 | O8: 6547 | P8: =IFERROR(J8-M8,"") | Q8: 91 | R8: 2323 | S8: =IFERROR(R8-Q8,"") | T8: 564 | U8: 523 | V8: =IFERROR(T8-U8,"") | W8: 3354 | X8: 12 | AA8: 27.8 | AB8: 745 | AC8: =IFERROR(W8*AB8/1000,"") | AD8: =IFERROR(J8/M8,"") | AE8: =IFERROR(R8/I8,"") | AF8: =IFERROR(R8/O8,"") | AG8: =IFERROR(G8/I8,"") | AH8: =IFERROR(G8/O8,"") | AI8: =IFERROR(G8/C8,"") | AJ8: =IFERROR(D8/C8,"") | AP8: =IFERROR(IF(AND(NOT(ISNUMBER(F8)),NOT(ISNUMBER(AO8))),"",F8+AO8),"") | AQ8: =IFERROR(IF(OR(NOT(ISNUMBER(E8)),NOT(ISNUMBER(AP8))),"",E8-AP8),"") | AR8: 2232 | AS8: =IFERROR(IF(OR(NOT(ISNUMBER(AR8)),NOT(ISNUMBER(S8))),"",AR8-S8),"") | AT8: Net debt = Bank loans 150.9 - Cash 5.9 = USD 145.0mn (Rp 2,232 bn). Company reports net debt/equity 0.34x.
A9: PT Austindo Nusantara Jaya Tbk | B9: 2022 | C9: 4191 | D9: 839 | E9: 1079 | F9: 523 | G9: 330 | H9: 338 | I9: 9382 | J9: 920 | K9: 8462 | L9: 2779 | M9: 631 | N9: 2148 | O9: 6603 | P9: =IFERROR(J9-M9,"") | Q9: 168 | R9: 2089 | S9: =IFERROR(R9-Q9,"") | T9: 934 | U9: 524 | V9: =IFERROR(T9-U9,"") | W9: 3354 | X9: 101 | AA9: 43 | AB9: 665 | AC9: =IFERROR(W9*AB9/1000,"") | AD9: =IFERROR(J9/M9,"") | AE9: =IFERROR(R9/I9,"") | AF9: =IFERROR(R9/O9,"") | AG9: =IFERROR(G9/I9,"") | AH9: =IFERROR(G9/O9,"") | AI9: =IFERROR(G9/C9,"") | AJ9: =IFERROR(D9/C9,"") | AP9: =IFERROR(IF(AND(NOT(ISNUMBER(F9)),NOT(ISNUMBER(AO9))),"",F9+AO9),"") | AQ9: =IFERROR(IF(OR(NOT(ISNUMBER(E9)),NOT(ISNUMBER(AP9))),"",E9-AP9),"") | AR9: 1921 | AS9: =IFERROR(IF(OR(NOT(ISNUMBER(AR9)),NOT(ISNUMBER(S9))),"",AR9-S9),"") | AT9: Net debt = Bank loans 134.2 - Cash 10.8 = USD 123.4mn (Rp 1,921 bn). Company reports net debt/equity 0.29x.
A10: PT Austindo Nusantara Jaya Tbk | B10: 2024 | C10: 3827 | D10: 764 | E10: 957 | F10: 389 | G10: 149 | H10: 155 | I10: 9263 | J10: 1005 | K10: 8258 | L10: 2930 | M10: 798 | N10: 2132 | O10: 6332 | P10: =IFERROR(J10-M10,"") | Q10: 147 | R10: 2352 | S10: =IFERROR(R10-Q10,"") | T10: 705 | U10: 452 | V10: =IFERROR(T10-U10,"") | W10: 3354 | X10: 47 | Z10: 27.8 | AB10: 715 | AC10: =IFERROR(W10*AB10/1000,"") | AD10: =IFERROR(J10/M10,"") | AE10: =IFERROR(R10/I10,"") | AF10: =IFERROR(R10/O10,"") | AG10: =IFERROR(G10/I10,"") | AH10: =IFERROR(G10/O10,"") | AI10: =IFERROR(G10/C10,"") | AJ10: =IFERROR(D10/C10,"") | AP10: =IFERROR(IF(AND(NOT(ISNUMBER(F10)),NOT(ISNUMBER(AO10))),"",F10+AO10),"") | AQ10: =IFERROR(IF(OR(NOT(ISNUMBER(E10)),NOT(ISNUMBER(AP10))),"",E10-AP10),"") | AR10: 2205 | AS10: =IFERROR(IF(OR(NOT(ISNUMBER(AR10)),NOT(ISNUMBER(S10))),"",AR10-S10),"") | AT10: Net debt = Bank loans 145.5 - Cash 9.1 = USD 136.4mn (Rp 2,205 bn). Net debt/equity 0.3x.
A11: PT BISI International Tbk | B11: 2023 | C11: 2298 | D11: 1162 | F11: 692 | G11: 596 | H11: 596 | I11: 3902 | J11: 2945 | K11: 957 | L11: 455 | M11: 401 | N11: 54 | O11: 3447 | P11: =IFERROR(J11-M11,"") | Q11: 1042 | R11: 0 | S11: =IFERROR(R11-Q11,"") | T11: 43 | U11: 255 | V11: =IFERROR(T11-U11,"") | W11: 3000 | X11: 198.54 | Y11: 1149 | AB11: 1600 | AC11: =IFERROR(W11*AB11/1000,"") | AD11: =IFERROR(J11/M11,"") | AE11: =IFERROR(R11/I11,"") | AF11: =IFERROR(R11/O11,"") | AG11: =IFERROR(G11/I11,"") | AH11: =IFERROR(G11/O11,"") | AI11: =IFERROR(G11/C11,"") | AJ11: =IFERROR(D11/C11,"") | AP11: =IFERROR(IF(AND(NOT(ISNUMBER(F11)),NOT(ISNUMBER(AO11))),"",F11+AO11),"") | AQ11: =IFERROR(IF(OR(NOT(ISNUMBER(E11)),NOT(ISNUMBER(AP11))),"",E11-AP11),"") | AR11: -1042 | AS11: =IFERROR(IF(OR(NOT(ISNUMBER(AR11)),NOT(ISNUMBER(S11))),"",AR11-S11),"") | AT11: BISI has zero bank debt; net debt is negative (net cash of Rp 1,042 bn).
A12: PT BISI International Tbk | B12: 2024 | C12: 1368 | D12: 625 | F12: 206 | G12: 179 | H12: 179 | I12: 3635 | J12: 2573 | K12: 1062 | L12: 244 | M12: 192 | N12: 52 | O12: 3390 | P12: =IFERROR(J12-M12,"") | Q12: 568 | R12: 0 | S12: =IFERROR(R12-Q12,"") | T12: -146 | U12: 95 | V12: =IFERROR(T12-U12,"") | W12: 3000 | X12: 59.5 | Y12: 1130 | AA12: 80 | AB12: 1200 | AC12: =IFERROR(W12*AB12/1000,"") | AD12: =IFERROR(J12/M12,"") | AE12: =IFERROR(R12/I12,"") | AF12: =IFERROR(R12/O12,"") | AG12: =IFERROR(G12/I12,"") | AH12: =IFERROR(G12/O12,"") | AI12: =IFERROR(G12/C12,"") | AJ12: =IFERROR(D12/C12,"") | AP12: =IFERROR(IF(AND(NOT(ISNUMBER(F12)),NOT(ISNUMBER(AO12))),"",F12+AO12),"") | AQ12: =IFERROR(IF(OR(NOT(ISNUMBER(E12)),NOT(ISNUMBER(AP12))),"",E12-AP12),"") | AR12: -568 | AS12: =IFERROR(IF(OR(NOT(ISNUMBER(AR12)),NOT(ISNUMBER(S12))),"",AR12-S12),"") | AT12: BISI has zero bank debt; net cash position of Rp 568 bn (cash and equivalents).
A13: PT BISI International Tbk | B13: 2025 | C13: 1696.438 | D13: 680.976 | F13: 226.93 | G13: 190.294 | H13: 190 | I13: 3738.296 | J13: 2640 | K13: 1098 | L13: 243.726 | M13: 184 | N13: 59 | O13: 3494.57 | P13: =IFERROR(J13-M13,"") | Q13: 166.707 | R13: 16.806 | S13: =IFERROR(R13-Q13,"") | T13: -263 | U13: 63 | V13: =IFERROR(T13-U13,"") | W13: 3000 | X13: 63.43 | Y13: 1165 | AA13: 28 | AC13: =IFERROR(W13*AB13/1000,"") | AD13: =IFERROR(J13/M13,"") | AE13: =IFERROR(R13/I13,"") | AF13: =IFERROR(R13/O13,"") | AG13: =IFERROR(G13/I13,"") | AH13: =IFERROR(G13/O13,"") | AI13: =IFERROR(G13/C13,"") | AJ13: =IFERROR(D13/C13,"") | AP13: =IFERROR(IF(AND(NOT(ISNUMBER(F13)),NOT(ISNUMBER(AO13))),"",F13+AO13),"") | AQ13: =IFERROR(IF(OR(NOT(ISNUMBER(E13)),NOT(ISNUMBER(AP13))),"",E13-AP13),"") | AR13: -150 | AS13: =IFERROR(IF(OR(NOT(ISNUMBER(AR13)),NOT(ISNUMBER(S13))),"",AR13-S13),"") | AT13: Net debt = Short-term bank loan 17 - Cash 167 = Rp -150 bn (net cash).
A14: PT Bumi Teknokultura Unggul Tbk | B14: 2022 | C14: 153.5 | D14: -11.82 | F14: -41.02 | G14: -133.47 | H14: -133.47 | I14: 4142.04 | J14: 75.77 | K14: 4066.27 | L14: 2939.13 | M14: 218.11 | N14: 2721.02 | O14: 1202.91 | P14: =IFERROR(J14-M14,"") | Q14: 8.93 | R14: 2478.57 | S14: =IFERROR(R14-Q14,"") | T14: 22.56 | U14: 0.2 | V14: =IFERROR(T14-U14,"") | W14: 46277.5 | X14: -2.88 | AB14: 50 | AC14: =IFERROR(W14*AB14/1000,"") | AD14: =IFERROR(J14/M14,"") | AE14: =IFERROR(R14/I14,"") | AF14: =IFERROR(R14/O14,"") | AG14: =IFERROR(G14/I14,"") | AH14: =IFERROR(G14/O14,"") | AI14: =IFERROR(G14/C14,"") | AJ14: =IFERROR(D14/C14,"") | AO14: 51.51 | AP14: =IFERROR(IF(AND(NOT(ISNUMBER(F14)),NOT(ISNUMBER(AO14))),"",F14+AO14),"") | AQ14: =IFERROR(IF(OR(NOT(ISNUMBER(E14)),NOT(ISNUMBER(AP14))),"",E14-AP14),"") | AR14: 2469.65 | AS14: =IFERROR(IF(OR(NOT(ISNUMBER(AR14)),NOT(ISNUMBER(S14))),"",AR14-S14),"") | AT14: Gross debt (bank loans) minus cash & equivalents; bonds not reported separately.
A15: PT Bumi Teknokultura Unggul Tbk | B15: 2023 | C15: 196.67 | D15: -6.03 | F15: -40.53 | G15: -114.05 | H15: -114.05 | I15: 4055.75 | J15: 59.79 | K15: 3995.96 | L15: 2948.91 | M15: 295.65 | N15: 2653.26 | O15: 1106.84 | P15: =IFERROR(J15-M15,"") | Q15: 13.82 | R15: 2413.69 | S15: =IFERROR(R15-Q15,"") | T15: 138.15 | U15: 69.21 | V15: =IFERROR(T15-U15,"") | W15: 46277.5 | X15: -2.46 | AB15: 50 | AC15: =IFERROR(W15*AB15/1000,"") | AD15: =IFERROR(J15/M15,"") | AE15: =IFERROR(R15/I15,"") | AF15: =IFERROR(R15/O15,"") | AG15: =IFERROR(G15/I15,"") | AH15: =IFERROR(G15/O15,"") | AI15: =IFERROR(G15/C15,"") | AJ15: =IFERROR(D15/C15,"") | AO15: 45.91 | AP15: =IFERROR(IF(AND(NOT(ISNUMBER(F15)),NOT(ISNUMBER(AO15))),"",F15+AO15),"") | AQ15: =IFERROR(IF(OR(NOT(ISNUMBER(E15)),NOT(ISNUMBER(AP15))),"",E15-AP15),"") | AR15: 2399.87 | AS15: =IFERROR(IF(OR(NOT(ISNUMBER(AR15)),NOT(ISNUMBER(S15))),"",AR15-S15),"") | AT15: Gross bank loans minus cash & equivalents.
A16: PT Bumi Teknokultura Unggul Tbk | B16: 2024 | C16: 635.63 | D16: -19.85 | F16: -70.3 | G16: -719.27 | H16: -719.27 | I16: 3894.06 | J16: 162.46 | K16: 3731.61 | L16: 3431.56 | M16: 69.97 | N16: 3361.6 | O16: 462.5 | P16: =IFERROR(J16-M16,"") | Q16: 61.35 | R16: 2346 | S16: =IFERROR(R16-Q16,"") | T16: 70.96 | U16: 21.77 | V16: =IFERROR(T16-U16,"") | W16: 46277.5 | X16: -15.54 | AB16: 3 | AC16: =IFERROR(W16*AB16/1000,"") | AD16: =IFERROR(J16/M16,"") | AE16: =IFERROR(R16/I16,"") | AF16: =IFERROR(R16/O16,"") | AG16: =IFERROR(G16/I16,"") | AH16: =IFERROR(G16/O16,"") | AI16: =IFERROR(G16/C16,"") | AJ16: =IFERROR(D16/C16,"") | AO16: 84.32 | AP16: =IFERROR(IF(AND(NOT(ISNUMBER(F16)),NOT(ISNUMBER(AO16))),"",F16+AO16),"") | AQ16: =IFERROR(IF(OR(NOT(ISNUMBER(E16)),NOT(ISNUMBER(AP16))),"",E16-AP16),"") | AR16: 2284.64 | AS16: =IFERROR(IF(OR(NOT(ISNUMBER(AR16)),NOT(ISNUMBER(S16))),"",AR16-S16),"") | AT16: Bank loans (Rp 2,346.00 bn) minus cash (Rp 61.35 bn).
A17: PT Eagle High Plantations Tbk | B17: 2023 | C17: 4204.61 | D17: 1057.15 | F17: 703.47 | G17: 159.97 | H17: 177.03 | I17: 10183.51 | J17: 1300.01 | K17: 8883.5 | L17: 7991.96 | M17: 3513.09 | N17: 4478.87 | O17: 2191.55 | P17: =IFERROR(J17-M17,"") | Q17: 25.37 | R17: 7777.55 | S17: =IFERROR(R17-Q17,"") | T17: 633.06 | U17: 279 | V17: =IFERROR(T17-U17,"") | W17: 31525.29 | X17: 5.68 | AB17: 54 | AC17: =IFERROR(W17*AB17/1000,"") | AD17: =IFERROR(J17/M17,"") | AE17: =IFERROR(R17/I17,"") | AF17: =IFERROR(R17/O17,"") | AG17: =IFERROR(G17/I17,"") | AH17: =IFERROR(G17/O17,"") | AI17: =IFERROR(G17/C17,"") | AJ17: =IFERROR(D17/C17,"") | AP17: =IFERROR(IF(AND(NOT(ISNUMBER(F17)),NOT(ISNUMBER(AO17))),"",F17+AO17),"") | AQ17: =IFERROR(IF(OR(NOT(ISNUMBER(E17)),NOT(ISNUMBER(AP17))),"",E17-AP17),"") | AS17: =IFERROR(IF(OR(NOT(ISNUMBER(AR17)),NOT(ISNUMBER(S17))),"",AR17-S17),"") | AT17: Gross debt not explicitly separated in Ikhtisar; implied high via DER 3.65x.
A18: PT Eagle High Plantations Tbk | B18: 2024 | C18: 4302.68 | D18: 1254.43 | F18: 926.51 | G18: 272.13 | H18: 260.21 | I18: 9794.38 | J18: 1420.68 | K18: 8373.7 | L18: 7342.29 | M18: 2945.12 | N18: 4397.17 | O18: 2452.09 | P18: =IFERROR(J18-M18,"") | Q18: 58.08 | R18: 3959.18 | S18: =IFERROR(R18-Q18,"") | T18: 833.79 | U18: 86.04 | V18: =IFERROR(T18-U18,"") | W18: 31525.29 | X18: 8.36 | AB18: 59 | AC18: =IFERROR(W18*AB18/1000,"") | AD18: =IFERROR(J18/M18,"") | AE18: =IFERROR(R18/I18,"") | AF18: =IFERROR(R18/O18,"") | AG18: =IFERROR(G18/I18,"") | AH18: =IFERROR(G18/O18,"") | AI18: =IFERROR(G18/C18,"") | AJ18: =IFERROR(D18/C18,"") | AO18: 176.43 | AP18: =IFERROR(IF(AND(NOT(ISNUMBER(F18)),NOT(ISNUMBER(AO18))),"",F18+AO18),"") | AQ18: =IFERROR(IF(OR(NOT(ISNUMBER(E18)),NOT(ISNUMBER(AP18))),"",E18-AP18),"") | AR18: 3901.1 | AS18: =IFERROR(IF(OR(NOT(ISNUMBER(AR18)),NOT(ISNUMBER(S18))),"",AR18-S18),"") | AT18: Bank loans (Rp 3,897.63 bn: ST 290.78 + current portion LT 696.23 + LT 2,910.63) + bonds payable (Rp 61.55 bn) minus cash (Rp 58.08 bn).
A19: PT Eagle High Plantations Tbk | B19: 2025 | C19: 5761.296 | D19: 1590.658 | F19: 1189.695 | G19: 361.72 | H19: 361.72 | I19: 10176.15 | J19: 1737.16 | K19: 8438.99 | L19: 7349.037 | M19: 2595.3 | N19: 4753.74 | O19: 2827.113 | P19: =IFERROR(J19-M19,"") | Q19: 209.762 | R19: 4259.253 | S19: =IFERROR(R19-Q19,"") | T19: 1340.73 | U19: 331.04 | V19: =IFERROR(T19-U19,"") | W19: 31525.29 | X19: 11.62 | AC19: =IFERROR(W19*AB19/1000,"") | AD19: =IFERROR(J19/M19,"") | AE19: =IFERROR(R19/I19,"") | AF19: =IFERROR(R19/O19,"") | AG19: =IFERROR(G19/I19,"") | AH19: =IFERROR(G19/O19,"") | AI19: =IFERROR(G19/C19,"") | AJ19: =IFERROR(D19/C19,"") | AO19: 175.54 | AP19: =IFERROR(IF(AND(NOT(ISNUMBER(F19)),NOT(ISNUMBER(AO19))),"",F19+AO19),"") | AQ19: =IFERROR(IF(OR(NOT(ISNUMBER(E19)),NOT(ISNUMBER(AP19))),"",E19-AP19),"") | AR19: 3894.7 | AS19: =IFERROR(IF(OR(NOT(ISNUMBER(AR19)),NOT(ISNUMBER(S19))),"",AR19-S19),"") | AT19: Bank loans (229.73 ST + 602.93 current LT + 3,109.85 LT = 3,942.51) + bonds (23.78 current + 6.02 LT = 29.80) + sukuk (37.29 current + 24.89 LT = 62.18) minus cash (139.79). Excludes non-bank financial institution loans.
A20: PT Citra Borneo Utama Tbk | B20: 2023 | C20: 10319.437 | D20: 1314.507 | F20: 311.759 | G20: 144.242 | H20: 144.242 | I20: 4336.194 | J20: 3925.96 | K20: 410.234 | L20: 3433.778 | M20: 2659.659 | N20: 774.119 | O20: 902.416 | P20: =IFERROR(J20-M20,"") | Q20: 304.932 | R20: 2987.469 | S20: =IFERROR(R20-Q20,"") | T20: -384.368 | U20: 19.183 | V20: =IFERROR(T20-U20,"") | W20: 3125 | X20: 46.16 | AB20: 1765 | AC20: =IFERROR(W20*AB20/1000,"") | AD20: =IFERROR(J20/M20,"") | AE20: =IFERROR(R20/I20,"") | AF20: =IFERROR(R20/O20,"") | AG20: =IFERROR(G20/I20,"") | AH20: =IFERROR(G20/O20,"") | AI20: =IFERROR(G20/C20,"") | AJ20: =IFERROR(D20/C20,"") | AO20: 42.464 | AP20: =IFERROR(IF(AND(NOT(ISNUMBER(F20)),NOT(ISNUMBER(AO20))),"",F20+AO20),"") | AQ20: =IFERROR(IF(OR(NOT(ISNUMBER(E20)),NOT(ISNUMBER(AP20))),"",E20-AP20),"") | AS20: =IFERROR(IF(OR(NOT(ISNUMBER(AR20)),NOT(ISNUMBER(S20))),"",AR20-S20),"") | AT20: Gross debt = ST bank loans 2,138.461 + current portion LT bank loans 79.830 + LT bank loans 769.178 = 2,987.469; cash 304.932
A21: PT Citra Borneo Utama Tbk | B21: 2024 | C21: 9766.108 | D21: 1146.509 | F21: 89.639 | G21: 68.186 | H21: 68.186 | I21: 4200.319 | J21: 3591.721 | K21: 608.598 | L21: 3231.021 | M21: 2547.153 | N21: 683.868 | O21: 969.298 | P21: =IFERROR(J21-M21,"") | Q21: 234.104 | R21: 2714.137 | S21: =IFERROR(R21-Q21,"") | T21: -246.579 | U21: 115.118 | V21: =IFERROR(T21-U21,"") | W21: 3125 | X21: 21.82 | AA21: 9.23 | AB21: 945 | AC21: =IFERROR(W21*AB21/1000,"") | AD21: =IFERROR(J21/M21,"") | AE21: =IFERROR(R21/I21,"") | AF21: =IFERROR(R21/O21,"") | AG21: =IFERROR(G21/I21,"") | AH21: =IFERROR(G21/O21,"") | AI21: =IFERROR(G21/C21,"") | AJ21: =IFERROR(D21/C21,"") | AO21: 44.678 | AP21: =IFERROR(IF(AND(NOT(ISNUMBER(F21)),NOT(ISNUMBER(AO21))),"",F21+AO21),"") | AQ21: =IFERROR(IF(OR(NOT(ISNUMBER(E21)),NOT(ISNUMBER(AP21))),"",E21-AP21),"") | AS21: =IFERROR(IF(OR(NOT(ISNUMBER(AR21)),NOT(ISNUMBER(S21))),"",AR21-S21),"") | AT21: Gross debt = ST bank loans 1,944.959 + current portion LT 89.830 + LT 679.348 = 2,714.137; cash 234.104
A22: PT Citra Borneo Utama Tbk | B22: 2025 | C22: 13970.811 | D22: 1982.302 | F22: 366.418 | G22: 106.175 | H22: 106.175 | I22: 4117.814 | J22: 2811.84 | K22: 1305.974 | L22: 3007.199 | M22: 2286.662 | N22: 720.537 | O22: 1110.615 | P22: =IFERROR(J22-M22,"") | Q22: 284.835 | R22: 1897.841 | S22: =IFERROR(R22-Q22,"") | T22: 395.712 | U22: 258.905 | V22: =IFERROR(T22-U22,"") | W22: 3125 | X22: 33.98 | AB22: 1045 | AC22: =IFERROR(W22*AB22/1000,"") | AD22: =IFERROR(J22/M22,"") | AE22: =IFERROR(R22/I22,"") | AF22: =IFERROR(R22/O22,"") | AG22: =IFERROR(G22/I22,"") | AH22: =IFERROR(G22/O22,"") | AI22: =IFERROR(G22/C22,"") | AJ22: =IFERROR(D22/C22,"") | AO22: 46.703 | AP22: =IFERROR(IF(AND(NOT(ISNUMBER(F22)),NOT(ISNUMBER(AO22))),"",F22+AO22),"") | AQ22: =IFERROR(IF(OR(NOT(ISNUMBER(E22)),NOT(ISNUMBER(AP22))),"",E22-AP22),"") | AS22: =IFERROR(IF(OR(NOT(ISNUMBER(AR22)),NOT(ISNUMBER(S22))),"",AR22-S22),"") | AT22: Gross debt = ST bank loans 1,218.493 + current portion LT 124.830 + LT 554.518 = 1,897.841; cash 284.835
A23: PT Cisadane Sawit Raya Tbk. | B23: 2022 | C23: 970.572 | D23: 571.759 | E23: 449.517 | F23: 396.174 | G23: 252.407 | H23: 252.407 | I23: 1835.254 | J23: 502.528 | K23: 1332.726 | L23: 872.142 | M23: 251.247 | N23: 620.895 | O23: 963.112 | P23: =IFERROR(J23-M23,"") | Q23: 263.734 | R23: 644.696 | S23: =IFERROR(R23-Q23,"") | T23: 401.336 | U23: 134.417 | V23: =IFERROR(T23-U23,"") | W23: 2050 | X23: 123 | Z23: 25 | AA23: 10 | AB23: 570 | AC23: =IFERROR(W23*AB23/1000,"") | AD23: =IFERROR(J23/M23,"") | AE23: =IFERROR(R23/I23,"") | AF23: =IFERROR(R23/O23,"") | AG23: =IFERROR(G23/I23,"") | AH23: =IFERROR(G23/O23,"") | AI23: =IFERROR(G23/C23,"") | AJ23: =IFERROR(D23/C23,"") | AP23: =IFERROR(IF(AND(NOT(ISNUMBER(F23)),NOT(ISNUMBER(AO23))),"",F23+AO23),"") | AQ23: =IFERROR(IF(OR(NOT(ISNUMBER(E23)),NOT(ISNUMBER(AP23))),"",E23-AP23),"") | AR23: 380.962 | AS23: =IFERROR(IF(OR(NOT(ISNUMBER(AR23)),NOT(ISNUMBER(S23))),"",AR23-S23),"") | AT23: Net debt = Total loans 644,696 - Cash & equivalents 263,734 = 380,962 (company disclosed)
A24: PT Cisadane Sawit Raya Tbk. | B24: 2023 | C24: 875.512 | D24: 399.586 | E24: 317.261 | F24: 221.843 | G24: 146.139 | H24: 146.139 | I24: 1842.858 | J24: 323.758 | K24: 1519.099 | L24: 727.686 | M24: 187.487 | N24: 540.199 | O24: 1115.172 | P24: =IFERROR(J24-M24,"") | Q24: 25.365 | R24: 509.346 | S24: =IFERROR(R24-Q24,"") | T24: 192.491 | U24: 136.372 | V24: =IFERROR(T24-U24,"") | W24: 2050 | X24: 71 | AB24: 472 | AC24: =IFERROR(W24*AB24/1000,"") | AD24: =IFERROR(J24/M24,"") | AE24: =IFERROR(R24/I24,"") | AF24: =IFERROR(R24/O24,"") | AG24: =IFERROR(G24/I24,"") | AH24: =IFERROR(G24/O24,"") | AI24: =IFERROR(G24/C24,"") | AJ24: =IFERROR(D24/C24,"") | AP24: =IFERROR(IF(AND(NOT(ISNUMBER(F24)),NOT(ISNUMBER(AO24))),"",F24+AO24),"") | AQ24: =IFERROR(IF(OR(NOT(ISNUMBER(E24)),NOT(ISNUMBER(AP24))),"",E24-AP24),"") | AR24: 483.981 | AS24: =IFERROR(IF(OR(NOT(ISNUMBER(AR24)),NOT(ISNUMBER(S24))),"",AR24-S24),"") | AT24: Net debt = Total Loans 509,346 - Cash 25,365 = 483,981 (company disclosed); Gearing ratio 43.40%
A25: PT Cisadane Sawit Raya Tbk. | B25: 2024 | C25: 1066.759 | D25: 483.864 | E25: 441.979 | F25: 263.628 | G25: 214.855 | H25: 214.855 | I25: 2251.265 | J25: 463.276 | K25: 1787.989 | L25: 952.719 | M25: 250.757 | N25: 701.962 | O25: 1298.545 | P25: =IFERROR(J25-M25,"") | Q25: 133.268 | R25: 693.577 | S25: =IFERROR(R25-Q25,"") | T25: 332.808 | U25: 227.648 | V25: =IFERROR(T25-U25,"") | W25: 2050 | X25: 105 | AA25: 14.63 | AB25: 725 | AC25: =IFERROR(W25*AB25/1000,"") | AD25: =IFERROR(J25/M25,"") | AE25: =IFERROR(R25/I25,"") | AF25: =IFERROR(R25/O25,"") | AG25: =IFERROR(G25/I25,"") | AH25: =IFERROR(G25/O25,"") | AI25: =IFERROR(G25/C25,"") | AJ25: =IFERROR(D25/C25,"") | AP25: =IFERROR(IF(AND(NOT(ISNUMBER(F25)),NOT(ISNUMBER(AO25))),"",F25+AO25),"") | AQ25: =IFERROR(IF(OR(NOT(ISNUMBER(E25)),NOT(ISNUMBER(AP25))),"",E25-AP25),"") | AR25: 560.309 | AS25: =IFERROR(IF(OR(NOT(ISNUMBER(AR25)),NOT(ISNUMBER(S25))),"",AR25-S25),"") | AT25: Net debt = Total Loans 693,577 - Cash 133,268 = 560,309 (company disclosed); Gearing ratio 43.15%
A26: PT Dharma Satya Nusantara Tbk | B26: 2022 | C26: 9633.671 | D26: 3117.575 | E26: 3018.363 | F26: 2172.475 | G26: 1206.587 | H26: 1206.835 | I26: 15357.229 | J26: 3229.582 | K26: 12127.647 | L26: 7197.089 | M26: 3022.162 | N26: 4174.927 | O26: 8160.14 | P26: =IFERROR(J26-M26,"") | Q26: 359.349 | R26: 4926.946 | S26: =IFERROR(R26-Q26,"") | T26: 1538.027 | U26: 1197.756 | V26: =IFERROR(T26-U26,"") | W26: 10599.842 | X26: 113.86 | Y26: 758.03 | AA26: 20 | AB26: 496 | AC26: =IFERROR(W26*AB26/1000,"") | AD26: =IFERROR(J26/M26,"") | AE26: =IFERROR(R26/I26,"") | AF26: =IFERROR(R26/O26,"") | AG26: =IFERROR(G26/I26,"") | AH26: =IFERROR(G26/O26,"") | AI26: =IFERROR(G26/C26,"") | AJ26: =IFERROR(D26/C26,"") | AO26: 846.012 | AP26: =IFERROR(IF(AND(NOT(ISNUMBER(F26)),NOT(ISNUMBER(AO26))),"",F26+AO26),"") | AQ26: =IFERROR(IF(OR(NOT(ISNUMBER(E26)),NOT(ISNUMBER(AP26))),"",E26-AP26),"") | AR26: 4567.597 | AS26: =IFERROR(IF(OR(NOT(ISNUMBER(AR26)),NOT(ISNUMBER(S26))),"",AR26-S26),"") | AT26: Gross debt = short-term bank loans (668.076) + current LT bank loans (759.953) + long-term bank loans (3,041.083) + current bonds (282.310) + LT bonds (175.524). Net debt = gross debt - cash. D&A approximated as fixed-asset depreciation (478.683) + bearer plant amortization (243.793) + RoU depr + plasma amort + biological; EBITDA-EBIT ~ 845.9 bn used.
A27: PT Dharma Satya Nusantara Tbk | B27: 2023 | C27: 9498.749 | D27: 2527.468 | E27: 2421.068 | F27: 1555.713 | G27: 841.665 | H27: 839.809 | I27: 16178.278 | J27: 2949.268 | K27: 13229.01 | L27: 7288.85 | M27: 2945.961 | N27: 4342.889 | O27: 8889.428 | P27: =IFERROR(J27-M27,"") | Q27: 389.746 | R27: 5075.615 | S27: =IFERROR(R27-Q27,"") | T27: 1874.372 | U27: 1382.461 | V27: =IFERROR(T27-U27,"") | W27: 10599.842 | X27: 79.23 | Y27: 822.27 | AA27: 30 | AB27: 555 | AC27: =IFERROR(W27*AB27/1000,"") | AD27: =IFERROR(J27/M27,"") | AE27: =IFERROR(R27/I27,"") | AF27: =IFERROR(R27/O27,"") | AG27: =IFERROR(G27/I27,"") | AH27: =IFERROR(G27/O27,"") | AI27: =IFERROR(G27/C27,"") | AJ27: =IFERROR(D27/C27,"") | AO27: 865.355 | AP27: =IFERROR(IF(AND(NOT(ISNUMBER(F27)),NOT(ISNUMBER(AO27))),"",F27+AO27),"") | AQ27: =IFERROR(IF(OR(NOT(ISNUMBER(E27)),NOT(ISNUMBER(AP27))),"",E27-AP27),"") | AR27: 4685.869 | AS27: =IFERROR(IF(OR(NOT(ISNUMBER(AR27)),NOT(ISNUMBER(S27))),"",AR27-S27),"") | AT27: Gross debt = ST bank loans 947.588 + current LT bank loans 771.194 + LT bank loans 3,178.020 + current bonds 3.001 + LT bonds 175.812 = 5,075.615. Net debt = gross debt - cash 389.746. D&A approx = EBITDA-EBIT = 865.355.
A28: PT Dharma Satya Nusantara Tbk | B28: 2024 | C28: 10119.22 | D28: 3004.201 | E28: 3096.491 | F28: 2123.67 | G28: 1141.375 | H28: 1142.493 | I28: 17412.416 | J28: 2897.246 | K28: 14515.17 | L28: 7515.101 | M28: 2530.342 | N28: 4984.759 | O28: 9897.315 | P28: =IFERROR(J28-M28,"") | Q28: 557.023 | R28: 5228.212 | S28: =IFERROR(R28-Q28,"") | T28: 2150.615 | U28: 1092.101 | V28: =IFERROR(T28-U28,"") | W28: 10599.842 | X28: 107.78 | Y28: 917.32 | AA28: 22 | AB28: 950 | AC28: =IFERROR(W28*AB28/1000,"") | AD28: =IFERROR(J28/M28,"") | AE28: =IFERROR(R28/I28,"") | AF28: =IFERROR(R28/O28,"") | AG28: =IFERROR(G28/I28,"") | AH28: =IFERROR(G28/O28,"") | AI28: =IFERROR(G28/C28,"") | AJ28: =IFERROR(D28/C28,"") | AO28: 972.821 | AP28: =IFERROR(IF(AND(NOT(ISNUMBER(F28)),NOT(ISNUMBER(AO28))),"",F28+AO28),"") | AQ28: =IFERROR(IF(OR(NOT(ISNUMBER(E28)),NOT(ISNUMBER(AP28))),"",E28-AP28),"") | AR28: 4671.189 | AS28: =IFERROR(IF(OR(NOT(ISNUMBER(AR28)),NOT(ISNUMBER(S28))),"",AR28-S28),"") | AT28: Gross debt = ST bank loans 476.957 + current LT bank loans 597.660 + LT bank loans 3,971.671 + current bonds 181.924 + LT bonds 0 = 5,228.212. Net debt = gross debt - cash 557.023. D&A approx = EBITDA-EBIT = 972.821.
A29: PT FAP Agri Tbk | B29: 2022 | C29: 4828.634 | D29: 1616.33 | F29: 1304.862 | G29: 749.311 | H29: 709.144 | I29: 8624.009 | J29: 1808.825 | K29: 6815.184 | L29: 4724.997 | M29: 2052.812 | N29: 2672.185 | O29: 3899.012 | P29: =IFERROR(J29-M29,"") | Q29: 507.768 | R29: 3508.193 | S29: =IFERROR(R29-Q29,"") | T29: 1895.737 | U29: 468.859 | V29: =IFERROR(T29-U29,"") | W29: 3629.412 | X29: 195.39 | Y29: 1074.26 | AB29: 4300 | AC29: =IFERROR(W29*AB29/1000,"") | AD29: =IFERROR(J29/M29,"") | AE29: =IFERROR(R29/I29,"") | AF29: =IFERROR(R29/O29,"") | AG29: =IFERROR(G29/I29,"") | AH29: =IFERROR(G29/O29,"") | AI29: =IFERROR(G29/C29,"") | AJ29: =IFERROR(D29/C29,"") | AO29: 507.53 | AP29: =IFERROR(IF(AND(NOT(ISNUMBER(F29)),NOT(ISNUMBER(AO29))),"",F29+AO29),"") | AQ29: =IFERROR(IF(OR(NOT(ISNUMBER(E29)),NOT(ISNUMBER(AP29))),"",E29-AP29),"") | AR29: 3000.425 | AS29: =IFERROR(IF(OR(NOT(ISNUMBER(AR29)),NOT(ISNUMBER(S29))),"",AR29-S29),"") | AT29: Gross debt = ST bank loans 530.783 + bank overdraft 427.739 + LT bank loans 2,549.671 = 3,508.193 bn. Net debt = gross debt - cash 507.768. D&A from CF reconciliation: Rp507.53bn total depreciation. Capex = fixed asset acquisitions 410.978 + immature plantation additions 57.880 = 468.859.
A30: PT FAP Agri Tbk | B30: 2023 | C30: 5062.244 | D30: 832.914 | F30: 379.319 | G30: 161.679 | H30: 153.571 | I30: 8634.035 | J30: 1800.279 | K30: 6833.757 | L30: 4570.386 | M30: 2594.225 | N30: 1976.162 | O30: 4063.649 | P30: =IFERROR(J30-M30,"") | Q30: 475.802 | R30: 3259.078 | S30: =IFERROR(R30-Q30,"") | T30: 1030.969 | U30: 478.938 | V30: =IFERROR(T30-U30,"") | W30: 3629.412 | X30: 42.31 | Y30: 1065.46 | AB30: 5300 | AC30: =IFERROR(W30*AB30/1000,"") | AD30: =IFERROR(J30/M30,"") | AE30: =IFERROR(R30/I30,"") | AF30: =IFERROR(R30/O30,"") | AG30: =IFERROR(G30/I30,"") | AH30: =IFERROR(G30/O30,"") | AI30: =IFERROR(G30/C30,"") | AJ30: =IFERROR(D30/C30,"") | AO30: 518.456 | AP30: =IFERROR(IF(AND(NOT(ISNUMBER(F30)),NOT(ISNUMBER(AO30))),"",F30+AO30),"") | AQ30: =IFERROR(IF(OR(NOT(ISNUMBER(E30)),NOT(ISNUMBER(AP30))),"",E30-AP30),"") | AR30: 2783.276 | AS30: =IFERROR(IF(OR(NOT(ISNUMBER(AR30)),NOT(ISNUMBER(S30))),"",AR30-S30),"") | AT30: Gross debt = bank overdraft 724.815 + current LT bank loan 705.892 + LT bank loan 1,828.371 = 3,259.078 bn. Net debt = gross debt - cash 475.802. Depreciation from CF note 518.456bn. Capex = fixed-asset 441.137 + immature plantation 37.801 = 478.938.
A31: PT FAP Agri Tbk | B31: 2024 | C31: 5742.984 | D31: 1318.57 | F31: 876.685 | G31: 571.454 | H31: 542.473 | I31: 8816.684 | J31: 1943.127 | K31: 6873.557 | L31: 4963.949 | M31: 2572.488 | N31: 2391.461 | O31: 3852.735 | P31: =IFERROR(J31-M31,"") | Q31: 815.777 | R31: 3514.138 | S31: =IFERROR(R31-Q31,"") | T31: 1706.122 | U31: 516.223 | V31: =IFERROR(T31-U31,"") | W31: 3629.412 | X31: 151.02 | Y31: 1061.52 | AB31: 5400 | AC31: =IFERROR(W31*AB31/1000,"") | AD31: =IFERROR(J31/M31,"") | AE31: =IFERROR(R31/I31,"") | AF31: =IFERROR(R31/O31,"") | AG31: =IFERROR(G31/I31,"") | AH31: =IFERROR(G31/O31,"") | AI31: =IFERROR(G31/C31,"") | AJ31: =IFERROR(D31/C31,"") | AO31: 523.881 | AP31: =IFERROR(IF(AND(NOT(ISNUMBER(F31)),NOT(ISNUMBER(AO31))),"",F31+AO31),"") | AQ31: =IFERROR(IF(OR(NOT(ISNUMBER(E31)),NOT(ISNUMBER(AP31))),"",E31-AP31),"") | AR31: 2698.361 | AS31: =IFERROR(IF(OR(NOT(ISNUMBER(AR31)),NOT(ISNUMBER(S31))),"",AR31-S31),"") | AT31: Gross debt = bank overdraft 676.569 + ST bank loans 661.945 + LT bank loans 2,175.625 = 3,514.138 bn. Net debt = gross debt - cash 815.777 = 2,698.361. Depreciation 523.881bn from CF note.
A32: PT FKS Multi Agro Tbk | B32: 2022 | C32: 23242 | D32: 1243.4 | F32: 748 | G32: 486.4 | H32: 478.8 | I32: 7185.9 | J32: 5283.3 | K32: 1902.1 | L32: 4578.1 | M32: 3645.2 | N32: 933.3 | O32: 2605.8 | P32: =IFERROR(J32-M32,"") | Q32: 811.1 | R32: 2085 | S32: =IFERROR(R32-Q32,"") | T32: 366.1 | U32: 94.7 | V32: =IFERROR(T32-U32,"") | W32: 480 | X32: 995 | AB32: 6750 | AC32: =IFERROR(W32*AB32/1000,"") | AD32: =IFERROR(J32/M32,"") | AE32: =IFERROR(R32/I32,"") | AF32: =IFERROR(R32/O32,"") | AG32: =IFERROR(G32/I32,"") | AH32: =IFERROR(G32/O32,"") | AI32: =IFERROR(G32/C32,"") | AJ32: =IFERROR(D32/C32,"") | AP32: =IFERROR(IF(AND(NOT(ISNUMBER(F32)),NOT(ISNUMBER(AO32))),"",F32+AO32),"") | AQ32: =IFERROR(IF(OR(NOT(ISNUMBER(E32)),NOT(ISNUMBER(AP32))),"",E32-AP32),"") | AS32: =IFERROR(IF(OR(NOT(ISNUMBER(AR32)),NOT(ISNUMBER(S32))),"",AR32-S32),"") | AT32: Gross debt = ST bank + current LT + LT bank (USD 133.89 mn) converted at USD/IDR 15,568 (end-2022).
A33: PT FKS Multi Agro Tbk | B33: 2023 | C33: 21349 | D33: 1083 | F33: 656 | G33: 377 | H33: 368 | I33: 7567 | J33: 5513 | K33: 2053 | L33: 4813 | M33: 4081 | N33: 732 | O33: 2755 | P33: =IFERROR(J33-M33,"") | Q33: 977 | R33: 2212 | S33: =IFERROR(R33-Q33,"") | T33: 586 | U33: 225 | V33: =IFERROR(T33-U33,"") | W33: 480 | X33: 762 | AB33: 5525 | AC33: =IFERROR(W33*AB33/1000,"") | AD33: =IFERROR(J33/M33,"") | AE33: =IFERROR(R33/I33,"") | AF33: =IFERROR(R33/O33,"") | AG33: =IFERROR(G33/I33,"") | AH33: =IFERROR(G33/O33,"") | AI33: =IFERROR(G33/C33,"") | AJ33: =IFERROR(D33/C33,"") | AP33: =IFERROR(IF(AND(NOT(ISNUMBER(F33)),NOT(ISNUMBER(AO33))),"",F33+AO33),"") | AQ33: =IFERROR(IF(OR(NOT(ISNUMBER(E33)),NOT(ISNUMBER(AP33))),"",E33-AP33),"") | AS33: =IFERROR(IF(OR(NOT(ISNUMBER(AR33)),NOT(ISNUMBER(S33))),"",AR33-S33),"") | AT33: Gross debt = ST bank 93.886 + current LT 10.501 + LT bank 39.068 = USD143.455 mn; converted at USD/IDR 15,416 (end-2023 BI middle rate per statement note). P&L items converted at 2023 avg rate USD/IDR 15,237.
A34: PT FKS Multi Agro Tbk | B34: 2024 | C34: 20495 | D34: 845 | F34: 367 | G34: 152 | H34: 138 | I34: 8439 | J34: 6157 | K34: 2282 | L34: 5611 | M34: 4749 | N34: 862 | O34: 2828 | P34: =IFERROR(J34-M34,"") | Q34: 1235 | R34: 2027 | S34: =IFERROR(R34-Q34,"") | T34: 830 | U34: 171 | V34: =IFERROR(T34-U34,"") | W34: 480 | X34: 285 | AB34: 10650 | AC34: =IFERROR(W34*AB34/1000,"") | AD34: =IFERROR(J34/M34,"") | AE34: =IFERROR(R34/I34,"") | AF34: =IFERROR(R34/O34,"") | AG34: =IFERROR(G34/I34,"") | AH34: =IFERROR(G34/O34,"") | AI34: =IFERROR(G34/C34,"") | AJ34: =IFERROR(D34/C34,"") | AP34: =IFERROR(IF(AND(NOT(ISNUMBER(F34)),NOT(ISNUMBER(AO34))),"",F34+AO34),"") | AQ34: =IFERROR(IF(OR(NOT(ISNUMBER(E34)),NOT(ISNUMBER(AP34))),"",E34-AP34),"") | AS34: =IFERROR(IF(OR(NOT(ISNUMBER(AR34)),NOT(ISNUMBER(S34))),"",AR34-S34),"") | AT34: Gross debt = ST bank 70.540 + current LT 8.880 + LT bank 46.030 = USD125.450 mn; converted at USD/IDR 16,162 (end-2024 BI middle rate per statement note Rp16,162). P&L items converted at 2024 avg rate USD/IDR 15,855.
A35: PT Golden Plantation Tbk | B35: 2020 | C35: 3.72 | D35: -4.84 | F35: -10.09 | G35: -383.23 | H35: -302.03 | I35: 471.66 | J35: 8.1 | K35: 463.56 | L35: 387.27 | M35: 93.33 | N35: 293.94 | O35: 84.39 | P35: =IFERROR(J35-M35,"") | Q35: 0.17 | R35: 228.53 | S35: =IFERROR(R35-Q35,"") | T35: 1.04 | U35: 15.83 | V35: =IFERROR(T35-U35,"") | X35: -82.41 | AC35: =IFERROR(W35*AB35/1000,"") | AD35: =IFERROR(J35/M35,"") | AE35: =IFERROR(R35/I35,"") | AF35: =IFERROR(R35/O35,"") | AG35: =IFERROR(G35/I35,"") | AH35: =IFERROR(G35/O35,"") | AI35: =IFERROR(G35/C35,"") | AJ35: =IFERROR(D35/C35,"") | AP35: =IFERROR(IF(AND(NOT(ISNUMBER(F35)),NOT(ISNUMBER(AO35))),"",F35+AO35),"") | AQ35: =IFERROR(IF(OR(NOT(ISNUMBER(E35)),NOT(ISNUMBER(AP35))),"",E35-AP35),"") | AS35: =IFERROR(IF(OR(NOT(ISNUMBER(AR35)),NOT(ISNUMBER(S35))),"",AR35-S35),"") | AT35: Gross debt = Current maturities of bank loans Rp9.18 bn + Long-term bank loans Rp219.35 bn = Rp228.53 bn. Net debt = 228.53 - 0.17 cash = Rp228.36 bn.
A36: PT Gunanusa Eramandiri Tbk | B36: 2024 | C36: 1444 | D36: 186 | F36: 109 | G36: 79 | H36: 60 | I36: 980 | J36: 575 | K36: 405 | L36: 301 | M36: 271 | N36: 30 | O36: 679 | P36: =IFERROR(J36-M36,"") | Q36: 29 | R36: 65 | S36: =IFERROR(R36-Q36,"") | T36: -8 | U36: 134 | V36: =IFERROR(T36-U36,"") | W36: 2500 | X36: 27 | AB36: 302 | AC36: =IFERROR(W36*AB36/1000,"") | AD36: =IFERROR(J36/M36,"") | AE36: =IFERROR(R36/I36,"") | AF36: =IFERROR(R36/O36,"") | AG36: =IFERROR(G36/I36,"") | AH36: =IFERROR(G36/O36,"") | AI36: =IFERROR(G36/C36,"") | AJ36: =IFERROR(D36/C36,"") | AP36: =IFERROR(IF(AND(NOT(ISNUMBER(F36)),NOT(ISNUMBER(AO36))),"",F36+AO36),"") | AQ36: =IFERROR(IF(OR(NOT(ISNUMBER(E36)),NOT(ISNUMBER(AP36))),"",E36-AP36),"") | AR36: 36 | AS36: =IFERROR(IF(OR(NOT(ISNUMBER(AR36)),NOT(ISNUMBER(S36))),"",AR36-S36),"") | AT36: Net debt = Short-term bank loans Rp65.1 bn - cash Rp28.6 bn = Rp36.5 bn (Company has no long-term bank debt). Debt-to-equity 0.28x, Debt-to-assets 0.19x. Current ratio 2.18x.
A37: PT Gozco Plantations Tbk | B37: 2022 | C37: 554.7 | D37: 122.5 | E37: 305.8 | F37: 136.9 | G37: 75.8 | H37: 75.6 | I37: 2045.4 | J37: 456.9 | K37: 1588.5 | L37: 892.9 | M37: 455.9 | N37: 437 | O37: 1152.5 | P37: =IFERROR(J37-M37,"") | Q37: 235.2 | R37: 356.7 | S37: =IFERROR(R37-Q37,"") | T37: 178.7 | U37: 31.7 | V37: =IFERROR(T37-U37,"") | W37: 6000 | X37: 12.61 | AB37: 81 | AC37: =IFERROR(W37*AB37/1000,"") | AD37: =IFERROR(J37/M37,"") | AE37: =IFERROR(R37/I37,"") | AF37: =IFERROR(R37/O37,"") | AG37: =IFERROR(G37/I37,"") | AH37: =IFERROR(G37/O37,"") | AI37: =IFERROR(G37/C37,"") | AJ37: =IFERROR(D37/C37,"") | AO37: 168.9 | AP37: =IFERROR(IF(AND(NOT(ISNUMBER(F37)),NOT(ISNUMBER(AO37))),"",F37+AO37),"") | AQ37: =IFERROR(IF(OR(NOT(ISNUMBER(E37)),NOT(ISNUMBER(AP37))),"",E37-AP37),"") | AR37: 121.5 | AS37: =IFERROR(IF(OR(NOT(ISNUMBER(AR37)),NOT(ISNUMBER(S37))),"",AR37-S37),"") | AT37: Gearing ratio 13% (2022). Interest-bearing debt 356.74 bn - Cash 235.21 bn = Net debt ~121.5 bn. Debt/equity 77%, Debt/asset 44%.
A38: PT Gozco Plantations Tbk | B38: 2023 | C38: 744.3 | D38: 93.6 | E38: 169.2 | F38: 44.4 | G38: 2.4 | H38: 2.1 | I38: 2118.2 | J38: 572.3 | K38: 1545.9 | L38: 949.9 | M38: 345.4 | N38: 604.6 | O38: 1168.3 | P38: =IFERROR(J38-M38,"") | Q38: 355.4 | R38: 466.6 | S38: =IFERROR(R38-Q38,"") | T38: 260.2 | U38: 93.2 | V38: =IFERROR(T38-U38,"") | W38: 6000 | X38: 0.36 | AB38: 120 | AC38: =IFERROR(W38*AB38/1000,"") | AD38: =IFERROR(J38/M38,"") | AE38: =IFERROR(R38/I38,"") | AF38: =IFERROR(R38/O38,"") | AG38: =IFERROR(G38/I38,"") | AH38: =IFERROR(G38/O38,"") | AI38: =IFERROR(G38/C38,"") | AJ38: =IFERROR(D38/C38,"") | AO38: 124.8 | AP38: =IFERROR(IF(AND(NOT(ISNUMBER(F38)),NOT(ISNUMBER(AO38))),"",F38+AO38),"") | AQ38: =IFERROR(IF(OR(NOT(ISNUMBER(E38)),NOT(ISNUMBER(AP38))),"",E38-AP38),"") | AR38: 111.3 | AS38: =IFERROR(IF(OR(NOT(ISNUMBER(AR38)),NOT(ISNUMBER(S38))),"",AR38-S38),"") | AT38: Gearing ratio 14% (2023) vs 13% (2022). Interest-bearing debt 466.63 bn - Cash 355.36 bn = Net debt ~111.3 bn. Debt/equity 81%, Debt/asset 45%.
A39: PT Gozco Plantations Tbk | B39: 2024 | C39: 804.6 | D39: 163.6 | E39: 242.4 | F39: 115.6 | G39: 62.4 | H39: 60.5 | I39: 2321.2 | J39: 286.2 | K39: 2035 | L39: 1089.3 | M39: 510.9 | N39: 578.4 | O39: 1232 | P39: =IFERROR(J39-M39,"") | Q39: 154.8 | R39: 391.7 | S39: =IFERROR(R39-Q39,"") | T39: 169.6 | U39: 21.9 | V39: =IFERROR(T39-U39,"") | W39: 6000 | X39: 10.09 | AB39: 113 | AC39: =IFERROR(W39*AB39/1000,"") | AD39: =IFERROR(J39/M39,"") | AE39: =IFERROR(R39/I39,"") | AF39: =IFERROR(R39/O39,"") | AG39: =IFERROR(G39/I39,"") | AH39: =IFERROR(G39/O39,"") | AI39: =IFERROR(G39/C39,"") | AJ39: =IFERROR(D39/C39,"") | AO39: 126.9 | AP39: =IFERROR(IF(AND(NOT(ISNUMBER(F39)),NOT(ISNUMBER(AO39))),"",F39+AO39),"") | AQ39: =IFERROR(IF(OR(NOT(ISNUMBER(E39)),NOT(ISNUMBER(AP39))),"",E39-AP39),"") | AR39: 236.8 | AS39: =IFERROR(IF(OR(NOT(ISNUMBER(AR39)),NOT(ISNUMBER(S39))),"",AR39-S39),"") | AT39: Gearing ratio 22% (2024) vs 14% (2023). Interest-bearing debt 391.65 bn - Cash 154.83 bn = Net debt ~236.8 bn. Debt/equity 88%, Debt/asset 47%.
A40: PT Indo Pureco Pratama Tbk | B40: 2023 | C40: 35.73 | D40: 11.65 | F40: 5.45 | G40: 3.86 | H40: 3.86 | I40: 301.27 | J40: 99.86 | K40: 201.42 | L40: 15 | M40: 9.12 | N40: 5.88 | O40: 286.28 | P40: =IFERROR(J40-M40,"") | Q40: 1.05 | R40: 6.56 | S40: =IFERROR(R40-Q40,"") | T40: -2.15 | U40: 7.55 | V40: =IFERROR(T40-U40,"") | W40: 4600 | X40: 0.84 | Y40: 62.23 | Z40: 0 | AA40: 0 | AB40: 50 | AC40: =IFERROR(W40*AB40/1000,"") | AD40: =IFERROR(J40/M40,"") | AE40: =IFERROR(R40/I40,"") | AF40: =IFERROR(R40/O40,"") | AG40: =IFERROR(G40/I40,"") | AH40: =IFERROR(G40/O40,"") | AI40: =IFERROR(G40/C40,"") | AJ40: =IFERROR(D40/C40,"") | AO40: 1.72 | AP40: =IFERROR(IF(AND(NOT(ISNUMBER(F40)),NOT(ISNUMBER(AO40))),"",F40+AO40),"") | AQ40: =IFERROR(IF(OR(NOT(ISNUMBER(E40)),NOT(ISNUMBER(AP40))),"",E40-AP40),"") | AS40: =IFERROR(IF(OR(NOT(ISNUMBER(AR40)),NOT(ISNUMBER(S40))),"",AR40-S40),"") | AT40: Gross debt = LT bank loans Rp6.56 bn (Rp1.75 bn current portion + Rp4.81 bn LT). Net debt = Rp6.56 bn - cash Rp1.05 bn = Rp5.51 bn. New loan drawn in 2023 (Rp7 bn receipt, Rp0.44 bn repayment). No interim/final dividend paid in 2023.
A41: PT Jhonlin Agro Raya Tbk | B41: 2022 | C41: 4708 | D41: 168 | F41: 88 | G41: 42 | H41: 42 | I41: 3001 | J41: 1434 | K41: 1567 | L41: 1847 | M41: 628 | N41: 1220 | O41: 1154 | P41: =IFERROR(J41-M41,"") | Q41: 206 | R41: 1446 | S41: =IFERROR(R41-Q41,"") | T41: 62 | U41: 275 | V41: =IFERROR(T41-U41,"") | W41: 8000 | X41: 5.8 | AB41: 318 | AC41: =IFERROR(W41*AB41/1000,"") | AD41: =IFERROR(J41/M41,"") | AE41: =IFERROR(R41/I41,"") | AF41: =IFERROR(R41/O41,"") | AG41: =IFERROR(G41/I41,"") | AH41: =IFERROR(G41/O41,"") | AI41: =IFERROR(G41/C41,"") | AJ41: =IFERROR(D41/C41,"") | AP41: =IFERROR(IF(AND(NOT(ISNUMBER(F41)),NOT(ISNUMBER(AO41))),"",F41+AO41),"") | AQ41: =IFERROR(IF(OR(NOT(ISNUMBER(E41)),NOT(ISNUMBER(AP41))),"",E41-AP41),"") | AS41: =IFERROR(IF(OR(NOT(ISNUMBER(AR41)),NOT(ISNUMBER(S41))),"",AR41-S41),"") | AT41: Gross debt = ST bank loan Rp214.7 bn + LT bank loan Rp1,231.1 bn = Rp1,445.8 bn (Note 21); Cash Rp206.0 bn (Note 5). Net debt = Rp1,239.8 bn. Debt-to-equity ratio reported at 160% (2022).
A42: PT Jhonlin Agro Raya Tbk | B42: 2023 | C42: 4442 | D42: 385 | F42: 253 | G42: 77 | H42: 77 | I42: 3653 | J42: 1352 | K42: 2301 | L42: 2211 | M42: 366 | N42: 1845 | O42: 1442 | P42: =IFERROR(J42-M42,"") | Q42: 160 | R42: 1924 | S42: =IFERROR(R42-Q42,"") | T42: 230 | U42: 440 | V42: =IFERROR(T42-U42,"") | W42: 9231 | X42: 8.37 | AB42: 248 | AC42: =IFERROR(W42*AB42/1000,"") | AD42: =IFERROR(J42/M42,"") | AE42: =IFERROR(R42/I42,"") | AF42: =IFERROR(R42/O42,"") | AG42: =IFERROR(G42/I42,"") | AH42: =IFERROR(G42/O42,"") | AI42: =IFERROR(G42/C42,"") | AJ42: =IFERROR(D42/C42,"") | AP42: =IFERROR(IF(AND(NOT(ISNUMBER(F42)),NOT(ISNUMBER(AO42))),"",F42+AO42),"") | AQ42: =IFERROR(IF(OR(NOT(ISNUMBER(E42)),NOT(ISNUMBER(AP42))),"",E42-AP42),"") | AS42: =IFERROR(IF(OR(NOT(ISNUMBER(AR42)),NOT(ISNUMBER(S42))),"",AR42-S42),"") | AT42: Gross debt = Current portion LT loan Rp88.1 bn + LT bank debt Rp1,835.85 bn = Rp1,923.96 bn (Note 22 - PT Bank Mandiri Rp1,721.5 bn + BPD Kalsel Rp206.7 bn; net of unamortized fees Rp4.24 bn). Cash Rp160.2 bn. Debt-to-equity 153%. New Rp500 bn investment credit signed Nov 2023.
A43: PT Jhonlin Agro Raya Tbk | B43: 2024 | C43: 3865 | D43: 481 | F43: 416 | G43: 261 | H43: 261 | I43: 4105 | J43: 1922 | K43: 2183 | L43: 2404 | M43: 602 | N43: 1802 | O43: 1701 | P43: =IFERROR(J43-M43,"") | Q43: 252 | R43: 1855 | S43: =IFERROR(R43-Q43,"") | T43: 253 | U43: 15 | V43: =IFERROR(T43-U43,"") | W43: 9231 | X43: 28.25 | AB43: 310 | AC43: =IFERROR(W43*AB43/1000,"") | AD43: =IFERROR(J43/M43,"") | AE43: =IFERROR(R43/I43,"") | AF43: =IFERROR(R43/O43,"") | AG43: =IFERROR(G43/I43,"") | AH43: =IFERROR(G43/O43,"") | AI43: =IFERROR(G43/C43,"") | AJ43: =IFERROR(D43/C43,"") | AP43: =IFERROR(IF(AND(NOT(ISNUMBER(F43)),NOT(ISNUMBER(AO43))),"",F43+AO43),"") | AQ43: =IFERROR(IF(OR(NOT(ISNUMBER(E43)),NOT(ISNUMBER(AP43))),"",E43-AP43),"") | AS43: =IFERROR(IF(OR(NOT(ISNUMBER(AR43)),NOT(ISNUMBER(S43))),"",AR43-S43),"") | AT43: Gross debt = Current portion LT Rp64.5 bn + LT Rp1,790.1 bn = Rp1,854.6 bn (Note 21 - Bank Mandiri + BPD Kalsel). Cash Rp252.2 bn. Net debt Rp1,602 bn. Debt-to-equity 141%, Debt-to-asset 0.59. EBITDA/Revenue ratio 6.15 reported.
A44: PT Jaya Agra Wattie Tbk | B44: 2022 | C44: 972 | D44: 27 | F44: -30 | G44: -302 | H44: -300 | I44: 3590 | J44: 262 | K44: 3327 | L44: 3471 | M44: 656 | N44: 2815 | O44: 118 | P44: =IFERROR(J44-M44,"") | Q44: 1.98 | R44: 2235 | S44: =IFERROR(R44-Q44,"") | T44: -138 | U44: 54 | V44: =IFERROR(T44-U44,"") | W44: 3775 | X44: -80 | Y44: 31 | Z44: 0 | AA44: 0 | AB44: 105 | AC44: =IFERROR(W44*AB44/1000,"") | AD44: =IFERROR(J44/M44,"") | AE44: =IFERROR(R44/I44,"") | AF44: =IFERROR(R44/O44,"") | AG44: =IFERROR(G44/I44,"") | AH44: =IFERROR(G44/O44,"") | AI44: =IFERROR(G44/C44,"") | AJ44: =IFERROR(D44/C44,"") | AO44: 113 | AP44: =IFERROR(IF(AND(NOT(ISNUMBER(F44)),NOT(ISNUMBER(AO44))),"",F44+AO44),"") | AQ44: =IFERROR(IF(OR(NOT(ISNUMBER(E44)),NOT(ISNUMBER(AP44))),"",E44-AP44),"") | AS44: =IFERROR(IF(OR(NOT(ISNUMBER(AR44)),NOT(ISNUMBER(S44))),"",AR44-S44),"") | AT44: Gross bank debt = Rp125 bn ST + Rp2,109.99 bn LT = Rp2,234.99 bn. Cash Rp1.98 bn. Plus related-party LT loan from SAI Rp950 bn. EBIT derived as Gross Profit 27 - Opex 57 = -Rp30 bn (operating loss).
A45: PT Jaya Agra Wattie Tbk | B45: 2023 | C45: 896 | D45: -16 | F45: -73 | G45: -304 | H45: -302 | I45: 3656 | J45: 272 | K45: 3385 | L45: 2675 | M45: 602 | N45: 2073 | O45: 982 | P45: =IFERROR(J45-M45,"") | Q45: 7.03 | R45: 1964 | S45: =IFERROR(R45-Q45,"") | T45: -121 | U45: 81 | V45: =IFERROR(T45-U45,"") | W45: 16233 | X45: -59 | Y45: 60 | Z45: 0 | AA45: 0 | AB45: 180 | AC45: =IFERROR(W45*AB45/1000,"") | AD45: =IFERROR(J45/M45,"") | AE45: =IFERROR(R45/I45,"") | AF45: =IFERROR(R45/O45,"") | AG45: =IFERROR(G45/I45,"") | AH45: =IFERROR(G45/O45,"") | AI45: =IFERROR(G45/C45,"") | AJ45: =IFERROR(D45/C45,"") | AO45: 117 | AP45: =IFERROR(IF(AND(NOT(ISNUMBER(F45)),NOT(ISNUMBER(AO45))),"",F45+AO45),"") | AQ45: =IFERROR(IF(OR(NOT(ISNUMBER(E45)),NOT(ISNUMBER(AP45))),"",E45-AP45),"") | AS45: =IFERROR(IF(OR(NOT(ISNUMBER(AR45)),NOT(ISNUMBER(S45))),"",AR45-S45),"") | AT45: Gross bank debt = Rp125 bn ST + Rp1,838.76 bn LT (incl current portion Rp228.5 bn) = Rp1,963.76 bn. Cash Rp7.03 bn. Plus related-party LT loan from SAI Rp417 bn (post 22 Nov 2023 Rp1.25 tn debt-to-equity conversion).
A46: PT Jaya Agra Wattie Tbk | B46: 2024 | C46: 1071 | D46: 110 | F46: 51 | G46: -194 | H46: -193 | I46: 3868 | J46: 532 | K46: 3336 | L46: 2502 | M46: 533 | N46: 1968 | O46: 1366 | P46: =IFERROR(J46-M46,"") | Q46: 5.85 | R46: 995 | S46: =IFERROR(R46-Q46,"") | T46: -179 | U46: 87 | V46: =IFERROR(T46-U46,"") | W46: 16233 | X46: -12 | Y46: 84 | Z46: 0 | AA46: 0 | AB46: 110 | AC46: =IFERROR(W46*AB46/1000,"") | AD46: =IFERROR(J46/M46,"") | AE46: =IFERROR(R46/I46,"") | AF46: =IFERROR(R46/O46,"") | AG46: =IFERROR(G46/I46,"") | AH46: =IFERROR(G46/O46,"") | AI46: =IFERROR(G46/C46,"") | AJ46: =IFERROR(D46/C46,"") | AO46: 108 | AP46: =IFERROR(IF(AND(NOT(ISNUMBER(F46)),NOT(ISNUMBER(AO46))),"",F46+AO46),"") | AQ46: =IFERROR(IF(OR(NOT(ISNUMBER(E46)),NOT(ISNUMBER(AP46))),"",E46-AP46),"") | AS46: =IFERROR(IF(OR(NOT(ISNUMBER(AR46)),NOT(ISNUMBER(S46))),"",AR46-S46),"") | AT46: Gross bank debt = Rp85 bn ST + Rp910 bn LT (incl current portion Rp145 bn) = Rp995 bn; plus zero-interest related-party loan from SAI Rp1,158 bn LT. Cash Rp5.85 bn. Net debt (bank only) ~Rp989 bn.
A47: PT Perusahaan Perkebunan London Sumatra Indonesia Tbk | B47: 2022 | C47: 4585 | D47: 1491 | E47: 1747 | F47: 1206 | G47: 1035 | H47: 1036 | I47: 12417 | J47: 5107 | K47: 7310 | L47: 1481 | M47: 710 | N47: 772 | O47: 10936 | P47: =IFERROR(J47-M47,"") | Q47: 3847 | R47: 0 | S47: =IFERROR(R47-Q47,"") | T47: 1087 | U47: 321 | V47: =IFERROR(T47-U47,"") | W47: 6820 | X47: 152 | Y47: 1603 | AA47: 51 | AB47: 1015 | AC47: =IFERROR(W47*AB47/1000,"") | AD47: =IFERROR(J47/M47,"") | AE47: =IFERROR(R47/I47,"") | AF47: =IFERROR(R47/O47,"") | AG47: =IFERROR(G47/I47,"") | AH47: =IFERROR(G47/O47,"") | AI47: =IFERROR(G47/C47,"") | AJ47: =IFERROR(D47/C47,"") | AP47: =IFERROR(IF(AND(NOT(ISNUMBER(F47)),NOT(ISNUMBER(AO47))),"",F47+AO47),"") | AQ47: =IFERROR(IF(OR(NOT(ISNUMBER(E47)),NOT(ISNUMBER(AP47))),"",E47-AP47),"") | AR47: -3847 | AS47: =IFERROR(IF(OR(NOT(ISNUMBER(AR47)),NOT(ISNUMBER(S47))),"",AR47-S47),"") | AT47: Zero bank debt (Funded Debt - per Financial Highlights). Net gearing -0.35x. Market cap Rp6.92tn at 31 Dec 2022.
A48: PT Perusahaan Perkebunan London Sumatra Indonesia Tbk | B48: 2023 | C48: 4190 | D48: 1151 | E48: 1301 | F48: 759 | G48: 761 | H48: 762 | I48: 12514 | J48: 5377 | K48: 7137 | L48: 1167 | M48: 564 | N48: 602 | O48: 11347 | P48: =IFERROR(J48-M48,"") | Q48: 4511 | R48: 0 | S48: =IFERROR(R48-Q48,"") | T48: 1411 | U48: 369 | V48: =IFERROR(T48-U48,"") | W48: 6820 | X48: 112 | Y48: 1664 | AA48: 53 | AB48: 890 | AC48: =IFERROR(W48*AB48/1000,"") | AD48: =IFERROR(J48/M48,"") | AE48: =IFERROR(R48/I48,"") | AF48: =IFERROR(R48/O48,"") | AG48: =IFERROR(G48/I48,"") | AH48: =IFERROR(G48/O48,"") | AI48: =IFERROR(G48/C48,"") | AJ48: =IFERROR(D48/C48,"") | AP48: =IFERROR(IF(AND(NOT(ISNUMBER(F48)),NOT(ISNUMBER(AO48))),"",F48+AO48),"") | AQ48: =IFERROR(IF(OR(NOT(ISNUMBER(E48)),NOT(ISNUMBER(AP48))),"",E48-AP48),"") | AR48: -4511 | AS48: =IFERROR(IF(OR(NOT(ISNUMBER(AR48)),NOT(ISNUMBER(S48))),"",AR48-S48),"") | AT48: Zero bank debt (Funded Debt - per Financial Highlights). Net gearing -0.40x in 2023. Market cap Rp6.07tn at 31 Dec 2023.
A49: PT Perusahaan Perkebunan London Sumatra Indonesia Tbk | B49: 2024 | C49: 4563 | D49: 1992 | E49: 2099 | F49: 1551 | G49: 1476 | H49: 1477 | I49: 13842 | J49: 7117 | K49: 6725 | L49: 1285 | M49: 678 | N49: 607 | O49: 12557 | P49: =IFERROR(J49-M49,"") | Q49: 5454 | R49: 0 | S49: =IFERROR(R49-Q49,"") | T49: 1565 | U49: 376 | V49: =IFERROR(T49-U49,"") | W49: 6820 | X49: 217 | Y49: 1841 | AA49: 39 | AB49: 975 | AC49: =IFERROR(W49*AB49/1000,"") | AD49: =IFERROR(J49/M49,"") | AE49: =IFERROR(R49/I49,"") | AF49: =IFERROR(R49/O49,"") | AG49: =IFERROR(G49/I49,"") | AH49: =IFERROR(G49/O49,"") | AI49: =IFERROR(G49/C49,"") | AJ49: =IFERROR(D49/C49,"") | AP49: =IFERROR(IF(AND(NOT(ISNUMBER(F49)),NOT(ISNUMBER(AO49))),"",F49+AO49),"") | AQ49: =IFERROR(IF(OR(NOT(ISNUMBER(E49)),NOT(ISNUMBER(AP49))),"",E49-AP49),"") | AR49: -5454 | AS49: =IFERROR(IF(OR(NOT(ISNUMBER(AR49)),NOT(ISNUMBER(S49))),"",AR49-S49),"") | AT49: Zero bank debt (Funded Debt - in Financial Highlights). Net debt = -cash = -Rp5,454 bn. Reported Net Gearing ratio -0.43x in 2024. Market cap Rp6.65 trillion at 31 Dec 2024.
A50: PT Multi Agro Gemilang Plantation Tbk | B50: 2022 | C50: 32.27 | D50: -3.43 | F50: -4.31 | G50: -10.68 | H50: -10.57 | I50: 840.19 | J50: 205.92 | K50: 634.27 | L50: 764.27 | M50: 645.96 | N50: 118.3 | O50: 75.92 | P50: =IFERROR(J50-M50,"") | Q50: 2.38 | R50: 358.71 | S50: =IFERROR(R50-Q50,"") | T50: 1.62 | U50: 0 | V50: =IFERROR(T50-U50,"") | W50: 9000 | X50: -1.17 | AC50: =IFERROR(W50*AB50/1000,"") | AD50: =IFERROR(J50/M50,"") | AE50: =IFERROR(R50/I50,"") | AF50: =IFERROR(R50/O50,"") | AG50: =IFERROR(G50/I50,"") | AH50: =IFERROR(G50/O50,"") | AI50: =IFERROR(G50/C50,"") | AJ50: =IFERROR(D50/C50,"") | AP50: =IFERROR(IF(AND(NOT(ISNUMBER(F50)),NOT(ISNUMBER(AO50))),"",F50+AO50),"") | AQ50: =IFERROR(IF(OR(NOT(ISNUMBER(E50)),NOT(ISNUMBER(AP50))),"",E50-AP50),"") | AR50: 356.33 | AS50: =IFERROR(IF(OR(NOT(ISNUMBER(AR50)),NOT(ISNUMBER(S50))),"",AR50-S50),"") | AT50: Note: Cached file is Q1 2022 interim. Gross debt = ST bank loans 240.91 + finance lease current 9.90 + finance lease LT 107.89 = 358.70 bn
A51: PT Mahkota Group Tbk | B51: 2022 | C51: 7505.7 | D51: 728.61 | F51: 100.54 | G51: -34.79 | H51: -20.1 | I51: 2561.66 | J51: 1429.23 | K51: 1132.43 | L51: 1916.29 | M51: 1423.46 | N51: 492.83 | O51: 645.37 | P51: =IFERROR(J51-M51,"") | Q51: 457.6 | R51: 1657.9 | S51: =IFERROR(R51-Q51,"") | T51: -285.73 | U51: 124.96 | V51: =IFERROR(T51-U51,"") | W51: 3554.45 | X51: -5.69 | AB51: 845 | AC51: =IFERROR(W51*AB51/1000,"") | AD51: =IFERROR(J51/M51,"") | AE51: =IFERROR(R51/I51,"") | AF51: =IFERROR(R51/O51,"") | AG51: =IFERROR(G51/I51,"") | AH51: =IFERROR(G51/O51,"") | AI51: =IFERROR(G51/C51,"") | AJ51: =IFERROR(D51/C51,"") | AP51: =IFERROR(IF(AND(NOT(ISNUMBER(F51)),NOT(ISNUMBER(AO51))),"",F51+AO51),"") | AQ51: =IFERROR(IF(OR(NOT(ISNUMBER(E51)),NOT(ISNUMBER(AP51))),"",E51-AP51),"") | AS51: =IFERROR(IF(OR(NOT(ISNUMBER(AR51)),NOT(ISNUMBER(S51))),"",AR51-S51),"") | AT51: Gross debt = ST bank loans 1,084.69 + LT bank loans current 145.46 + LT bank loans non-current 337.76 + MTN non-current 90.00 = Rp1,657.90 bn. Net debt = 1,657.90 - Cash 457.60 = Rp1,200.30 bn. DER 296.93%.
A52: PT Mahkota Group Tbk | B52: 2023 | C52: 5425.48 | D52: 257.35 | F52: -43.9 | G52: -172.27 | H52: -152.23 | I52: 2680.2 | J52: 1425.67 | K52: 1254.53 | L52: 2159.14 | M52: 1693.11 | N52: 466.02 | O52: 521.06 | P52: =IFERROR(J52-M52,"") | Q52: 421.27 | R52: 1916.95 | S52: =IFERROR(R52-Q52,"") | T52: 309.79 | U52: 180.81 | V52: =IFERROR(T52-U52,"") | W52: 3554.45 | X52: -43.12 | AB52: 705 | AC52: =IFERROR(W52*AB52/1000,"") | AD52: =IFERROR(J52/M52,"") | AE52: =IFERROR(R52/I52,"") | AF52: =IFERROR(R52/O52,"") | AG52: =IFERROR(G52/I52,"") | AH52: =IFERROR(G52/O52,"") | AI52: =IFERROR(G52/C52,"") | AJ52: =IFERROR(D52/C52,"") | AP52: =IFERROR(IF(AND(NOT(ISNUMBER(F52)),NOT(ISNUMBER(AO52))),"",F52+AO52),"") | AQ52: =IFERROR(IF(OR(NOT(ISNUMBER(E52)),NOT(ISNUMBER(AP52))),"",E52-AP52),"") | AS52: =IFERROR(IF(OR(NOT(ISNUMBER(AR52)),NOT(ISNUMBER(S52))),"",AR52-S52),"") | AT52: Gross debt = ST bank loans 1,425.05 + LT bank loans current 88.55 + LT bank loans non-current 313.35 + MTN non-current 90.00 = Rp1,916.95 bn. Net debt = 1,916.95 - (Cash 421.27 + Restricted cash 305.87) = Rp1,189.81 bn. DER 414.37%.
A53: PT Mahkota Group Tbk | B53: 2024 | C53: 4685.75 | D53: 352.54 | F53: 68.71 | G53: -22.98 | H53: -20.85 | I53: 3073.81 | J53: 1576.71 | K53: 1497.1 | L53: 2568.91 | M53: 1811.73 | N53: 757.18 | O53: 504.89 | P53: =IFERROR(J53-M53,"") | Q53: 276.1 | R53: 2310 | S53: =IFERROR(R53-Q53,"") | T53: -38.01 | U53: 319.07 | V53: =IFERROR(T53-U53,"") | W53: 3554.45 | X53: -5.91 | AB53: 695 | AC53: =IFERROR(W53*AB53/1000,"") | AD53: =IFERROR(J53/M53,"") | AE53: =IFERROR(R53/I53,"") | AF53: =IFERROR(R53/O53,"") | AG53: =IFERROR(G53/I53,"") | AH53: =IFERROR(G53/O53,"") | AI53: =IFERROR(G53/C53,"") | AJ53: =IFERROR(D53/C53,"") | AP53: =IFERROR(IF(AND(NOT(ISNUMBER(F53)),NOT(ISNUMBER(AO53))),"",F53+AO53),"") | AQ53: =IFERROR(IF(OR(NOT(ISNUMBER(E53)),NOT(ISNUMBER(AP53))),"",E53-AP53),"") | AS53: =IFERROR(IF(OR(NOT(ISNUMBER(AR53)),NOT(ISNUMBER(S53))),"",AR53-S53),"") | AT53: Gross debt = ST bank loans 1,357.81 + LT bank loans current portion 166.10 + LT bank loans non-current 696.08 + MTN current 90.00 = Rp2,310 bn. Net debt = 2,310 - (Cash 276.10 + Restricted cash 476.75) = Rp1,557 bn. DER 508.80%.
A54: PT Menthobi Karyatama Raya Tbk | B54: 2022 | C54: 627.88 | D54: 174.19 | F54: 115.15 | G54: 61.88 | H54: 61.52 | I54: 966.24 | J54: 460.45 | K54: 505.79 | L54: 422.83 | M54: 211.34 | N54: 211.49 | O54: 543.41 | P54: =IFERROR(J54-M54,"") | Q54: 303.67 | R54: 352.67 | S54: =IFERROR(R54-Q54,"") | T54: 89.26 | V54: =IFERROR(T54-U54,"") | W54: 12000 | X54: 6.2 | AB54: 129 | AC54: =IFERROR(W54*AB54/1000,"") | AD54: =IFERROR(J54/M54,"") | AE54: =IFERROR(R54/I54,"") | AF54: =IFERROR(R54/O54,"") | AG54: =IFERROR(G54/I54,"") | AH54: =IFERROR(G54/O54,"") | AI54: =IFERROR(G54/C54,"") | AJ54: =IFERROR(D54/C54,"") | AP54: =IFERROR(IF(AND(NOT(ISNUMBER(F54)),NOT(ISNUMBER(AO54))),"",F54+AO54),"") | AQ54: =IFERROR(IF(OR(NOT(ISNUMBER(E54)),NOT(ISNUMBER(AP54))),"",E54-AP54),"") | AS54: =IFERROR(IF(OR(NOT(ISNUMBER(AR54)),NOT(ISNUMBER(S54))),"",AR54-S54),"") | AT54: Gross debt = ST bank loans 65 + current LT 80.59 + LT 207.07 = Rp352.67 bn. Net debt = 352.67 - 303.67 = Rp49.00 bn. Very low gearing post-IPO.
A55: PT Menthobi Karyatama Raya Tbk | B55: 2023 | C55: 710.98 | D55: 125.75 | F55: 62.68 | G55: 51.38 | H55: 51.24 | I55: 1331.79 | J55: 538.02 | K55: 793.78 | L55: 747.32 | M55: 166.15 | N55: 581.17 | O55: 584.48 | P55: =IFERROR(J55-M55,"") | Q55: 188.24 | R55: 662.84 | S55: =IFERROR(R55-Q55,"") | T55: 16.58 | U55: 371.81 | V55: =IFERROR(T55-U55,"") | W55: 12000.1 | X55: 4.27 | AB55: 150 | AC55: =IFERROR(W55*AB55/1000,"") | AD55: =IFERROR(J55/M55,"") | AE55: =IFERROR(R55/I55,"") | AF55: =IFERROR(R55/O55,"") | AG55: =IFERROR(G55/I55,"") | AH55: =IFERROR(G55/O55,"") | AI55: =IFERROR(G55/C55,"") | AJ55: =IFERROR(D55/C55,"") | AP55: =IFERROR(IF(AND(NOT(ISNUMBER(F55)),NOT(ISNUMBER(AO55))),"",F55+AO55),"") | AQ55: =IFERROR(IF(OR(NOT(ISNUMBER(E55)),NOT(ISNUMBER(AP55))),"",E55-AP55),"") | AS55: =IFERROR(IF(OR(NOT(ISNUMBER(AR55)),NOT(ISNUMBER(S55))),"",AR55-S55),"") | AT55: Gross debt = ST bank loans 27.99 + current portion LT 63.07 + LT 571.78 = Rp662.84 bn. Net debt = 662.84 - 188.24 = Rp474.60 bn. Gearing (Liab/Equity) 127.86%.
A56: PT Menthobi Karyatama Raya Tbk | B56: 2024 | C56: 1006.86 | D56: 179.43 | F56: 106.39 | G56: 52.25 | H56: 52.04 | I56: 1518.44 | J56: 668.76 | K56: 849.68 | L56: 889.1 | M56: 171.44 | N56: 717.66 | O56: 629.34 | P56: =IFERROR(J56-M56,"") | Q56: 164.52 | R56: 798.72 | S56: =IFERROR(R56-Q56,"") | T56: 114.33 | U56: 70.82 | V56: =IFERROR(T56-U56,"") | W56: 12052.4 | X56: 4.33 | AA56: 1 | AB56: 120 | AC56: =IFERROR(W56*AB56/1000,"") | AD56: =IFERROR(J56/M56,"") | AE56: =IFERROR(R56/I56,"") | AF56: =IFERROR(R56/O56,"") | AG56: =IFERROR(G56/I56,"") | AH56: =IFERROR(G56/O56,"") | AI56: =IFERROR(G56/C56,"") | AJ56: =IFERROR(D56/C56,"") | AP56: =IFERROR(IF(AND(NOT(ISNUMBER(F56)),NOT(ISNUMBER(AO56))),"",F56+AO56),"") | AQ56: =IFERROR(IF(OR(NOT(ISNUMBER(E56)),NOT(ISNUMBER(AP56))),"",E56-AP56),"") | AS56: =IFERROR(IF(OR(NOT(ISNUMBER(AR56)),NOT(ISNUMBER(S56))),"",AR56-S56),"") | AT56: Gross debt = short-term bank loans 20.0 + current portion LT bank loans 68.93 + LT bank loans 709.79 = Rp798.72 bn. Net debt = 798.72 - 164.52 = Rp634.20 bn. Gearing ratio (Liab/Equity) 141.28%.
A57: PT Nusantara Sawit Sejahtera Tbk | B57: 2022 | C57: 1134 | D57: 406 | F57: 313.18 | G57: 70 | H57: 70 | I57: 3035 | J57: 331 | K57: 2705 | L57: 2405 | M57: 337 | N57: 2068 | O57: 630 | P57: =IFERROR(J57-M57,"") | Q57: 40 | R57: 2104.6 | S57: =IFERROR(R57-Q57,"") | T57: 47 | U57: 103.49 | V57: =IFERROR(T57-U57,"") | W57: 20220 | X57: 3.47 | AC57: =IFERROR(W57*AB57/1000,"") | AD57: =IFERROR(J57/M57,"") | AE57: =IFERROR(R57/I57,"") | AF57: =IFERROR(R57/O57,"") | AG57: =IFERROR(G57/I57,"") | AH57: =IFERROR(G57/O57,"") | AI57: =IFERROR(G57/C57,"") | AJ57: =IFERROR(D57/C57,"") | AP57: =IFERROR(IF(AND(NOT(ISNUMBER(F57)),NOT(ISNUMBER(AO57))),"",F57+AO57),"") | AQ57: =IFERROR(IF(OR(NOT(ISNUMBER(E57)),NOT(ISNUMBER(AP57))),"",E57-AP57),"") | AS57: =IFERROR(IF(OR(NOT(ISNUMBER(AR57)),NOT(ISNUMBER(S57))),"",AR57-S57),"") | AT57: Debt-to-Equity 381.7%; Debt-to-Assets 79.2%. Very leveraged pre-IPO.
A58: PT Nusantara Sawit Sejahtera Tbk | B58: 2023 | C58: 1185 | D58: 303 | F58: 202.81 | G58: 2 | H58: 2 | I58: 3672 | J58: 636 | K58: 3037 | L58: 2611 | M58: 678 | N58: 1933 | O58: 1061 | P58: =IFERROR(J58-M58,"") | Q58: 243 | R58: 2110.01 | S58: =IFERROR(R58-Q58,"") | T58: 136 | U58: 329.88 | V58: =IFERROR(T58-U58,"") | W58: 23789 | X58: 0.09 | AB58: 177 | AC58: =IFERROR(W58*AB58/1000,"") | AD58: =IFERROR(J58/M58,"") | AE58: =IFERROR(R58/I58,"") | AF58: =IFERROR(R58/O58,"") | AG58: =IFERROR(G58/I58,"") | AH58: =IFERROR(G58/O58,"") | AI58: =IFERROR(G58/C58,"") | AJ58: =IFERROR(D58/C58,"") | AP58: =IFERROR(IF(AND(NOT(ISNUMBER(F58)),NOT(ISNUMBER(AO58))),"",F58+AO58),"") | AQ58: =IFERROR(IF(OR(NOT(ISNUMBER(E58)),NOT(ISNUMBER(AP58))),"",E58-AP58),"") | AS58: =IFERROR(IF(OR(NOT(ISNUMBER(AR58)),NOT(ISNUMBER(S58))),"",AR58-S58),"") | AT58: Debt-to-Equity 246.06%; Debt-to-Assets 71.10%; net debt excludes lease etc.
A59: PT Nusantara Sawit Sejahtera Tbk | B59: 2024 | C59: 1490 | D59: 585 | G59: 305 | H59: 305 | I59: 3728 | J59: 720 | K59: 3008 | L59: 2363 | M59: 627 | N59: 1735 | O59: 1365 | P59: =IFERROR(J59-M59,"") | Q59: 386 | S59: =IFERROR(R59-Q59,"") | T59: 438 | U59: 75 | V59: =IFERROR(T59-U59,"") | W59: 23802 | X59: 12.8 | AB59: 276 | AC59: =IFERROR(W59*AB59/1000,"") | AD59: =IFERROR(J59/M59,"") | AE59: =IFERROR(R59/I59,"") | AF59: =IFERROR(R59/O59,"") | AG59: =IFERROR(G59/I59,"") | AH59: =IFERROR(G59/O59,"") | AI59: =IFERROR(G59/C59,"") | AJ59: =IFERROR(D59/C59,"") | AP59: =IFERROR(IF(AND(NOT(ISNUMBER(F59)),NOT(ISNUMBER(AO59))),"",F59+AO59),"") | AQ59: =IFERROR(IF(OR(NOT(ISNUMBER(E59)),NOT(ISNUMBER(AP59))),"",E59-AP59),"") | AS59: =IFERROR(IF(OR(NOT(ISNUMBER(AR59)),NOT(ISNUMBER(S59))),"",AR59-S59),"") | AT59: Debt-to-Equity 173.08%, Debt-to-Assets 63.38%; long-term bank debt decreased 10% YoY; bank debt payments of Rp357,627 mn in 2024.
A60: PT Indo Oil Perkasa Tbk | B60: 2022 | C60: 514.2 | D60: 44.14 | F60: 15.18 | G60: 6.82 | H60: 6.82 | I60: 157.98 | J60: 118.48 | K60: 39.5 | L60: 75.19 | M60: 67.98 | N60: 7.22 | O60: 82.79 | P60: =IFERROR(J60-M60,"") | Q60: 7.96 | R60: 51.36 | S60: =IFERROR(R60-Q60,"") | T60: 18.87 | U60: 27.22 | V60: =IFERROR(T60-U60,"") | W60: 454.06 | X60: 15.02 | Y60: 182 | AB60: 218 | AC60: =IFERROR(W60*AB60/1000,"") | AD60: =IFERROR(J60/M60,"") | AE60: =IFERROR(R60/I60,"") | AF60: =IFERROR(R60/O60,"") | AG60: =IFERROR(G60/I60,"") | AH60: =IFERROR(G60/O60,"") | AI60: =IFERROR(G60/C60,"") | AJ60: =IFERROR(D60/C60,"") | AP60: =IFERROR(IF(AND(NOT(ISNUMBER(F60)),NOT(ISNUMBER(AO60))),"",F60+AO60),"") | AQ60: =IFERROR(IF(OR(NOT(ISNUMBER(E60)),NOT(ISNUMBER(AP60))),"",E60-AP60),"") | AS60: =IFERROR(IF(OR(NOT(ISNUMBER(AR60)),NOT(ISNUMBER(S60))),"",AR60-S60),"") | AT60: Gross debt = ST bank 43.65 + current LT bank 1.75 + LT bank 5.69 = Rp51.09 bn (approx) per 2023 AR reconciliation. Net debt = 51.09 - 7.96 = Rp43.13 bn. Debt-to-equity ratio 0.91x.
A61: PT Indo Oil Perkasa Tbk | B61: 2023 | C61: 600.35 | D61: 35.92 | F61: 11.25 | G61: 3.13 | H61: 3.13 | I61: 199.91 | J61: 136.07 | K61: 63.84 | L61: 115.42 | M61: 103.76 | N61: 11.66 | O61: 84.49 | P61: =IFERROR(J61-M61,"") | Q61: 7.91 | R61: 80.8 | S61: =IFERROR(R61-Q61,"") | T61: -11.95 | U61: 14.37 | V61: =IFERROR(T61-U61,"") | W61: 454.06 | X61: 6.89 | Y61: 186 | AB61: 133 | AC61: =IFERROR(W61*AB61/1000,"") | AD61: =IFERROR(J61/M61,"") | AE61: =IFERROR(R61/I61,"") | AF61: =IFERROR(R61/O61,"") | AG61: =IFERROR(G61/I61,"") | AH61: =IFERROR(G61/O61,"") | AI61: =IFERROR(G61/C61,"") | AJ61: =IFERROR(D61/C61,"") | AP61: =IFERROR(IF(AND(NOT(ISNUMBER(F61)),NOT(ISNUMBER(AO61))),"",F61+AO61),"") | AQ61: =IFERROR(IF(OR(NOT(ISNUMBER(E61)),NOT(ISNUMBER(AP61))),"",E61-AP61),"") | AS61: =IFERROR(IF(OR(NOT(ISNUMBER(AR61)),NOT(ISNUMBER(S61))),"",AR61-S61),"") | AT61: Gross debt = ST bank 73.95 + current LT bank 2.11 + LT bank 4.74 = Rp80.80 bn. Net debt = 80.80 - 7.91 = Rp72.89 bn. Excludes lease liabilities. Debt-to-equity ratio 1.37x.
A62: PT Indo Oil Perkasa Tbk | B62: 2024 | C62: 634.38 | D62: 45.26 | F62: 16.51 | G62: 6.35 | H62: 6.35 | I62: 219.17 | J62: 147.96 | K62: 71.21 | L62: 128.36 | M62: 123.59 | N62: 4.77 | O62: 90.81 | P62: =IFERROR(J62-M62,"") | Q62: 9.77 | R62: 86.87 | S62: =IFERROR(R62-Q62,"") | T62: 13.17 | U62: 6.69 | V62: =IFERROR(T62-U62,"") | W62: 454.06 | X62: 13.98 | Y62: 200 | AB62: 98 | AC62: =IFERROR(W62*AB62/1000,"") | AD62: =IFERROR(J62/M62,"") | AE62: =IFERROR(R62/I62,"") | AF62: =IFERROR(R62/O62,"") | AG62: =IFERROR(G62/I62,"") | AH62: =IFERROR(G62/O62,"") | AI62: =IFERROR(G62/C62,"") | AJ62: =IFERROR(D62/C62,"") | AP62: =IFERROR(IF(AND(NOT(ISNUMBER(F62)),NOT(ISNUMBER(AO62))),"",F62+AO62),"") | AQ62: =IFERROR(IF(OR(NOT(ISNUMBER(E62)),NOT(ISNUMBER(AP62))),"",E62-AP62),"") | AS62: =IFERROR(IF(OR(NOT(ISNUMBER(AR62)),NOT(ISNUMBER(S62))),"",AR62-S62),"") | AT62: Gross debt = ST bank loans 82.12 + current portion LT bank 2.63 + LT bank 2.11 = Rp86.87 bn. Net debt = 86.87 - 9.77 = Rp77.10 bn. Excludes lease liabilities and consumer financing.
A63: PT Pradiksi Gunatama Tbk | B63: 2022 | C63: 1007.31 | D63: 264.42 | F63: 233.64 | G63: 167.25 | H63: 172.15 | I63: 2347.52 | J63: 289.998 | K63: 2057.52 | L63: 918.35 | M63: 197.37 | N63: 720.98 | O63: 1429.17 | P63: =IFERROR(J63-M63,"") | Q63: 35.9 | R63: 692.08 | S63: =IFERROR(R63-Q63,"") | T63: 213.08 | U63: 77.07 | V63: =IFERROR(T63-U63,"") | W63: 5737.85 | X63: 30 | Y63: 249 | AB63: 805 | AC63: =IFERROR(W63*AB63/1000,"") | AD63: =IFERROR(J63/M63,"") | AE63: =IFERROR(R63/I63,"") | AF63: =IFERROR(R63/O63,"") | AG63: =IFERROR(G63/I63,"") | AH63: =IFERROR(G63/O63,"") | AI63: =IFERROR(G63/C63,"") | AJ63: =IFERROR(D63/C63,"") | AO63: 0 | AP63: =IFERROR(IF(AND(NOT(ISNUMBER(F63)),NOT(ISNUMBER(AO63))),"",F63+AO63),"") | AQ63: =IFERROR(IF(OR(NOT(ISNUMBER(E63)),NOT(ISNUMBER(AP63))),"",E63-AP63),"") | AR63: 656.18 | AS63: =IFERROR(IF(OR(NOT(ISNUMBER(AR63)),NOT(ISNUMBER(S63))),"",AR63-S63),"") | AT63: Net debt = Bank loans (BRI) Rp692.08 bn (current Rp122.98 + LT Rp569.10, net of Rp5.52 bn unamortized cost) - Cash Rp35.90 bn = Rp656.18 bn.
A64: PT Pradiksi Gunatama Tbk | B64: 2023 | C64: 868.46 | D64: 246.07 | F64: 191.94 | G64: 108.06 | H64: 108.06 | I64: 2591.48 | J64: 290.91 | K64: 2300.56 | L64: 965.4 | M64: 161.57 | N64: 803.83 | O64: 1626.07 | P64: =IFERROR(J64-M64,"") | Q64: 75.59 | R64: 569.84 | S64: =IFERROR(R64-Q64,"") | T64: 355.18 | U64: 353.38 | V64: =IFERROR(T64-U64,"") | W64: 5737.85 | X64: 18.83 | Y64: 283 | AB64: 424 | AC64: =IFERROR(W64*AB64/1000,"") | AD64: =IFERROR(J64/M64,"") | AE64: =IFERROR(R64/I64,"") | AF64: =IFERROR(R64/O64,"") | AG64: =IFERROR(G64/I64,"") | AH64: =IFERROR(G64/O64,"") | AI64: =IFERROR(G64/C64,"") | AJ64: =IFERROR(D64/C64,"") | AO64: 50.95 | AP64: =IFERROR(IF(AND(NOT(ISNUMBER(F64)),NOT(ISNUMBER(AO64))),"",F64+AO64),"") | AQ64: =IFERROR(IF(OR(NOT(ISNUMBER(E64)),NOT(ISNUMBER(AP64))),"",E64-AP64),"") | AR64: 494.25 | AS64: =IFERROR(IF(OR(NOT(ISNUMBER(AR64)),NOT(ISNUMBER(S64))),"",AR64-S64),"") | AT64: Net debt = Bank loans (BRI) Rp569.84 bn (net of unamortized arrangement cost Rp4.77 bn) - Cash Rp75.59 bn = Rp494.25 bn.
A65: PT Pradiksi Gunatama Tbk | B65: 2024 | C65: 738.57 | D65: 204.97 | F65: 150.69 | G65: 79.18 | H65: 79.18 | I65: 2639.2 | J65: 367.88 | K65: 2271.32 | L65: 846.25 | M65: 211.18 | N65: 635.07 | O65: 1792.95 | P65: =IFERROR(J65-M65,"") | Q65: 14.23 | R65: 488.72 | S65: =IFERROR(R65-Q65,"") | T65: 111.43 | U65: 39.46 | V65: =IFERROR(T65-U65,"") | W65: 5737.85 | X65: 13.8 | Y65: 312 | AB65: 424 | AC65: =IFERROR(W65*AB65/1000,"") | AD65: =IFERROR(J65/M65,"") | AE65: =IFERROR(R65/I65,"") | AF65: =IFERROR(R65/O65,"") | AG65: =IFERROR(G65/I65,"") | AH65: =IFERROR(G65/O65,"") | AI65: =IFERROR(G65/C65,"") | AJ65: =IFERROR(D65/C65,"") | AO65: 54.49 | AP65: =IFERROR(IF(AND(NOT(ISNUMBER(F65)),NOT(ISNUMBER(AO65))),"",F65+AO65),"") | AQ65: =IFERROR(IF(OR(NOT(ISNUMBER(E65)),NOT(ISNUMBER(AP65))),"",E65-AP65),"") | AR65: 474.49 | AS65: =IFERROR(IF(OR(NOT(ISNUMBER(AR65)),NOT(ISNUMBER(S65))),"",AR65-S65),"") | AT65: Net debt = Bank loans (BRI) Rp488.72 bn (net of Rp3.97 bn unamortized arrangement cost) less Cash Rp14.23 bn = Rp474.49 bn. No other interest-bearing debt. Also Rp100.37 bn interest-bearing related-party payable to PT Araya Agro Lestari (LT) excluded from bank debt.
A66: PT Pinago Utama Tbk | B66: 2022 | C66: 2034 | D66: 529 | F66: 317 | G66: 173 | H66: 173 | I66: 1551 | J66: 496 | K66: 1054 | L66: 842 | M66: 337 | N66: 505 | O66: 708 | P66: =IFERROR(J66-M66,"") | Q66: 72 | R66: 685 | S66: =IFERROR(R66-Q66,"") | T66: 200 | U66: 65 | V66: =IFERROR(T66-U66,"") | W66: 781 | X66: 222 | Y66: 907 | Z66: 50 | AA66: 70 | AB66: 1400 | AC66: =IFERROR(W66*AB66/1000,"") | AD66: =IFERROR(J66/M66,"") | AE66: =IFERROR(R66/I66,"") | AF66: =IFERROR(R66/O66,"") | AG66: =IFERROR(G66/I66,"") | AH66: =IFERROR(G66/O66,"") | AI66: =IFERROR(G66/C66,"") | AJ66: =IFERROR(D66/C66,"") | AP66: =IFERROR(IF(AND(NOT(ISNUMBER(F66)),NOT(ISNUMBER(AO66))),"",F66+AO66),"") | AQ66: =IFERROR(IF(OR(NOT(ISNUMBER(E66)),NOT(ISNUMBER(AP66))),"",E66-AP66),"") | AS66: =IFERROR(IF(OR(NOT(ISNUMBER(AR66)),NOT(ISNUMBER(S66))),"",AR66-S66),"") | AT66: Gross bank debt = ST bank loans 154.70 + current portion LT bank 90.83 + LT bank 439.09 = Rp684.62 bn. Cash Rp72.20 bn. Net bank debt ~Rp612.4 bn. Debt-to-equity 1.18.
A67: PT Pinago Utama Tbk | B67: 2023 | C67: 2037 | D67: 503 | F67: 291 | G67: 192 | H67: 191 | I67: 1489 | J67: 341 | K67: 1148 | L67: 692 | M67: 273 | N67: 420 | O67: 797 | P67: =IFERROR(J67-M67,"") | Q67: 29 | R67: 536 | S67: =IFERROR(R67-Q67,"") | T67: 364 | U67: 153 | V67: =IFERROR(T67-U67,"") | W67: 781 | X67: 245 | Y67: 1020 | Z67: 70 | AA67: 60 | AB67: 1400 | AC67: =IFERROR(W67*AB67/1000,"") | AD67: =IFERROR(J67/M67,"") | AE67: =IFERROR(R67/I67,"") | AF67: =IFERROR(R67/O67,"") | AG67: =IFERROR(G67/I67,"") | AH67: =IFERROR(G67/O67,"") | AI67: =IFERROR(G67/C67,"") | AJ67: =IFERROR(D67/C67,"") | AP67: =IFERROR(IF(AND(NOT(ISNUMBER(F67)),NOT(ISNUMBER(AO67))),"",F67+AO67),"") | AQ67: =IFERROR(IF(OR(NOT(ISNUMBER(E67)),NOT(ISNUMBER(AP67))),"",E67-AP67),"") | AS67: =IFERROR(IF(OR(NOT(ISNUMBER(AR67)),NOT(ISNUMBER(S67))),"",AR67-S67),"") | AT67: Gross bank debt = ST bank loans 99.10 + current portion LT bank 90.83 + LT bank 345.68 = Rp535.62 bn. Cash Rp28.71 bn. Net bank debt ~Rp506.9 bn. Debt-to-equity 0.87.
A68: PT Pinago Utama Tbk | B68: 2024 | C68: 2043 | D68: 537 | F68: 333 | G68: 221 | H68: 220 | I68: 1764 | J68: 502 | K68: 1262 | L68: 798 | M68: 489 | N68: 309 | O68: 966 | P68: =IFERROR(J68-M68,"") | Q68: 22 | R68: 590 | S68: =IFERROR(R68-Q68,"") | T68: 157 | U68: 157 | V68: =IFERROR(T68-U68,"") | W68: 781 | X68: 282 | Y68: 1236 | Z68: 40 | AA68: 52 | AB68: 1610 | AC68: =IFERROR(W68*AB68/1000,"") | AD68: =IFERROR(J68/M68,"") | AE68: =IFERROR(R68/I68,"") | AF68: =IFERROR(R68/O68,"") | AG68: =IFERROR(G68/I68,"") | AH68: =IFERROR(G68/O68,"") | AI68: =IFERROR(G68/C68,"") | AJ68: =IFERROR(D68/C68,"") | AP68: =IFERROR(IF(AND(NOT(ISNUMBER(F68)),NOT(ISNUMBER(AO68))),"",F68+AO68),"") | AQ68: =IFERROR(IF(OR(NOT(ISNUMBER(E68)),NOT(ISNUMBER(AP68))),"",E68-AP68),"") | AR68: 775 | AS68: =IFERROR(IF(OR(NOT(ISNUMBER(AR68)),NOT(ISNUMBER(S68))),"",AR68-S68),"") | AT68: Gross bank debt = ST bank loans 270.48 + current portion LT bank 110.83 + LT bank 208.42 = Rp589.74 bn. Net debt per AR p.92 = Total liabilities Rp797.87 bn - Cash Rp22.38 bn = Rp775.49 bn. DER 0.83.
A69: PT Pulau Subur Tbk | B69: 2023 | C69: 61.66 | D69: 34.5 | E69: 35.34 | F69: 32.78 | G69: 26.19 | H69: 26.19 | I69: 168.91 | J69: 100.32 | K69: 68.59 | L69: 6.18 | M69: 5.76 | N69: 0.42 | O69: 162.74 | P69: =IFERROR(J69-M69,"") | Q69: 74.98 | R69: 1.88 | S69: =IFERROR(R69-Q69,"") | T69: 17.26 | U69: 10.45 | V69: =IFERROR(T69-U69,"") | W69: 2167.5 | X69: 12.08 | Y69: 75.08 | AB69: 152 | AC69: =IFERROR(W69*AB69/1000,"") | AD69: =IFERROR(J69/M69,"") | AE69: =IFERROR(R69/I69,"") | AF69: =IFERROR(R69/O69,"") | AG69: =IFERROR(G69/I69,"") | AH69: =IFERROR(G69/O69,"") | AI69: =IFERROR(G69/C69,"") | AJ69: =IFERROR(D69/C69,"") | AP69: =IFERROR(IF(AND(NOT(ISNUMBER(F69)),NOT(ISNUMBER(AO69))),"",F69+AO69),"") | AQ69: =IFERROR(IF(OR(NOT(ISNUMBER(E69)),NOT(ISNUMBER(AP69))),"",E69-AP69),"") | AS69: =IFERROR(IF(OR(NOT(ISNUMBER(AR69)),NOT(ISNUMBER(S69))),"",AR69-S69),"") | AT69: Gearing ratio 3.79% (Liab/Equity). Gross debt = bank loan current maturity Rp1.88 bn (fully repaid in 2024). Net debt = 1.88 - 74.98 = strongly negative (net cash Rp73.1 bn) after IPO.
A70: PT Pulau Subur Tbk | B70: 2024 | C70: 63.58 | D70: 36.35 | E70: 36.88 | F70: 32.96 | G70: 27.13 | H70: 27.13 | I70: 190.56 | J70: 77.36 | K70: 113.2 | L70: 5.41 | M70: 3.97 | N70: 1.45 | O70: 185.15 | P70: =IFERROR(J70-M70,"") | Q70: 64.21 | R70: 1.01 | S70: =IFERROR(R70-Q70,"") | T70: 29.22 | U70: 44.6 | V70: =IFERROR(T70-U70,"") | W70: 2167.5 | X70: 12.52 | Y70: 85.42 | AA70: 2.2 | AB70: 77 | AC70: =IFERROR(W70*AB70/1000,"") | AD70: =IFERROR(J70/M70,"") | AE70: =IFERROR(R70/I70,"") | AF70: =IFERROR(R70/O70,"") | AG70: =IFERROR(G70/I70,"") | AH70: =IFERROR(G70/O70,"") | AI70: =IFERROR(G70/C70,"") | AJ70: =IFERROR(D70/C70,"") | AP70: =IFERROR(IF(AND(NOT(ISNUMBER(F70)),NOT(ISNUMBER(AO70))),"",F70+AO70),"") | AQ70: =IFERROR(IF(OR(NOT(ISNUMBER(E70)),NOT(ISNUMBER(AP70))),"",E70-AP70),"") | AS70: =IFERROR(IF(OR(NOT(ISNUMBER(AR70)),NOT(ISNUMBER(S70))),"",AR70-S70),"") | AT70: Gearing (Liab/Equity) 2.92%. Gross debt = lease liability Rp1.006 bn (2024 new vehicle lease); no bank debt at end-2024 (Rp1.88 bn bank loan fully repaid during year). Net debt = 1.01 - 64.21 = negative (net cash Rp63.2 bn).
A71: PT Sampoerna Agro Tbk | B71: 2022 | C71: 5672 | D71: 1984 | E71: 2162 | F71: 1619 | G71: 1039 | H71: 1050 | I71: 10243 | J71: 1800 | K71: 8443 | L71: 5013 | M71: 1361 | N71: 3652 | O71: 5230 | P71: =IFERROR(J71-M71,"") | Q71: 535 | R71: 3082 | S71: =IFERROR(R71-Q71,"") | T71: 1254 | U71: 404 | V71: =IFERROR(T71-U71,"") | W71: 1819 | X71: 577 | Y71: 2805 | Z71: 90 | AA71: 135 | AB71: 2100 | AC71: =IFERROR(W71*AB71/1000,"") | AD71: =IFERROR(J71/M71,"") | AE71: =IFERROR(R71/I71,"") | AF71: =IFERROR(R71/O71,"") | AG71: =IFERROR(G71/I71,"") | AH71: =IFERROR(G71/O71,"") | AI71: =IFERROR(G71/C71,"") | AJ71: =IFERROR(D71/C71,"") | AP71: =IFERROR(IF(AND(NOT(ISNUMBER(F71)),NOT(ISNUMBER(AO71))),"",F71+AO71),"") | AQ71: =IFERROR(IF(OR(NOT(ISNUMBER(E71)),NOT(ISNUMBER(AP71))),"",E71-AP71),"") | AS71: =IFERROR(IF(OR(NOT(ISNUMBER(AR71)),NOT(ISNUMBER(S71))),"",AR71-S71),"") | AT71: Gearing 69.2% (debt/equity) - reported. Gross debt = bonds (208+785=993) + sukuk (175+823=998) + bank loans (94+997=1091) = Rp3,082 bn. Net debt = 3,082 - 535 cash = Rp2,547 bn. Interest-bearing debt/total assets 35.3%. Note: DPS of Rp135 final (from 2021 profit) + Rp90 interim (from 2022 profit) = Rp225 paid in 2022.
A72: PT Sampoerna Agro Tbk | B72: 2023 | C72: 5621 | D72: 1327 | F72: 937 | G72: 441 | H72: 484 | I72: 10068 | J72: 1616 | K72: 8452 | L72: 4555 | M72: 1310 | N72: 3245 | O72: 5512 | P72: =IFERROR(J72-M72,"") | Q72: 536 | R72: 2837 | S72: =IFERROR(R72-Q72,"") | T72: 1423 | U72: 553 | V72: =IFERROR(T72-U72,"") | W72: 1819 | X72: 266 | Y72: 3031 | AA72: 288 | AB72: 2010 | AC72: =IFERROR(W72*AB72/1000,"") | AD72: =IFERROR(J72/M72,"") | AE72: =IFERROR(R72/I72,"") | AF72: =IFERROR(R72/O72,"") | AG72: =IFERROR(G72/I72,"") | AH72: =IFERROR(G72/O72,"") | AI72: =IFERROR(G72/C72,"") | AJ72: =IFERROR(D72/C72,"") | AP72: =IFERROR(IF(AND(NOT(ISNUMBER(F72)),NOT(ISNUMBER(AO72))),"",F72+AO72),"") | AQ72: =IFERROR(IF(OR(NOT(ISNUMBER(E72)),NOT(ISNUMBER(AP72))),"",E72-AP72),"") | AS72: =IFERROR(IF(OR(NOT(ISNUMBER(AR72)),NOT(ISNUMBER(S72))),"",AR72-S72),"") | AT72: Gearing 58.0% (debt/equity) - reported. Gross debt = bonds (127+660=787) + sukuk (237+587=824) + bank loans (138+1089=1226) = Rp2,837 bn. Net debt = 2,837 - 536 cash = Rp2,301 bn. Interest-bearing debt/total assets 31.8%.
A73: PT Sampoerna Agro Tbk | B73: 2024 | C73: 5694 | D73: 1601 | F73: 1264 | G73: 697 | H73: 749 | I73: 10702 | J73: 2225 | K73: 8478 | L73: 4492 | M73: 1760 | N73: 2732 | O73: 6210 | P73: =IFERROR(J73-M73,"") | Q73: 841 | R73: 2882 | S73: =IFERROR(R73-Q73,"") | T73: 1256 | U73: 437 | V73: =IFERROR(T73-U73,"") | W73: 1819 | X73: 412 | Y73: 3415 | AA73: 121 | AB73: 2140 | AC73: =IFERROR(W73*AB73/1000,"") | AD73: =IFERROR(J73/M73,"") | AE73: =IFERROR(R73/I73,"") | AF73: =IFERROR(R73/O73,"") | AG73: =IFERROR(G73/I73,"") | AH73: =IFERROR(G73/O73,"") | AI73: =IFERROR(G73/C73,"") | AJ73: =IFERROR(D73/C73,"") | AP73: =IFERROR(IF(AND(NOT(ISNUMBER(F73)),NOT(ISNUMBER(AO73))),"",F73+AO73),"") | AQ73: =IFERROR(IF(OR(NOT(ISNUMBER(E73)),NOT(ISNUMBER(AP73))),"",E73-AP73),"") | AS73: =IFERROR(IF(OR(NOT(ISNUMBER(AR73)),NOT(ISNUMBER(S73))),"",AR73-S73),"") | AT73: Gearing 49.5% (debt/equity) - reported. Gross debt = bonds (166+495=661) + sukuk (200+388=588) + bank loans (208+1425=1633) = Rp2,882 bn. Net debt = 2,882 - 841 cash = Rp2,041 bn. Interest-bearing debt/total assets 28.7%.
A74: PT Salim Ivomas Pratama Tbk | B74: 2022 | C74: 17794 | D74: 4649 | E74: 4684 | F74: 2920 | G74: 1510 | H74: 1198 | I74: 36113 | J74: 10443 | K74: 25670 | L74: 14946 | M74: 9461 | N74: 5485 | O74: 21167 | P74: =IFERROR(J74-M74,"") | Q74: 4297 | R74: 9871 | S74: =IFERROR(R74-Q74,"") | T74: 3596 | U74: 1460 | V74: =IFERROR(T74-U74,"") | W74: 15501 | X74: 77 | Y74: 1086 | AA74: 13 | AB74: 414 | AC74: =IFERROR(W74*AB74/1000,"") | AD74: =IFERROR(J74/M74,"") | AE74: =IFERROR(R74/I74,"") | AF74: =IFERROR(R74/O74,"") | AG74: =IFERROR(G74/I74,"") | AH74: =IFERROR(G74/O74,"") | AI74: =IFERROR(G74/C74,"") | AJ74: =IFERROR(D74/C74,"") | AP74: =IFERROR(IF(AND(NOT(ISNUMBER(F74)),NOT(ISNUMBER(AO74))),"",F74+AO74),"") | AQ74: =IFERROR(IF(OR(NOT(ISNUMBER(E74)),NOT(ISNUMBER(AP74))),"",E74-AP74),"") | AS74: =IFERROR(IF(OR(NOT(ISNUMBER(AR74)),NOT(ISNUMBER(S74))),"",AR74-S74),"") | AT74: Funded Debt Rp9,871.38 bn = ST bank loans 5,870.00 + current portion LT bank loans 824.24 + LT bank loans 1,837.53 + lease 46.77+123.04 + shareholder loan 1,461.50 + others. Cash & equivalents Rp4,296.67 bn. Gearing - Gross 0.47x; Gearing - Net 0.26x (FY22).
A75: PT Salim Ivomas Pratama Tbk | B75: 2023 | C75: 16003 | D75: 3358 | E75: 3535 | F75: 1930 | G75: 927 | H75: 736 | I75: 35012 | J75: 9897 | K75: 25115 | L75: 13291 | M75: 9411 | N75: 3880 | O75: 21721 | P75: =IFERROR(J75-M75,"") | Q75: 5161 | R75: 8693 | S75: =IFERROR(R75-Q75,"") | T75: 3830 | U75: 1324 | V75: =IFERROR(T75-U75,"") | W75: 15501 | X75: 48 | Y75: 1119 | AA75: 15 | AB75: 376 | AC75: =IFERROR(W75*AB75/1000,"") | AD75: =IFERROR(J75/M75,"") | AE75: =IFERROR(R75/I75,"") | AF75: =IFERROR(R75/O75,"") | AG75: =IFERROR(G75/I75,"") | AH75: =IFERROR(G75/O75,"") | AI75: =IFERROR(G75/C75,"") | AJ75: =IFERROR(D75/C75,"") | AP75: =IFERROR(IF(AND(NOT(ISNUMBER(F75)),NOT(ISNUMBER(AO75))),"",F75+AO75),"") | AQ75: =IFERROR(IF(OR(NOT(ISNUMBER(E75)),NOT(ISNUMBER(AP75))),"",E75-AP75),"") | AS75: =IFERROR(IF(OR(NOT(ISNUMBER(AR75)),NOT(ISNUMBER(S75))),"",AR75-S75),"") | AT75: Funded Debt Rp8,692.67 bn = ST bank loans 5,649.00 + current portion LT bank loans 1,294.25 + LT bank loans 852.81 + lease 41.06+89.48 + shareholder loan 1,071.47 + others. Cash & equivalents Rp5,161.18 bn. Gearing - Gross 0.40x; Gearing - Net 0.16x (FY23).
A76: PT Salim Ivomas Pratama Tbk | B76: 2024 | C76: 15968 | D76: 4838 | E76: 4731 | F76: 3302 | G76: 2184 | H76: 1550 | I76: 37248 | J76: 13233 | K76: 24015 | L76: 13260 | M76: 8769 | N76: 4491 | O76: 23987 | P76: =IFERROR(J76-M76,"") | Q76: 5752 | R76: 8400 | S76: =IFERROR(R76-Q76,"") | T76: 2300 | U76: 1264 | V76: =IFERROR(T76-U76,"") | W76: 15501 | X76: 100 | Y76: 1208 | AA76: 10 | AB76: 378 | AC76: =IFERROR(W76*AB76/1000,"") | AD76: =IFERROR(J76/M76,"") | AE76: =IFERROR(R76/I76,"") | AF76: =IFERROR(R76/O76,"") | AG76: =IFERROR(G76/I76,"") | AH76: =IFERROR(G76/O76,"") | AI76: =IFERROR(G76/C76,"") | AJ76: =IFERROR(D76/C76,"") | AP76: =IFERROR(IF(AND(NOT(ISNUMBER(F76)),NOT(ISNUMBER(AO76))),"",F76+AO76),"") | AQ76: =IFERROR(IF(OR(NOT(ISNUMBER(E76)),NOT(ISNUMBER(AP76))),"",E76-AP76),"") | AS76: =IFERROR(IF(OR(NOT(ISNUMBER(AR76)),NOT(ISNUMBER(S76))),"",AR76-S76),"") | AT76: Funded Debt Rp8,400.39 bn = ST bank loans 5,843.94 + current portion LT bank loans 237.41 + LT bank loans 1,689.90 + lease 39.58+63.61 + shareholder loan 772.34. Cash & equivalents Rp5,752.38 bn. Gearing - Gross 0.35x; Gearing - Net 0.11x (FY24).
A77: PT Sinar Mas Agro Resources and Technology Tbk | B77: 2022 | C77: 75046 | D77: 13312 | E77: 9531 | F77: 6601 | G77: 5505 | H77: 5501 | I77: 42601 | J77: 23709 | K77: 18892 | L77: 23353 | M77: 12105 | N77: 11248 | O77: 19248 | P77: =IFERROR(J77-M77,"") | Q77: 2480 | R77: 18168 | S77: =IFERROR(R77-Q77,"") | T77: 4283 | U77: 1279 | V77: =IFERROR(T77-U77,"") | W77: 2872 | X77: 1915 | Y77: 6698 | Z77: 200 | AA77: 370 | AB77: 4950 | AC77: =IFERROR(W77*AB77/1000,"") | AD77: =IFERROR(J77/M77,"") | AE77: =IFERROR(R77/I77,"") | AF77: =IFERROR(R77/O77,"") | AG77: =IFERROR(G77/I77,"") | AH77: =IFERROR(G77/O77,"") | AI77: =IFERROR(G77/C77,"") | AJ77: =IFERROR(D77/C77,"") | AP77: =IFERROR(IF(AND(NOT(ISNUMBER(F77)),NOT(ISNUMBER(AO77))),"",F77+AO77),"") | AQ77: =IFERROR(IF(OR(NOT(ISNUMBER(E77)),NOT(ISNUMBER(AP77))),"",E77-AP77),"") | AS77: =IFERROR(IF(OR(NOT(ISNUMBER(AR77)),NOT(ISNUMBER(S77))),"",AR77-S77),"") | AT77: Net debt to EBITDA 0.02x (exceptionally low given record profits). Gross debt = ST bank 3,798 + LT bank current 2,478 + bonds current 1,546 + LT bank 4,289 + bonds LT 6,056 = Rp18,167 bn. Gearing (debt to equity) improved to 0.95x from 1.37x.
A78: PT Sinar Mas Agro Resources and Technology Tbk | B78: 2023 | C78: 66531 | D78: 6761 | E78: 3799 | F78: 1483 | G78: 918 | H78: 918 | I78: 39716 | J78: 19141 | K78: 20575 | L78: 20644 | M78: 10225 | N78: 10419 | O78: 19072 | P78: =IFERROR(J78-M78,"") | Q78: 1642 | R78: 16007 | S78: =IFERROR(R78-Q78,"") | T78: 4038 | U78: 1847 | V78: =IFERROR(T78-U78,"") | W78: 2872 | X78: 320 | Y78: 6637 | Z78: 95 | AA78: 370 | AB78: 4000 | AC78: =IFERROR(W78*AB78/1000,"") | AD78: =IFERROR(J78/M78,"") | AE78: =IFERROR(R78/I78,"") | AF78: =IFERROR(R78/O78,"") | AG78: =IFERROR(G78/I78,"") | AH78: =IFERROR(G78/O78,"") | AI78: =IFERROR(G78/C78,"") | AJ78: =IFERROR(D78/C78,"") | AP78: =IFERROR(IF(AND(NOT(ISNUMBER(F78)),NOT(ISNUMBER(AO78))),"",F78+AO78),"") | AQ78: =IFERROR(IF(OR(NOT(ISNUMBER(E78)),NOT(ISNUMBER(AP78))),"",E78-AP78),"") | AS78: =IFERROR(IF(OR(NOT(ISNUMBER(AR78)),NOT(ISNUMBER(S78))),"",AR78-S78),"") | AT78: Net debt to EBITDA 0.65x (2022: 0.02x). Gross debt = ST bank 2,923 + LT bank current 1,581 + bonds current 2,043 + LT bank 5,440 + bonds LT 4,022 = Rp16,008 bn. Gearing reported 0.84x (debt to equity).
A79: PT Sinar Mas Agro Resources and Technology Tbk | B79: 2024 | C79: 78835 | D79: 8014 | E79: 4209 | F79: 2025 | G79: 1278 | H79: 1278 | I79: 45333 | J79: 24442 | K79: 20892 | L79: 25450 | M79: 13371 | N79: 12079 | O79: 19883 | P79: =IFERROR(J79-M79,"") | Q79: 1586 | R79: 19199 | S79: =IFERROR(R79-Q79,"") | T79: -253 | U79: 2270 | V79: =IFERROR(T79-U79,"") | W79: 2872 | X79: 445 | Y79: 6917 | Z79: 105 | AB79: 3650 | AC79: =IFERROR(W79*AB79/1000,"") | AD79: =IFERROR(J79/M79,"") | AE79: =IFERROR(R79/I79,"") | AF79: =IFERROR(R79/O79,"") | AG79: =IFERROR(G79/I79,"") | AH79: =IFERROR(G79/O79,"") | AI79: =IFERROR(G79/C79,"") | AJ79: =IFERROR(D79/C79,"") | AP79: =IFERROR(IF(AND(NOT(ISNUMBER(F79)),NOT(ISNUMBER(AO79))),"",F79+AO79),"") | AQ79: =IFERROR(IF(OR(NOT(ISNUMBER(E79)),NOT(ISNUMBER(AP79))),"",E79-AP79),"") | AS79: =IFERROR(IF(OR(NOT(ISNUMBER(AR79)),NOT(ISNUMBER(S79))),"",AR79-S79),"") | AT79: Net debt to EBITDA 0.59x per MD&A (2023: 0.65x). Gross debt = ST bank 5,134 + LT bank current 1,108 + LT bank 8,930 + bonds current 1,876 + bonds LT 2,150 = Rp19,198 bn. Gearing (debt to equity) reported 0.97x.
A80: PT Sawit Sumbermas Sarana Tbk | B80: 2023 | C80: 10703 | D80: 2799 | F80: 1196 | G80: 344 | H80: 512 | I80: 11810 | J80: 5028 | K80: 6782 | L80: 9820 | M80: 4755 | N80: 5066 | O80: 1990 | P80: =IFERROR(J80-M80,"") | Q80: 1237 | R80: 8102 | S80: =IFERROR(R80-Q80,"") | T80: 624 | U80: 103 | V80: =IFERROR(T80-U80,"") | W80: 9525 | X80: 53.78 | Y80: 184 | Z80: 0 | AA80: 149.28 | AB80: 1045 | AC80: =IFERROR(W80*AB80/1000,"") | AD80: =IFERROR(J80/M80,"") | AE80: =IFERROR(R80/I80,"") | AF80: =IFERROR(R80/O80,"") | AG80: =IFERROR(G80/I80,"") | AH80: =IFERROR(G80/O80,"") | AI80: =IFERROR(G80/C80,"") | AJ80: =IFERROR(D80/C80,"") | AP80: =IFERROR(IF(AND(NOT(ISNUMBER(F80)),NOT(ISNUMBER(AO80))),"",F80+AO80),"") | AQ80: =IFERROR(IF(OR(NOT(ISNUMBER(E80)),NOT(ISNUMBER(AP80))),"",E80-AP80),"") | AS80: =IFERROR(IF(OR(NOT(ISNUMBER(AR80)),NOT(ISNUMBER(S80))),"",AR80-S80),"") | AT80: Gross debt = ST bank loan 2,437 + Current LT bank loan 898 + LT bank loan 4,767 = Rp8,102 bn (Rp633 bn bonds fully repaid in 2023). Net debt ≈ 8,102 - 1,237 cash = Rp6,865 bn. Interest-bearing debt to equity ratio 4.11x. FY2022 dividend Rp1,421.97 bn (Rp149.28/share) paid 8 Jun 2023, 77% payout. FY2023 profit NOT distributed as dividend (allocated to retained earnings).
A81: PT Sawit Sumbermas Sarana Tbk | B81: 2024 | C81: 10522 | D81: 3280 | F81: 1770 | G81: 845 | H81: 820 | I81: 11765 | J81: 5232 | K81: 6533 | L81: 8873 | M81: 4716 | N81: 4157 | O81: 2891 | P81: =IFERROR(J81-M81,"") | Q81: 1180 | R81: 6985 | S81: =IFERROR(R81-Q81,"") | T81: 607 | U81: 19 | V81: =IFERROR(T81-U81,"") | W81: 9525 | X81: 86.04 | Y81: 276 | Z81: 0 | AA81: 0 | AB81: 1300 | AC81: =IFERROR(W81*AB81/1000,"") | AD81: =IFERROR(J81/M81,"") | AE81: =IFERROR(R81/I81,"") | AF81: =IFERROR(R81/O81,"") | AG81: =IFERROR(G81/I81,"") | AH81: =IFERROR(G81/O81,"") | AI81: =IFERROR(G81/C81,"") | AJ81: =IFERROR(D81/C81,"") | AP81: =IFERROR(IF(AND(NOT(ISNUMBER(F81)),NOT(ISNUMBER(AO81))),"",F81+AO81),"") | AQ81: =IFERROR(IF(OR(NOT(ISNUMBER(E81)),NOT(ISNUMBER(AP81))),"",E81-AP81),"") | AS81: =IFERROR(IF(OR(NOT(ISNUMBER(AR81)),NOT(ISNUMBER(S81))),"",AR81-S81),"") | AT81: Interest-bearing debt to equity ratio 2.45x (2024) vs 4.11x (2023). Gross debt = Short-term bank loan 2,195 + Current LT bank loan 989 + LT bank loan 3,801 = Rp6,985 bn; Net debt ≈ 6,985 - 1,180 cash = Rp5,805 bn. No cash dividend paid for FY2023 (retained); FY2024 dividend not declared in this AR. Realized capex Rp19 bn (infrastructure 2 + land 12 + vehicles 4). No net_profit YoY proforma adj; pre-proforma also Rp845 bn.
A82: PT Sawit Sumbermas Sarana Tbk | B82: 2025 | C82: 14813.17 | D82: 5174.93 | F82: 2548.24 | G82: 1392.63 | H82: 1161 | I82: 13584.22 | J82: 5901 | K82: 7683 | L82: 10642.51 | M82: 4613 | N82: 6029 | O82: 2941.7 | P82: =IFERROR(J82-M82,"") | Q82: 874.06 | R82: 8139 | S82: =IFERROR(R82-Q82,"") | T82: 1097 | U82: 402 | V82: =IFERROR(T82-U82,"") | W82: 9525 | X82: 121.86 | Y82: 239 | Z82: 0 | AA82: 47.24 | AB82: 1580 | AC82: =IFERROR(W82*AB82/1000,"") | AD82: =IFERROR(J82/M82,"") | AE82: =IFERROR(R82/I82,"") | AF82: =IFERROR(R82/O82,"") | AG82: =IFERROR(G82/I82,"") | AH82: =IFERROR(G82/O82,"") | AI82: =IFERROR(G82/C82,"") | AJ82: =IFERROR(D82/C82,"") | AP82: =IFERROR(IF(AND(NOT(ISNUMBER(F82)),NOT(ISNUMBER(AO82))),"",F82+AO82),"") | AQ82: =IFERROR(IF(OR(NOT(ISNUMBER(E82)),NOT(ISNUMBER(AP82))),"",E82-AP82),"") | AS82: =IFERROR(IF(OR(NOT(ISNUMBER(AR82)),NOT(ISNUMBER(S82))),"",AR82-S82),"") | AT82: Gross debt = ST bank loan 1,698 + Current LT bank loan 991 + LT bank loan 5,450 = Rp8,139 bn. Net debt ≈ 8,139 - 874 cash = Rp7,265 bn. DER 361.88%. Capex from CF: Acquisitions of fixed assets Rp402 bn (2024: Rp230 bn). SML acquisition consumed Rp1,491 bn cash. FY2024 dividend paid in 2025 = Rp450 bn (Rp47.24/share). Syndicated bank loan facility obtained in 2025 for funding structure.
